Workbook
Name data_amt: Данные!$D$2:$D$341
Name data_cat: Данные!$C$2:$C$341
Name data_dir: Данные!$E$2:$E$341
Name data_item: Данные!$B$2:$B$341

Sheet Данные
A1: Дата | B1: Статья | C1: Категория | D1: Сумма | E1: Направление | F1: Проект | G1: Примечание | H1: Кол-во | I1: Цена | J1: Срок | K1: Флаг | L1: Доля | M1: Вес | N1: Код | O1: Остаток
A2: 45870 | B2: Сырьё 4 | C2: Кат-06 | D2: 390525.48 | E2: расход | F2: П11 | G2: 'с кавычкой | H2: 99 | I2: 4552.71 | J2: 45700 | K2: TRUE | L2: 0.154 | M2: 4.891439 | N2: K67369 | O2: -105380.68
A3: 45939 | B3: Доход 2 | C3: Кат-12 | D3: -78635.15 | E3: расход | F3: П05 | G3: 25% | H3: 65 | I3: 5460.82 | J3: 46102 | K3: TRUE | L3: 0.77 | M3: 9.94534 | N3: K239333 | O3: 257001.29
A4: 45698 | B4: Налог 1 | C4: Кат-15 | D4: 24606.32 | E4: расход | F4: П02 | G4: 25% | H4: 4 | I4: 6222.2 | J4: 46109 | K4: FALSE | L4: 0.402 | M4: 3.0237285 | N4: K677214 | O4: 452631.44
A5: 46011 | B5: Доход 4 | C5: Кат-03 | D5: 317210.93 | E5: приход | F5: П14 | G5: 25% | H5: 88 | I5: 5100.59 | J5: 46270 | K5: FALSE | L5: 0.949 | M5: 1.3192058 | N5: K977882 | O5: -336987.18
A6: 45781 | B6: Налог 3 | C6: Кат-11 | D6: 62162.46 | E6: расход | F6: П02 | H6: 85 | I6: 2727.87 | J6: 45773 | K6: TRUE | L6: 0.144 | M6: 6.5457657 | N6: K549060 | O6: -175382.91
A7: 45692 | B7: Доход 3 | C7: Кат-14 | D7: 50413.46 | E7: приход | F7: П08 | G7: он сказал "да" | H7: 21 | I7: 7921.98 | J7: 46018 | K7: FALSE | L7: 0.004 | M7: 1.8297106 | N7: K28350 | O7: 484251.44
A8: 45768 | B8: Чай 2 | C8: Кат-18 | D8: -53073.73 | E8: расход | F8: П12 | G8: 25% | H8: 9 | I8: 1491.37 | J8: 45847 | K8: FALSE | L8: 0.312 | M8: 9.0910573 | N8: K861756 | O8: 132972.16
A9: 45907 | B9: Сырьё 1 | C9: Кат-06 | D9: 53759.45 | E9: расход | F9: П15 | G9: TRUE | H9: 32 | I9: 766.57 | J9: 45941 | K9: TRUE | L9: 0.148 | M9: 8.2118014 | N9: K307948 | O9: 392440.7
A10: 45850 | B10: Сырье 1 | C10: Кат-11 | D10: 72419.45 | E10: расход | F10: П12 | G10: =1+1 | H10: 20 | I10: 6317.22 | J10: 46032 | K10: TRUE | L10: 0.872 | M10: 6.4881417 | N10: K358758 | O10: -145403.93
A11: 45870 | B11: Ёлка 3 | C11: Кат-13 | D11: 170040.1 | E11: приход | F11: П02 | H11: 14 | I11: 7105.7 | J11: 45878 | K11: FALSE | L11: 0.926 | M11: 0.72140963 | N11: K110150 | O11: -326665.79
A12: 45902 | B12: Чаи 4 | C12: Кат-06 | D12: 89894.04 | E12: приход | F12: П15 | G12: пробелы | H12: 1 | I12: 8608.17 | J12: 45795 | K12: FALSE | L12: 0.385 | M12: 7.1257513 | N12: K134502 | O12: -215782.98
A13: 46009 | B13: Налог 1 | C13: Кат-13 | D13: -78781.56 | E13: приход | F13: П03 | G13: путь\к\файлу | H13: 61 | I13: 192.13 | J13: 45669 | K13: FALSE | L13: 0.653 | M13: 7.9840452 | N13: K644748 | O13: 174135.62
A14: 45992 | B14: Чаи 1 | C14: Кат-17 | D14: 359716.92 | E14: расход | F14: П09 | G14: 2025-01-01 | H14: 10 | I14: 836.13 | J14: 46143 | K14: FALSE | L14: 0.551 | M14: 6.861817 | N14: K861061 | O14: -3102.43
A15: 45932 | B15: Сырьё 1 | C15: Кат-18 | D15: 267685.09 | E15: расход | F15: П02 | G15: TRUE | H15: 70 | I15: 337.33 | J15: 46366 | K15: FALSE | L15: 0.85 | M15: 6.2798565 | N15: K468277 | O15: 98538.37
A16: 45814 | B16: Связь 3 | C16: Кат-01 | D16: 369197.94 | E16: расход | F16: П09 | G16: TRUE | H16: 15 | I16: 9543.86 | J16: 45671 | K16: TRUE | L16: 0.976 | M16: 6.3044936 | N16: K479752 | O16: -497254.49
A17: 45870 | B17: Доход 1 | C17: Кат-13 | D17: 386326.05 | E17: расход | F17: П09 | G17: он сказал "да" | H17: 40 | I17: 6149.58 | J17: 46320 | K17: TRUE | L17: 0.759 | M17: 7.1544776 | N17: K241962 | O17: -340589.31
A18: 45972 | B18: Связь 3 | C18: Кат-09 | D18: 153637.47 | E18: приход | F18: П12 | G18: путь\к\файлу | H18: 77 | I18: 1237.9 | J18: 45952 | K18: TRUE | L18: 0.319 | M18: 7.4562634 | N18: K34119 | O18: -265488.29
A19: 45666 | B19: Налог 2 | C19: Кат-14 | D19: 58052.64 | E19: приход | F19: П10 | G19: обычный текст | H19: 66 | I19: 4704.15 | J19: 45803 | K19: TRUE | L19: 0.91 | M19: 9.9669643 | N19: K607536 | O19: -302362.17
A20: 45887 | B20: Аренда 2 | C20: Кат-19 | D20: 353981.07 | E20: приход | F20: П07 | G20: 25% | H20: 1 | I20: 5034.99 | J20: 45939 | K20: FALSE | L20: 0.906 | M20: 4.2413345 | N20: K187445 | O20: 54272.46
A21: 45849 | B21: Чай 3 | C21: Кат-10 | D21: 225608.62 | E21: приход | F21: П07 | G21: TRUE | H21: 55 | I21: 374.9 | J21: 46158 | K21: TRUE | L21: 0.139 | M21: 2.7454624 | N21: K306175 | O21: -209049.39
A22: 45886 | B22: Налог 1 | C22: Кат-16 | D22: 94760.89 | E22: расход | F22: П04 | G22: 'с кавычкой | H22: 0 | I22: 1456.39 | J22: 45897 | K22: TRUE | L22: 0.608 | M22: 5.1767241 | N22: K403984 | O22: -108032.77
A23: 45674 | B23: Чаи 1 | C23: Кат-07 | D23: 150225.98 | E23: приход | F23: П10 | G23: пробелы | H23: 91 | I23: 4846.2 | J23: 46174 | K23: TRUE | L23: 0.928 | M23: 0.49381798 | N23: K346466 | O23: 338797.34
... A29: 45891 | B29: Елка 3 | C29: Кат-01 | D29: 1.2814733e+09 | E29: приход | F29: П01 | G29: обычный текст | H29: 7 | I29: 8906.24 | J29: 45779 | K29: FALSE | L29: 0.684 | M29: 8.6563913 | N29: K922157 | O29: -427031.58
A30: 45980 | B30: Ёлка 1 | C30: Кат-17 | D30: 57068.59 | E30: приход | F30: П11 | H30: 29 | I30: 4044.33 | J30: 46330 | K30: FALSE | L30: 0.09 | M30: 5.5685139 | N30: K359871 | O30: -335017.2
A31: 45694 | B31: Связь 1 | C31: Кат-19 | D31: 178192.36 | E31: приход | F31: П01 | G31: 'с кавычкой | H31: 20 | I31: 3442.57 | J31: 45896 | K31: FALSE | L31: 0.231 | M31: 7.8811559 | N31: K554589 | O31: -252598.89
A32: 45963 | B32: Связь 2 | C32: Кат-17 | D32: -68844.6 | E32: расход | F32: П05 | G32: 2025-01-01 | H32: 44 | I32: 3839.67 | J32: 46194 | K32: FALSE | L32: 0.712 | M32: 0.58203895 | N32: K444788 | O32: -79740.38
A33: 45832 | B33: Сырьё 4 | C33: Кат-15 | D33: 6434.18 | E33: расход | F33: П03 | G33: пробелы | H33: 2 | I33: 4684.49 | J33: 45871 | K33: FALSE | L33: 0.125 | M33: 1.2359374 | N33: K340369 | O33: -54374.87
A34: 45765 | B34: Чай 2 | C34: Кат-14 | D34: -29513.86 | E34: расход | F34: П08 | G34: 'с кавычкой | H34: 99 | I34: 7570.22 | J34: 45995 | K34: TRUE | L34: 0.537 | M34: 5.6520037 | N34: K593825 | O34: -399106.66
A35: 45796 | B35: Чай 3 | C35: Кат-15 | D35: 72144.07 | E35: расход | F35: П10 | G35: пробелы | H35: 75 | I35: 7469.7 | J35: 45984 | K35: TRUE | L35: 0.333 | M35: 8.0419463 | N35: K938352 | O35: 412030.36
A36: 45681 | B36: Связь 1 | C36: Кат-09 | D36: 97614.39 | E36: приход | F36: П04 | G36: он сказал "да" | H36: 97 | I36: 5474.36 | J36: 46006 | K36: FALSE | L36: 0.016 | M36: 7.8039018 | N36: K811663 | O36: 280714.95
A37: 46017 | B37: Доход 3 | C37: Кат-10 | D37: -83837.23 | E37: расход | F37: П09 | G37: путь\к\файлу | H37: 17 | I37: 7465.77 | J37: 45846 | K37: TRUE | L37: 0.384 | M37: 1.0216789 | N37: K35817 | O37: -94126.92
A38: 45675 | B38: Сырьё 2 | C38: Кат-18 | D38: 48723.82 | E38: расход | F38: П15 | G38: 2025-01-01 | H38: 37 | I38: 5043.61 | J38: 45794 | K38: TRUE | L38: 0.496 | M38: 1.1926085 | N38: K275953 | O38: 65603.62
A39: 45662 | B39: Аренда 2 | C39: Кат-01 | D39: 204895.21 | E39: расход | F39: П01 | G39: =1+1 | H39: 85 | I39: 1817.91 | J39: 45917 | K39: FALSE | L39: 0.223 | M39: 6.8138124 | N39: K347378 | O39: 456608.53
A40: 45937 | B40: Чай 2 | C40: Кат-14 | D40: 66279.71 | E40: приход | F40: П04 | G40: пробелы | H40: 43 | I40: 3039.5 | J40: 46274 | K40: FALSE | L40: 0.99 | M40: 6.9203224 | N40: K78757 | O40: 158731.17
A41: 45761 | B41: Чай 3 | C41: Кат-09 | D41: 392435.78 | E41: расход | F41: П02 | G41: 'с кавычкой | H41: 80 | I41: 9538.15 | J41: 45877 | K41: FALSE | L41: 0.128 | M41: 0.77584809 | N41: K584645 | O41: -380913.54
A42: 45878 | B42: Аренда 2 | C42: Кат-15 | D42: 74328.45 | E42: расход | F42: П09 | G42: обычный текст | H42: 99 | I42: 2614.22 | J42: 46161 | K42: TRUE | L42: 0.802 | M42: 4.6396291 | N42: K744947 | O42: 109001.35
A43: 45923 | B43: Ёлка 2 | C43: Кат-15 | D43: 70013.85 | E43: расход | F43: П06 | H43: 68 | I43: 157.13 | J43: 46377 | K43: TRUE | L43: 0.165 | M43: 7.7028911 | N43: K342103 | O43: 329128.67
A44: 45738 | B44: Чай 1 | C44: Кат-08 | D44: 239810.47 | E44: приход | F44: П07 | G44: обычный текст | H44: 8 | I44: 4447.87 | J44: 45736 | K44: TRUE | L44: 0.976 | M44: 1.7178456 | N44: K903894 | O44: 146611.26
A45: 45939 | B45: Связь 2 | C45: Кат-17 | D45: -32180.28 | E45: расход | F45: П04 | G45: путь\к\файлу | H45: 60 | I45: 3714.7 | J45: 46196 | K45: FALSE | L45: 0.589 | M45: 6.9196208 | N45: K651840 | O45: 348187.59
A46: 45987 | B46: Доход 2 | C46: Кат-05 | D46: 236132.35 | E46: приход | F46: П13 | G46: TRUE | H46: 22 | I46: 5787.99 | J46: 45983 | K46: FALSE | L46: 0.588 | M46: 2.9031263 | N46: K926381 | O46: -312374.35
A47: 45872 | B47: Чай 2 | C47: Кат-15 | D47: 249984.99 | E47: расход | F47: П14 | G47: 25% | H47: 27 | I47: 3535.79 | J47: 46253 | K47: TRUE | L47: 0.899 | M47: 8.1617062 | N47: K238579 | O47: 100565.58
A48: 45721 | B48: Налог 1 | C48: Кат-12 | D48: -53530.76 | E48: приход | F48: П06 | G48: путь\к\файлу | H48: 88 | I48: 3197.4 | J48: 46187 | K48: FALSE | L48: 0.413 | M48: 9.0975299 | N48: K530841 | O48: -83509
A49: 45668 | B49: Чай 3 | C49: Кат-13 | D49: 56606.62 | E49: расход | F49: П05 | G49: =1+1 | H49: 70 | I49: 504.4 | J49: 45986 | K49: FALSE | L49: 0.661 | M49: 9.7794851 | N49: K8253 | O49: 234730.56
A50: 45662 | B50: Ёлка 3 | C50: Кат-17 | D50: 14732.38 | E50: приход | F50: П15 | G50: TRUE | H50: 1 | I50: 5046.97 | J50: 46244 | K50: TRUE | L50: 0.565 | M50: 8.2413879 | N50: K841819 | O50: -20048.63
A51: 45694 | B51: Аренда 1 | C51: Кат-11 | D51: 158877.33 | E51: расход | F51: П12 | G51: TRUE | H51: 80 | I51: 3409.95 | J51: 46153 | K51: FALSE | L51: 0.358 | M51: 4.3243378 | N51: K478436 | O51: 327745.48
A52: 45951 | B52: Ёлка 4 | C52: Кат-18 | D52: 52231.74 | E52: расход | F52: П02 | G52: =1+1 | H52: 83 | I52: 5970.43 | J52: 46279 | K52: FALSE | L52: 0.894 | M52: 3.5009592 | N52: K466079 | O52: -312631.34
A53: 45824 | B53: Связь 2 | C53: Кат-10 | D53: 3338.13 | E53: расход | F53: П05 | G53: он сказал "да" | H53: 66 | I53: 645.66 | J53: 46340 | K53: FALSE | L53: 0.048 | M53: 3.5452868 | N53: K999854 | O53: 327003.09
A54: 45738 | B54: Аренда 1 | C54: Кат-14 | D54: 200873.7 | E54: приход | F54: П08 | G54: 25% | H54: 24 | I54: 5264.6 | J54: 45721 | K54: FALSE | L54: 0.135 | M54: 7.8045912 | N54: K773951 | O54: -361441.72
A55: 45743 | B55: Ёлка 2 | C55: Кат-16 | D55: 273906.27 | E55: приход | F55: П09 | G55: 'с кавычкой | H55: 32 | I55: 5596.13 | J55: 46178 | K55: TRUE | L55: 0.841 | M55: 5.6483197 | N55: K952223 | O55: 324683.31
... A66: 45689 | B66: Налог 3 | C66: Кат-03 | D66: -59194.5 | E66: расход | F66: П13 | G66: 'с кавычкой | H66: 40 | I66: 7442.27 | J66: 45802 | K66: FALSE | L66: 0.579 | M66: 6.5499407 | N66: K786041 | O66: -93700.21
A67: 45684 | B67: Доход 2 | C67: Кат-09 | D67: 283598.73 | E67: расход | F67: П08 | H67: 30 | I67: 1002.7 | J67: 45695 | K67: TRUE | L67: 0.877 | M67: 4.4845548 | N67: K415248 | O67: 4621.15
A68: 45669 | B68: Сырьё 3 | C68: Кат-07 | D68: 54402.51 | E68: расход | F68: П08 | G68: путь\к\файлу | H68: 52 | I68: 1542.6 | J68: 45982 | K68: FALSE | L68: 0.763 | M68: 9.8167426 | N68: K111455 | O68: -45200.72
A69: 45683 | B69: Доход 4 | C69: Кат-19 | D69: -60052.41 | E69: приход | F69: П11 | G69: он сказал "да" | H69: 37 | I69: 4971.43 | J69: 46217 | K69: FALSE | L69: 0.642 | M69: 1.1868733 | N69: K931674 | O69: 215473.67
A70: 45781 | B70: Чаи 1 | C70: Кат-09 | D70: 134574.59 | E70: приход | F70: П06 | G70: TRUE | H70: 40 | I70: 1961.44 | J70: 46091 | K70: FALSE | L70: 0.946 | M70: 6.665197 | N70: K464229 | O70: 269182.69
A71: 45804 | B71: Доход 2 | C71: Кат-09 | D71: 170120.84 | E71: расход | F71: П10 | G71: 2025-01-01 | H71: 76 | I71: 6525.1 | J71: 45887 | K71: TRUE | L71: 0.263 | M71: 4.3567642 | N71: K869398 | O71: -439631.59
A72: 46015 | B72: Сырьё 2 | C72: Кат-13 | D72: 103867.83 | E72: расход | F72: П08 | G72: 25% | H72: 49 | I72: 6958.76 | J72: 45923 | K72: TRUE | L72: 0.811 | M72: 7.8613886 | N72: K164715 | O72: 407077.49
A73: 45768 | B73: Сырьё 4 | C73: Кат-17 | D73: 47294.32 | E73: приход | F73: П05 | G73: он сказал "да" | H73: 31 | I73: 4136.03 | J73: 45842 | K73: TRUE | L73: 0.124 | M73: 2.5393815 | N73: K576719 | O73: 402269.18
A74: 45927 | B74: Доход 2 | C74: Кат-15 | D74: -59420.61 | E74: приход | F74: П05 | G74: 2025-01-01 | H74: 90 | I74: 8.06 | J74: 46033 | K74: FALSE | L74: 0.63 | M74: 5.7307974 | N74: K326614 | O74: -463358.13
A75: 45662 | B75: Ёлка 1 | C75: Кат-20 | D75: 284772.29 | E75: приход | F75: П03 | G75: 2025-01-01 | H75: 37 | I75: 5776.38 | J75: 45757 | K75: FALSE | L75: 0.451 | M75: 6.6199469 | N75: K736613 | O75: 185725.27
A76: 45795 | B76: Налог 4 | C76: Кат-16 | D76: 297671.82 | E76: расход | F76: П10 | G76: обычный текст | H76: 2 | I76: 883.6 | J76: 46260 | K76: TRUE | L76: 0.052 | M76: 8.5837463 | N76: K979065 | O76: 463227.74
A77: 45957 | B77: Аренда 3 | C77: Кат-08 | D77: 198357.66 | E77: расход | F77: П08 | G77: обычный текст | H77: 64 | I77: 872.21 | J77: 46293 | K77: TRUE | L77: 0.626 | M77: 1.76217 | N77: K731810 | O77: 167911.86
A78: 45914 | B78: Доход 1 | C78: Кат-07 | D78: 274207.5 | E78: приход | F78: П10 | G78: TRUE | H78: 87 | I78: 2013.33 | J78: 46135 | K78: TRUE | L78: 0.507 | M78: 4.875309 | N78: K324732 | O78: -340874.63
A79: 45670 | B79: Ёлка 2 | C79: Кат-08 | D79: 225830.81 | E79: расход | F79: П11 | G79: обычный текст | H79: 55 | I79: 9213.45 | J79: 46276 | K79: FALSE | L79: 0.56 | M79: 7.9842501 | N79: K824244 | O79: -345041.86
... A83: 45675 | B83: Елка 4 | C83: Кат-14 | D83: -53677.74 | E83: приход | F83: П12 | G83: =1+1 | H83: 74 | I83: 9521.22 | J83: 46194 | K83: FALSE | L83: 0.664 | M83: 7.4190987 | N83: K236470 | O83: -15969.74
A84: 45979 | B84: Налог 2 | C84: Кат-06 | D84: 28716.73 | E84: приход | F84: П13 | H84: 8 | I84: 5484.13 | J84: 46082 | K84: TRUE | L84: 0.493 | M84: 3.3626773 | N84: K937524 | O84: -475997.56
A85: 45967 | B85: Связь 3 | C85: Кат-05 | D85: 331731.76 | E85: расход | F85: П13 | H85: 8 | I85: 5272.44 | J85: 45699 | K85: FALSE | L85: 0.232 | M85: 2.2370857 | N85: K187478 | O85: -157972.52
A86: 46003 | B86: Связь 3 | C86: Кат-12 | D86: 159471.5 | E86: приход | F86: П09 | G86: 2025-01-01 | H86: 4 | I86: 3190.14 | J86: 45752 | K86: FALSE | L86: 0.831 | M86: 1.9061923 | N86: K545279 | O86: 13636.18
A87: 46018 | B87: Чай 1 | C87: Кат-15 | D87: 206959.82 | E87: расход | F87: П10 | G87: пробелы | H87: 83 | I87: 1079.83 | J87: 46099 | K87: FALSE | L87: 0.502 | M87: 6.4652038 | N87: K614254 | O87: 443800.47
A88: 45666 | B88: Сырьё 1 | C88: Кат-09 | D88: 67299.02 | E88: расход | F88: П01 | G88: TRUE | H88: 42 | I88: 4779.35 | J88: 45855 | K88: FALSE | L88: 0.001 | M88: 6.3120271 | N88: K74252 | O88: 267908.91
A89: 46001 | B89: Ёлка 3 | C89: Кат-04 | D89: -76555.96 | E89: приход | F89: П15 | G89: 25% | H89: 63 | I89: 8441.34 | J89: 46001 | K89: TRUE | L89: 0.309 | M89: 1.3268099 | N89: K755660 | O89: -477698.13
A90: 45915 | B90: Налог 2 | C90: Кат-01 | D90: 317963.88 | E90: расход | F90: П13 | G90: 'с кавычкой | H90: 52 | I90: 7713.5 | J90: 45906 | K90: TRUE | L90: 0.385 | M90: 1.5383161 | N90: K348112 | O90: 317822.14
A91: 45881 | B91: Налог 2 | C91: Кат-17 | D91: -13469.76 | E91: приход | F91: П15 | G91: =1+1 | H91: 86 | I91: 6355.76 | J91: 45684 | K91: TRUE | L91: 0.646 | M91: 7.3924276 | N91: K682772 | O91: 426828.69
A92: 45871 | B92: Налог 3 | C92: Кат-04 | D92: 295033.37 | E92: приход | F92: П02 | G92: 25% | H92: 33 | I92: 3458.7 | J92: 45815 | K92: TRUE | L92: 0.723 | M92: 7.2110449 | N92: K985801 | O92: 58858.71
A93: 45823 | B93: Ёлка 2 | C93: Кат-03 | D93: 17122.95 | E93: расход | F93: П02 | G93: обычный текст | H93: 76 | I93: 1108.73 | J93: 46313 | K93: TRUE | L93: 0.651 | M93: 3.0206288 | N93: K213671 | O93: -58316.25
A94: 45971 | B94: Елка 2 | C94: Кат-05 | D94: 103673.2 | E94: приход | F94: П08 | G94: 2025-01-01 | H94: 11 | I94: 9494.47 | J94: 46365 | K94: FALSE | L94: 0.693 | M94: 7.0369113 | N94: K40831 | O94: -20608.58
A95: 45925 | B95: Ёлка 1 | C95: Кат-15 | D95: 289995.8 | E95: приход | F95: П05 | G95: путь\к\файлу | H95: 56 | I95: 5200.88 | J95: 46365 | K95: FALSE | L95: 0.042 | M95: 4.3114405 | N95: K966141 | O95: -325588.36
A96: 45722 | B96: Ёлка 4 | C96: Кат-02 | D96: 237308.9 | E96: приход | F96: П13 | G96: пробелы | H96: 47 | I96: 8560.11 | J96: 46302 | K96: FALSE | L96: 0.022 | M96: 7.807423 | N96: K548456 | O96: -290054.3
A97: 45682 | B97: Сырьё 1 | C97: Кат-11 | D97: 160679.83 | E97: расход | F97: П04 | G97: путь\к\файлу | H97: 59 | I97: 5477.29 | J97: 45759 | K97: TRUE | L97: 0.33 | M97: 4.5608088 | N97: K159624 | O97: 84911.95
... A102: 45895 | B102: Елка 3 | C102: Кат-18 | D102: 43871.56 | E102: приход | F102: П08 | G102: =1+1 | H102: 82 | I102: 7777.85 | J102: 46132 | K102: FALSE | L102: 0.504 | M102: 2.2685342 | N102: K606580 | O102: 260578.11
A103: 45677 | B103: Доход 3 | C103: Кат-11 | D103: 371061.55 | E103: расход | F103: П12 | H103: 50 | I103: 8582.92 | J103: 45735 | K103: TRUE | L103: 0.936 | M103: 0.16796065 | N103: K99370 | O103: -287826.12
A104: 45907 | B104: Сырьё 1 | C104: Кат-09 | D104: 10677.33 | E104: расход | F104: П14 | G104: он сказал "да" | H104: 55 | I104: 6760.78 | J104: 45672 | K104: FALSE | L104: 0.283 | M104: 3.6144005 | N104: K603595 | O104: 116659.05
A105: 45720 | B105: Чай 2 | C105: Кат-01 | D105: 261512.61 | E105: расход | F105: П05 | G105: путь\к\файлу | H105: 81 | I105: 735.39 | J105: 45925 | K105: FALSE | L105: 0.443 | M105: 4.4827354 | N105: K105203 | O105: -327819.61
A106: 45944 | B106: Аренда 1 | C106: Кат-17 | D106: 306186.42 | E106: приход | F106: П12 | G106: обычный текст | H106: 10 | I106: 4054.74 | J106: 45698 | K106: TRUE | L106: 0.622 | M106: 8.6460882 | N106: K983490 | O106: -255276.7
A107: 45801 | B107: Елка 3 | C107: Кат-04 | D107: 38193.87 | E107: приход | F107: П08 | G107: 25% | H107: 81 | I107: 5276.96 | J107: 46247 | K107: TRUE | L107: 0.026 | M107: 3.7967642 | N107: K145598 | O107: 400419.7
A108: 45815 | B108: Сырье 3 | C108: Кат-05 | D108: 180154.93 | E108: приход | F108: П11 | G108: пробелы | H108: 13 | I108: 9477.75 | J108: 46158 | K108: TRUE | L108: 0.757 | M108: 5.5016737 | N108: K493829 | O108: 98527.71
A109: 45817 | B109: Елка 1 | C109: Кат-02 | D109: 230678.07 | E109: расход | F109: П02 | G109: обычный текст | H109: 0 | I109: 8609.15 | J109: 45709 | K109: FALSE | L109: 0.975 | M109: 8.8114164 | N109: K655802 | O109: -474532.79
A110: 45689 | B110: Сырьё 4 | C110: Кат-11 | D110: 301703.81 | E110: приход | F110: П13 | G110: 2025-01-01 | H110: 23 | I110: 1912.43 | J110: 46131 | K110: FALSE | L110: 0.083 | M110: 3.2917931 | N110: K945887 | O110: 346552.76
A111: 45664 | B111: Налог 2 | C111: Кат-06 | D111: 38666.81 | E111: приход | F111: П14 | H111: 89 | I111: 3503.34 | J111: 45861 | K111: TRUE | L111: 0.695 | M111: 9.5486831 | N111: K670011 | O111: 490573.63
A112: 45821 | B112: Связь 4 | C112: Кат-13 | D112: 302386.02 | E112: приход | F112: П02 | H112: 49 | I112: 8786.22 | J112: 45857 | K112: FALSE | L112: 0.975 | M112: 7.1458436 | N112: K722529 | O112: -61231.59
A113: 45853 | B113: Елка 2 | C113: Кат-10 | D113: -15627.84 | E113: приход | F113: П03 | G113: 25% | H113: 33 | I113: 5908.61 | J113: 45728 | K113: TRUE | L113: 0.846 | M113: 2.1334978 | N113: K8317 | O113: 425133.11
A114: 45848 | B114: Сырье 3 | C114: Кат-14 | D114: 167126.5 | E114: приход | F114: П01 | H114: 84 | I114: 5575.01 | J114: 45799 | K114: FALSE | L114: 0.639 | M114: 1.6453468 | N114: K706967 | O114: -258182.7
A115: 45970 | B115: Сырье 1 | C115: Кат-06 | D115: -11327.51 | E115: расход | F115: П09 | G115: TRUE | H115: 45 | I115: 6594.94 | J115: 46117 | K115: FALSE | L115: 0.589 | M115: 9.2096758 | N115: K525045 | O115: 154915.74
A116: 45724 | B116: Елка 1 | C116: Кат-01 | D116: 131126.71 | E116: приход | F116: П02 | G116: TRUE | H116: 77 | I116: 5452.61 | J116: 46358 | K116: FALSE | L116: 0.868 | M116: 9.4610066 | N116: K875962 | O116: 449952.56
A117: 45800 | B117: Доход 3 | C117: Кат-04 | D117: 135032.74 | E117: приход | F117: П06 | G117: он сказал "да" | H117: 65 | I117: 9774.86 | J117: 45848 | K117: FALSE | L117: 0.624 | M117: 2.7494063 | N117: K276561 | O117: -149924.63
A118: 45798 | B118: Аренда 3 | C118: Кат-01 | D118: -2930.33 | E118: приход | F118: П15 | G118: он сказал "да" | H118: 18 | I118: 4723.63 | J118: 45992 | K118: FALSE | L118: 0.693 | M118: 2.8776047 | N118: K507924 | O118: 207499.06
A119: 45812 | B119: Ёлка 4 | C119: Кат-08 | D119: 233111.93 | E119: расход | F119: П10 | H119: 68 | I119: 3930.49 | J119: 45845 | K119: FALSE | L119: 0.604 | M119: 0.71305681 | N119: K28046 | O119: -479205.34
A120: 46013 | B120: Чай 2 | C120: Кат-19 | D120: 313851.44 | E120: расход | F120: П09 | G120: он сказал "да" | H120: 21 | I120: 7083.38 | J120: 45773 | K120: FALSE | L120: 0.577 | M120: 8.7049598 | N120: K406190 | O120: -481225.81
A121: 45890 | B121: Чаи 1 | C121: Кат-08 | D121: -21565.47 | E121: приход | F121: П06 | G121: 'с кавычкой | H121: 68 | I121: 9961.84 | J121: 46207 | K121: FALSE | L121: 0.857 | M121: 6.3133107 | N121: K122198 | O121: 28789.72
A122: 45887 | B122: Налог 1 | C122: Кат-08 | D122: 293045.7 | E122: расход | F122: П10 | G122: он сказал "да" | H122: 41 | I122: 9322.77 | J122: 46185 | K122: FALSE | L122: 0.132 | M122: 5.9507592 | N122: K201401 | O122: -377197.73
...

Sheet Статьи
A1: Статья | B1: Группа | C1: Название группы | E1: Группа | F1: Название
A2: Чай 1 | B2: 1 | C2: {=_xlfn.XLOOKUP(B2,$E$2:$E$9,$F$2:$F$9,"нет")} -> Группа «1» | E2: 1 | F2: Группа «1»
A3: Чаи 1 | B3: 1 | C3: {=_xlfn.XLOOKUP(B3,$E$2:$E$9,$F$2:$F$9,"нет")} -> Группа «1» | E3: 2 | F3: Группа «2»
A4: Ёлка 1 | B4: 1 | C4: {=_xlfn.XLOOKUP(B4,$E$2:$E$9,$F$2:$F$9,"нет")} -> Группа «1» | E4: 3 | F4: Группа «3»
A5: Елка 1 | B5: 1 | C5: {=_xlfn.XLOOKUP(B5,$E$2:$E$9,$F$2:$F$9,"нет")} -> Группа «1» | E5: 4 | F5: Группа «4»
A6: Аренда 1 | B6: 1 | C6: {=_xlfn.XLOOKUP(B6,$E$2:$E$9,$F$2:$F$9,"нет")} -> Группа «1» | E6: 5 | F6: Группа «5»
A7: Связь 1 | B7: 2 | C7: {=_xlfn.XLOOKUP(B7,$E$2:$E$9,$F$2:$F$9,"нет")} -> Группа «2» | E7: 6 | F7: Группа «6»
A8: Налог 1 | B8: 2 | C8: {=_xlfn.XLOOKUP(B8,$E$2:$E$9,$F$2:$F$9,"нет")} -> Группа «2» | E8: 7 | F8: Группа «7»
A9: Доход 1 | B9: 2 | C9: {=_xlfn.XLOOKUP(B9,$E$2:$E$9,$F$2:$F$9,"нет")} -> Группа «2» | E9: 8 | F9: Группа «8»
A10: Сырьё 1 | B10: 2 | C10: {=_xlfn.XLOOKUP(B10,$E$2:$E$9,$F$2:$F$9,"нет")} -> Группа «2»
A11: Сырье 1 | B11: 2 | C11: {=_xlfn.XLOOKUP(B11,$E$2:$E$9,$F$2:$F$9,"нет")} -> Группа «2»
A12: Чай 2 | B12: 3 | C12: {=_xlfn.XLOOKUP(B12,$E$2:$E$9,$F$2:$F$9,"нет")} -> Группа «3»
A13: Чаи 2 | B13: 3 | C13: {=_xlfn.XLOOKUP(B13,$E$2:$E$9,$F$2:$F$9,"нет")} -> Группа «3»
A14: Ёлка 2 | B14: 3 | C14: {=_xlfn.XLOOKUP(B14,$E$2:$E$9,$F$2:$F$9,"нет")} -> Группа «3»
A15: Елка 2 | B15: 3 | C15: {=_xlfn.XLOOKUP(B15,$E$2:$E$9,$F$2:$F$9,"нет")} -> Группа «3»
A16: Аренда 2 | B16: 3 | C16: {=_xlfn.XLOOKUP(B16,$E$2:$E$9,$F$2:$F$9,"нет")} -> Группа «3»
A17: Связь 2 | B17: 4 | C17: {=_xlfn.XLOOKUP(B17,$E$2:$E$9,$F$2:$F$9,"нет")} -> Группа «4»
A18: Налог 2 | B18: 4 | C18: {=_xlfn.XLOOKUP(B18,$E$2:$E$9,$F$2:$F$9,"нет")} -> Группа «4»
A19: Доход 2 | B19: 4 | C19: {=_xlfn.XLOOKUP(B19,$E$2:$E$9,$F$2:$F$9,"нет")} -> Группа «4»
A20: Сырьё 2 | B20: 4 | C20: {=_xlfn.XLOOKUP(B20,$E$2:$E$9,$F$2:$F$9,"нет")} -> Группа «4»
A21: Сырье 2 | B21: 4 | C21: {=_xlfn.XLOOKUP(B21,$E$2:$E$9,$F$2:$F$9,"нет")} -> Группа «4»
... A41: Сырье 4 | B41: 8 | C41: {=_xlfn.XLOOKUP(B41,$E$2:$E$9,$F$2:$F$9,"нет")} -> Группа «8»

Sheet Параметры
A1: Начало | B1: 45658
A2: Конец | B2: {=EOMONTH(B1,11)} -> 46022
A3: Приход | B3: приход
A4: Расход | B4: расход
A5: Начало DATE | B5: {=DATE(2025,1,1)} -> 45658
A10: Чай* | B10: {=COUNTIFS(Данные!$B:$B,"Чай*")} -> 41
B11: {=COUNTIFS(Данные!$B:$B,A10,Данные!$E:$E,B3)} -> 17
B12: {=IFERROR(ПоМесяцам!N3/ПоМесяцам!N4,0)} -> 1.0546062
B13: {=ROUND(B12,2)} -> 1.05
B14: {=IF(B12>1,"больше","не больше")} -> больше
B15: {=TEXT(B1,"YYYY-MM-DD")} -> 2025-01-01
B16: {=TEXT(B13,"0.00")} -> 1.05
B17: {=IFERROR(1/(B3="нет"),-1)} -> -1
B18: {=SUMIFS(Данные!$D:$D,Данные!$B:$B,"Чаи*")} -> 3633640.1

Sheet ПоМесяцам
A1: ПоМесяцам | B1: {=Параметры!B1} -> 45658 | C1: {=EOMONTH(B1,0)+1} -> 45689 | D1: {=EOMONTH(C1,0)+1} -> 45717 | E1: {=EOMONTH(D1,0)+1} -> 45748 | F1: {=EOMONTH(E1,0)+1} -> 45778 | G1: {=EOMONTH(F1,0)+1} -> 45809 | H1: {=EOMONTH(G1,0)+1} -> 45839 | I1: {=EOMONTH(H1,0)+1} -> 45870 | J1: {=EOMONTH(I1,0)+1} -> 45901 | ... M1: {=EOMONTH(L1,0)+1} -> 45992
B2: {=EOMONTH(B1,0)} -> 45688 | C2: {=EOMONTH(C1,0)} -> 45716 | D2: {=EOMONTH(D1,0)} -> 45747 | E2: {=EOMONTH(E1,0)} -> 45777 | F2: {=EOMONTH(F1,0)} -> 45808 | G2: {=EOMONTH(G1,0)} -> 45838 | H2: {=EOMONTH(H1,0)} -> 45869 | I2: {=EOMONTH(I1,0)} -> 45900 | ... M2: {=EOMONTH(M1,0)} -> 46022
A3: {=Статьи!A2} -> Чай 1 | B3: {=SUMIFS(Данные!$D:$D,Данные!$B:$B,$A3,Данные!$A:$A,">="&B$1,Данные!$A:$A,"<="&B$2)} -> 201440.5 | C3: {=SUMIFS(Данные!$D:$D,Данные!$B:$B,$A3,Данные!$A:$A,">="&C$1,Данные!$A:$A,"<="&C$2)} -> 0 | D3: {=SUMIFS(Данные!$D:$D,Данные!$B:$B,$A3,Данные!$A:$A,">="&D$1,Данные!$A:$A,"<="&D$2)} -> 674698.26 | E3: {=SUMIFS(Данные!$D:$D,Данные!$B:$B,$A3,Данные!$A:$A,">="&E$1,Данные!$A:$A,"<="&E$2)} -> -77680.2 | F3: {=SUMIFS(Данные!$D:$D,Данные!$B:$B,$A3,Данные!$A:$A,">="&F$1,Данные!$A:$A,"<="&F$2)} -> 0 | G3: {=SUMIFS(Данные!$D:$D,Данные!$B:$B,$A3,Данные!$A:$A,">="&G$1,Данные!$A:$A,"<="&G$2)} -> 0 | H3: {=SUMIFS(Данные!$D:$D,Данные!$B:$B,$A3,Данные!$A:$A,">="&H$1,Данные!$A:$A,"<="&H$2)} -> 494752.81 | I3: {=SUMIFS(Данные!$D:$D,Данные!$B:$B,$A3,Данные!$A:$A,">="&I$1,Данные!$A:$A,"<="&I$2)} -> 0 | ... M3: {=SUMIFS(Данные!$D:$D,Данные!$B:$B,$A3,Данные!$A:$A,">="&M$1,Данные!$A:$A,"<="&M$2)} -> 206959.82 | N3: {=SUM(B3:M3)} -> 1884168.1
A4: {=Статьи!A3} -> Чаи 1 | B4: {=SUMIFS(Данные!$D:$D,Данные!$B:$B,$A4,Данные!$A:$A,">="&B$1,Данные!$A:$A,"<="&B$2)} -> 150225.98 | C4: {=SUMIFS(Данные!$D:$D,Данные!$B:$B,$A4,Данные!$A:$A,">="&C$1,Данные!$A:$A,"<="&C$2)} -> 0 | D4: {=SUMIFS(Данные!$D:$D,Данные!$B:$B,$A4,Данные!$A:$A,">="&D$1,Данные!$A:$A,"<="&D$2)} -> 0 | E4: {=SUMIFS(Данные!$D:$D,Данные!$B:$B,$A4,Данные!$A:$A,">="&E$1,Данные!$A:$A,"<="&E$2)} -> 0 | F4: {=SUMIFS(Данные!$D:$D,Данные!$B:$B,$A4,Данные!$A:$A,">="&F$1,Данные!$A:$A,"<="&F$2)} -> 482987.52 | G4: {=SUMIFS(Данные!$D:$D,Данные!$B:$B,$A4,Данные!$A:$A,">="&G$1,Данные!$A:$A,"<="&G$2)} -> -6678.65 | H4: {=SUMIFS(Данные!$D:$D,Данные!$B:$B,$A4,Данные!$A:$A,">="&H$1,Данные!$A:$A,"<="&H$2)} -> 0 | I4: {=SUMIFS(Данные!$D:$D,Данные!$B:$B,$A4,Данные!$A:$A,">="&I$1,Данные!$A:$A,"<="&I$2)} -> 200235.22 | ... M4: {=SUMIFS(Данные!$D:$D,Данные!$B:$B,$A4,Данные!$A:$A,">="&M$1,Данные!$A:$A,"<="&M$2)} -> 668551.03 | N4: {=SUM(B4:M4)} -> 1786608.3
A5: {=Статьи!A4} -> Ёлка 1 | B5: {=SUMIFS(Данные!$D:$D,Данные!$B:$B,$A5,Данные!$A:$A,">="&B$1,Данные!$A:$A,"<="&B$2)} -> 284772.29 | C5: {=SUMIFS(Данные!$D:$D,Данные!$B:$B,$A5,Данные!$A:$A,">="&C$1,Данные!$A:$A,"<="&C$2)} -> 476555.97 | D5: {=SUMIFS(Данные!$D:$D,Данные!$B:$B,$A5,Данные!$A:$A,">="&D$1,Данные!$A:$A,"<="&D$2)} -> 0 | E5: {=SUMIFS(Данные!$D:$D,Данные!$B:$B,$A5,Данные!$A:$A,">="&E$1,Данные!$A:$A,"<="&E$2)} -> 239698.95 | F5: {=SUMIFS(Данные!$D:$D,Данные!$B:$B,$A5,Данные!$A:$A,">="&F$1,Данные!$A:$A,"<="&F$2)} -> 390910.21 | G5: {=SUMIFS(Данные!$D:$D,Данные!$B:$B,$A5,Данные!$A:$A,">="&G$1,Данные!$A:$A,"<="&G$2)} -> 112561.77 | H5: {=SUMIFS(Данные!$D:$D,Данные!$B:$B,$A5,Данные!$A:$A,">="&H$1,Данные!$A:$A,"<="&H$2)} -> 0 | I5: {=SUMIFS(Данные!$D:$D,Данные!$B:$B,$A5,Данные!$A:$A,">="&I$1,Данные!$A:$A,"<="&I$2)} -> 0 | ... M5: {=SUMIFS(Данные!$D:$D,Данные!$B:$B,$A5,Данные!$A:$A,">="&M$1,Данные!$A:$A,"<="&M$2)} -> 0 | N5: {=SUM(B5:M5)} -> 1939261.5
A6: {=Статьи!A5} -> Елка 1 | B6: {=SUMIFS(Данные!$D:$D,Данные!$B:$B,$A6,Данные!$A:$A,">="&B$1,Данные!$A:$A,"<="&B$2)} -> 0 | C6: {=SUMIFS(Данные!$D:$D,Данные!$B:$B,$A6,Данные!$A:$A,">="&C$1,Данные!$A:$A,"<="&C$2)} -> 111694.51 | D6: {=SUMIFS(Данные!$D:$D,Данные!$B:$B,$A6,Данные!$A:$A,">="&D$1,Данные!$A:$A,"<="&D$2)} -> 561396.13 | E6: {=SUMIFS(Данные!$D:$D,Данные!$B:$B,$A6,Данные!$A:$A,">="&E$1,Данные!$A:$A,"<="&E$2)} -> 0 | F6: {=SUMIFS(Данные!$D:$D,Данные!$B:$B,$A6,Данные!$A:$A,">="&F$1,Данные!$A:$A,"<="&F$2)} -> 147133.95 | G6: {=SUMIFS(Данные!$D:$D,Данные!$B:$B,$A6,Данные!$A:$A,">="&G$1,Данные!$A:$A,"<="&G$2)} -> 492890.75 | H6: {=SUMIFS(Данные!$D:$D,Данные!$B:$B,$A6,Данные!$A:$A,">="&H$1,Данные!$A:$A,"<="&H$2)} -> 0 | I6: {=SUMIFS(Данные!$D:$D,Данные!$B:$B,$A6,Данные!$A:$A,">="&I$1,Данные!$A:$A,"<="&I$2)} -> 0 | ... M6: {=SUMIFS(Данные!$D:$D,Данные!$B:$B,$A6,Данные!$A:$A,">="&M$1,Данные!$A:$A,"<="&M$2)} -> 0 | N6: {=SUM(B6:M6)} -> 1525962.7
A7: {=Статьи!A6} -> Аренда 1 | B7: {=SUMIFS(Данные!$D:$D,Данные!$B:$B,$A7,Данные!$A:$A,">="&B$1,Данные!$A:$A,"<="&B$2)} -> 0 | C7: {=SUMIFS(Данные!$D:$D,Данные!$B:$B,$A7,Данные!$A:$A,">="&C$1,Данные!$A:$A,"<="&C$2)} -> 117411.05 | D7: {=SUMIFS(Данные!$D:$D,Данные!$B:$B,$A7,Данные!$A:$A,">="&D$1,Данные!$A:$A,"<="&D$2)} -> 200873.7 | E7: {=SUMIFS(Данные!$D:$D,Данные!$B:$B,$A7,Данные!$A:$A,">="&E$1,Данные!$A:$A,"<="&E$2)} -> 90275.12 | F7: {=SUMIFS(Данные!$D:$D,Данные!$B:$B,$A7,Данные!$A:$A,">="&F$1,Данные!$A:$A,"<="&F$2)} -> 0 | G7: {=SUMIFS(Данные!$D:$D,Данные!$B:$B,$A7,Данные!$A:$A,">="&G$1,Данные!$A:$A,"<="&G$2)} -> 0 | H7: {=SUMIFS(Данные!$D:$D,Данные!$B:$B,$A7,Данные!$A:$A,">="&H$1,Данные!$A:$A,"<="&H$2)} -> 0 | I7: {=SUMIFS(Данные!$D:$D,Данные!$B:$B,$A7,Данные!$A:$A,">="&I$1,Данные!$A:$A,"<="&I$2)} -> 345306.23 | ... M7: {=SUMIFS(Данные!$D:$D,Данные!$B:$B,$A7,Данные!$A:$A,">="&M$1,Данные!$A:$A,"<="&M$2)} -> 354795.36 | N7: {=SUM(B7:M7)} -> 1496071.2
A8: Итого группа 1 | B8: {=SUM(B3:B7)} -> 636438.77 | C8: {=SUM(C3:C7)} -> 705661.53 | D8: {=SUM(D3:D7)} -> 1436968.1 | E8: {=SUM(E3:E7)} -> 252293.87 | F8: {=SUM(F3:F7)} -> 1021031.7 | G8: {=SUM(G3:G7)} -> 598773.87 | H8: {=SUM(H3:H7)} -> 494752.81 | I8: {=SUM(I3:I7)} -> 545541.45 | ... N8: {=SUM(N3:N7)} -> 8632071.8
A9: {=Статьи!A7} -> Связь 1 | B9: {=SUMIFS(Данные!$D:$D,Данные!$B:$B,$A9,Данные!$A:$A,">="&B$1,Данные!$A:$A,"<="&B$2)} -> 97614.39 | C9: {=SUMIFS(Данные!$D:$D,Данные!$B:$B,$A9,Данные!$A:$A,">="&C$1,Данные!$A:$A,"<="&C$2)} -> 178192.36 | D9: {=SUMIFS(Данные!$D:$D,Данные!$B:$B,$A9,Данные!$A:$A,">="&D$1,Данные!$A:$A,"<="&D$2)} -> 0 | E9: {=SUMIFS(Данные!$D:$D,Данные!$B:$B,$A9,Данные!$A:$A,">="&E$1,Данные!$A:$A,"<="&E$2)} -> 0 | F9: {=SUMIFS(Данные!$D:$D,Данные!$B:$B,$A9,Данные!$A:$A,">="&F$1,Данные!$A:$A,"<="&F$2)} -> 141542.73 | G9: {=SUMIFS(Данные!$D:$D,Данные!$B:$B,$A9,Данные!$A:$A,">="&G$1,Данные!$A:$A,"<="&G$2)} -> 615190.07 | H9: {=SUMIFS(Данные!$D:$D,Данные!$B:$B,$A9,Данные!$A:$A,">="&H$1,Данные!$A:$A,"<="&H$2)} -> 173233.8 | I9: {=SUMIFS(Данные!$D:$D,Данные!$B:$B,$A9,Данные!$A:$A,">="&I$1,Данные!$A:$A,"<="&I$2)} -> 0 | ... M9: {=SUMIFS(Данные!$D:$D,Данные!$B:$B,$A9,Данные!$A:$A,">="&M$1,Данные!$A:$A,"<="&M$2)} -> 78369.71 | N9: {=SUM(B9:M9)} -> 1284143.1
A10: {=Статьи!A8} -> Налог 1 | B10: {=SUMIFS(Данные!$D:$D,Данные!$B:$B,$A10,Данные!$A:$A,">="&B$1,Данные!$A:$A,"<="&B$2)} -> 0 | C10: {=SUMIFS(Данные!$D:$D,Данные!$B:$B,$A10,Данные!$A:$A,">="&C$1,Данные!$A:$A,"<="&C$2)} -> 24606.32 | D10: {=SUMIFS(Данные!$D:$D,Данные!$B:$B,$A10,Данные!$A:$A,">="&D$1,Данные!$A:$A,"<="&D$2)} -> -53530.76 | E10: {=SUMIFS(Данные!$D:$D,Данные!$B:$B,$A10,Данные!$A:$A,">="&E$1,Данные!$A:$A,"<="&E$2)} -> 0 | F10: {=SUMIFS(Данные!$D:$D,Данные!$B:$B,$A10,Данные!$A:$A,">="&F$1,Данные!$A:$A,"<="&F$2)} -> 46330.65 | G10: {=SUMIFS(Данные!$D:$D,Данные!$B:$B,$A10,Данные!$A:$A,">="&G$1,Данные!$A:$A,"<="&G$2)} -> 222390.05 | H10: {=SUMIFS(Данные!$D:$D,Данные!$B:$B,$A10,Данные!$A:$A,">="&H$1,Данные!$A:$A,"<="&H$2)} -> 0 | I10: {=SUMIFS(Данные!$D:$D,Данные!$B:$B,$A10,Данные!$A:$A,">="&I$1,Данные!$A:$A,"<="&I$2)} -> 387806.59 | ... M10: {=SUMIFS(Данные!$D:$D,Данные!$B:$B,$A10,Данные!$A:$A,">="&M$1,Данные!$A:$A,"<="&M$2)} -> -78781.56 | N10: {=SUM(B10:M10)} -> 630619.24
A11: {=Статьи!A9} -> Доход 1 | B11: {=SUMIFS(Данные!$D:$D,Данные!$B:$B,$A11,Данные!$A:$A,">="&B$1,Данные!$A:$A,"<="&B$2)} -> 10010.8 | C11: {=SUMIFS(Данные!$D:$D,Данные!$B:$B,$A11,Данные!$A:$A,">="&C$1,Данные!$A:$A,"<="&C$2)} -> 0 | D11: {=SUMIFS(Данные!$D:$D,Данные!$B:$B,$A11,Данные!$A:$A,">="&D$1,Данные!$A:$A,"<="&D$2)} -> 242812.16 | E11: {=SUMIFS(Данные!$D:$D,Данные!$B:$B,$A11,Данные!$A:$A,">="&E$1,Данные!$A:$A,"<="&E$2)} -> 0 | F11: {=SUMIFS(Данные!$D:$D,Данные!$B:$B,$A11,Данные!$A:$A,">="&F$1,Данные!$A:$A,"<="&F$2)} -> 280790.62 | G11: {=SUMIFS(Данные!$D:$D,Данные!$B:$B,$A11,Данные!$A:$A,">="&G$1,Данные!$A:$A,"<="&G$2)} -> 0 | H11: {=SUMIFS(Данные!$D:$D,Данные!$B:$B,$A11,Данные!$A:$A,">="&H$1,Данные!$A:$A,"<="&H$2)} -> 217989.18 | I11: {=SUMIFS(Данные!$D:$D,Данные!$B:$B,$A11,Данные!$A:$A,">="&I$1,Данные!$A:$A,"<="&I$2)} -> 386326.05 | ... M11: {=SUMIFS(Данные!$D:$D,Данные!$B:$B,$A11,Данные!$A:$A,">="&M$1,Данные!$A:$A,"<="&M$2)} -> 0 | N11: {=SUM(B11:M11)} -> 1746676.3
A12: {=Статьи!A10} -> Сырьё 1 | B12: {=SUMIFS(Данные!$D:$D,Данные!$B:$B,$A12,Данные!$A:$A,">="&B$1,Данные!$A:$A,"<="&B$2)} -> 356320.82 | C12: {=SUMIFS(Данные!$D:$D,Данные!$B:$B,$A12,Данные!$A:$A,">="&C$1,Данные!$A:$A,"<="&C$2)} -> 0 | D12: {=SUMIFS(Данные!$D:$D,Данные!$B:$B,$A12,Данные!$A:$A,">="&D$1,Данные!$A:$A,"<="&D$2)} -> 0 | E12: {=SUMIFS(Данные!$D:$D,Данные!$B:$B,$A12,Данные!$A:$A,">="&E$1,Данные!$A:$A,"<="&E$2)} -> 339107.89 | F12: {=SUMIFS(Данные!$D:$D,Данные!$B:$B,$A12,Данные!$A:$A,">="&F$1,Данные!$A:$A,"<="&F$2)} -> 0 | G12: {=SUMIFS(Данные!$D:$D,Данные!$B:$B,$A12,Данные!$A:$A,">="&G$1,Данные!$A:$A,"<="&G$2)} -> -182223.25 | H12: {=SUMIFS(Данные!$D:$D,Данные!$B:$B,$A12,Данные!$A:$A,">="&H$1,Данные!$A:$A,"<="&H$2)} -> 0 | I12: {=SUMIFS(Данные!$D:$D,Данные!$B:$B,$A12,Данные!$A:$A,">="&I$1,Данные!$A:$A,"<="&I$2)} -> -42568.94 | ... M12: {=SUMIFS(Данные!$D:$D,Данные!$B:$B,$A12,Данные!$A:$A,">="&M$1,Данные!$A:$A,"<="&M$2)} -> 326886.85 | N12: {=SUM(B12:M12)} -> 1461005.5
A13: {=Статьи!A11} -> Сырье 1 | B13: {=SUMIFS(Данные!$D:$D,Данные!$B:$B,$A13,Данные!$A:$A,">="&B$1,Данные!$A:$A,"<="&B$2)} -> 0 | C13: {=SUMIFS(Данные!$D:$D,Данные!$B:$B,$A13,Данные!$A:$A,">="&C$1,Данные!$A:$A,"<="&C$2)} -> 0 | D13: {=SUMIFS(Данные!$D:$D,Данные!$B:$B,$A13,Данные!$A:$A,">="&D$1,Данные!$A:$A,"<="&D$2)} -> -7891.15 | E13: {=SUMIFS(Данные!$D:$D,Данные!$B:$B,$A13,Данные!$A:$A,">="&E$1,Данные!$A:$A,"<="&E$2)} -> 0 | F13: {=SUMIFS(Данные!$D:$D,Данные!$B:$B,$A13,Данные!$A:$A,">="&F$1,Данные!$A:$A,"<="&F$2)} -> 0 | G13: {=SUMIFS(Данные!$D:$D,Данные!$B:$B,$A13,Данные!$A:$A,">="&G$1,Данные!$A:$A,"<="&G$2)} -> 0 | H13: {=SUMIFS(Данные!$D:$D,Данные!$B:$B,$A13,Данные!$A:$A,">="&H$1,Данные!$A:$A,"<="&H$2)} -> 44692.14 | I13: {=SUMIFS(Данные!$D:$D,Данные!$B:$B,$A13,Данные!$A:$A,">="&I$1,Данные!$A:$A,"<="&I$2)} -> 197703.92 | ... M13: {=SUMIFS(Данные!$D:$D,Данные!$B:$B,$A13,Данные!$A:$A,">="&M$1,Данные!$A:$A,"<="&M$2)} -> -31559.73 | N13: {=SUM(B13:M13)} -> 472649.75
A14: Итого группа 2 | B14: {=SUM(B9:B13)} -> 463946.01 | C14: {=SUM(C9:C13)} -> 202798.68 | D14: {=SUM(D9:D13)} -> 181390.25 | E14: {=SUM(E9:E13)} -> 339107.89 | F14: {=SUM(F9:F13)} -> 468664 | G14: {=SUM(G9:G13)} -> 655356.87 | H14: {=SUM(H9:H13)} -> 435915.12 | I14: {=SUM(I9:I13)} -> 929267.62 | ... N14: {=SUM(N9:N13)} -> 5595093.9
A15: {=Статьи!A12} -> Чай 2 | B15: {=SUMIFS(Данные!$D:$D,Данные!$B:$B,$A15,Данные!$A:$A,">="&B$1,Данные!$A:$A,"<="&B$2)} -> 0 | C15: {=SUMIFS(Данные!$D:$D,Данные!$B:$B,$A15,Данные!$A:$A,">="&C$1,Данные!$A:$A,"<="&C$2)} -> 0 | D15: {=SUMIFS(Данные!$D:$D,Данные!$B:$B,$A15,Данные!$A:$A,">="&D$1,Данные!$A:$A,"<="&D$2)} -> 261512.61 | E15: {=SUMIFS(Данные!$D:$D,Данные!$B:$B,$A15,Данные!$A:$A,">="&E$1,Данные!$A:$A,"<="&E$2)} -> -82587.59 | F15: {=SUMIFS(Данные!$D:$D,Данные!$B:$B,$A15,Данные!$A:$A,">="&F$1,Данные!$A:$A,"<="&F$2)} -> 0 | G15: {=SUMIFS(Данные!$D:$D,Данные!$B:$B,$A15,Данные!$A:$A,">="&G$1,Данные!$A:$A,"<="&G$2)} -> 0 | H15: {=SUMIFS(Данные!$D:$D,Данные!$B:$B,$A15,Данные!$A:$A,">="&H$1,Данные!$A:$A,"<="&H$2)} -> 222008.01 | I15: {=SUMIFS(Данные!$D:$D,Данные!$B:$B,$A15,Данные!$A:$A,">="&I$1,Данные!$A:$A,"<="&I$2)} -> 452052.26 | ... M15: {=SUMIFS(Данные!$D:$D,Данные!$B:$B,$A15,Данные!$A:$A,">="&M$1,Данные!$A:$A,"<="&M$2)} -> 635438.37 | N15: {=SUM(B15:M15)} -> 2050056.9
A16: {=Статьи!A13} -> Чаи 2 | B16: {=SUMIFS(Данные!$D:$D,Данные!$B:$B,$A16,Данные!$A:$A,">="&B$1,Данные!$A:$A,"<="&B$2)} -> 0 | C16: {=SUMIFS(Данные!$D:$D,Данные!$B:$B,$A16,Данные!$A:$A,">="&C$1,Данные!$A:$A,"<="&C$2)} -> 0 | D16: {=SUMIFS(Данные!$D:$D,Данные!$B:$B,$A16,Данные!$A:$A,">="&D$1,Данные!$A:$A,"<="&D$2)} -> 0 | E16: {=SUMIFS(Данные!$D:$D,Данные!$B:$B,$A16,Данные!$A:$A,">="&E$1,Данные!$A:$A,"<="&E$2)} -> 0 | F16: {=SUMIFS(Данные!$D:$D,Данные!$B:$B,$A16,Данные!$A:$A,">="&F$1,Данные!$A:$A,"<="&F$2)} -> 0 | G16: {=SUMIFS(Данные!$D:$D,Данные!$B:$B,$A16,Данные!$A:$A,">="&G$1,Данные!$A:$A,"<="&G$2)} -> 0 | H16: {=SUMIFS(Данные!$D:$D,Данные!$B:$B,$A16,Данные!$A:$A,">="&H$1,Данные!$A:$A,"<="&H$2)} -> 0 | I16: {=SUMIFS(Данные!$D:$D,Данные!$B:$B,$A16,Данные!$A:$A,">="&I$1,Данные!$A:$A,"<="&I$2)} -> 0 | ... M16: {=SUMIFS(Данные!$D:$D,Данные!$B:$B,$A16,Данные!$A:$A,">="&M$1,Данные!$A:$A,"<="&M$2)} -> 73165.31 | N16: {=SUM(B16:M16)} -> 334421.4
A17: {=Статьи!A14} -> Ёлка 2 | B17: {=SUMIFS(Данные!$D:$D,Данные!$B:$B,$A17,Данные!$A:$A,">="&B$1,Данные!$A:$A,"<="&B$2)} -> 225830.81 | C17: {=SUMIFS(Данные!$D:$D,Данные!$B:$B,$A17,Данные!$A:$A,">="&C$1,Данные!$A:$A,"<="&C$2)} -> -52645.57 | D17: {=SUMIFS(Данные!$D:$D,Данные!$B:$B,$A17,Данные!$A:$A,">="&D$1,Данные!$A:$A,"<="&D$2)} -> 273906.27 | E17: {=SUMIFS(Данные!$D:$D,Данные!$B:$B,$A17,Данные!$A:$A,">="&E$1,Данные!$A:$A,"<="&E$2)} -> 0 | F17: {=SUMIFS(Данные!$D:$D,Данные!$B:$B,$A17,Данные!$A:$A,">="&F$1,Данные!$A:$A,"<="&F$2)} -> 0 | G17: {=SUMIFS(Данные!$D:$D,Данные!$B:$B,$A17,Данные!$A:$A,">="&G$1,Данные!$A:$A,"<="&G$2)} -> 17122.95 | H17: {=SUMIFS(Данные!$D:$D,Данные!$B:$B,$A17,Данные!$A:$A,">="&H$1,Данные!$A:$A,"<="&H$2)} -> 0 | I17: {=SUMIFS(Данные!$D:$D,Данные!$B:$B,$A17,Данные!$A:$A,">="&I$1,Данные!$A:$A,"<="&I$2)} -> -28948.52 | ... M17: {=SUMIFS(Данные!$D:$D,Данные!$B:$B,$A17,Данные!$A:$A,">="&M$1,Данные!$A:$A,"<="&M$2)} -> 0 | N17: {=SUM(B17:M17)} -> 773174.4
A18: {=Статьи!A15} -> Елка 2 | B18: {=SUMIFS(Данные!$D:$D,Данные!$B:$B,$A18,Данные!$A:$A,">="&B$1,Данные!$A:$A,"<="&B$2)} -> 0 | C18: {=SUMIFS(Данные!$D:$D,Данные!$B:$B,$A18,Данные!$A:$A,">="&C$1,Данные!$A:$A,"<="&C$2)} -> 0 | D18: {=SUMIFS(Данные!$D:$D,Данные!$B:$B,$A18,Данные!$A:$A,">="&D$1,Данные!$A:$A,"<="&D$2)} -> -63824.16 | E18: {=SUMIFS(Данные!$D:$D,Данные!$B:$B,$A18,Данные!$A:$A,">="&E$1,Данные!$A:$A,"<="&E$2)} -> 0 | F18: {=SUMIFS(Данные!$D:$D,Данные!$B:$B,$A18,Данные!$A:$A,">="&F$1,Данные!$A:$A,"<="&F$2)} -> 0 | G18: {=SUMIFS(Данные!$D:$D,Данные!$B:$B,$A18,Данные!$A:$A,">="&G$1,Данные!$A:$A,"<="&G$2)} -> 358273.26 | H18: {=SUMIFS(Данные!$D:$D,Данные!$B:$B,$A18,Данные!$A:$A,">="&H$1,Данные!$A:$A,"<="&H$2)} -> -15627.84 | I18: {=SUMIFS(Данные!$D:$D,Данные!$B:$B,$A18,Данные!$A:$A,">="&I$1,Данные!$A:$A,"<="&I$2)} -> 365776.07 | ... M18: {=SUMIFS(Данные!$D:$D,Данные!$B:$B,$A18,Данные!$A:$A,">="&M$1,Данные!$A:$A,"<="&M$2)} -> 0 | N18: {=SUM(B18:M18)} -> 674538.7
A19: {=Статьи!A16} -> Аренда 2 | B19: {=SUMIFS(Данные!$D:$D,Данные!$B:$B,$A19,Данные!$A:$A,">="&B$1,Данные!$A:$A,"<="&B$2)} -> 193100.63 | C19: {=SUMIFS(Данные!$D:$D,Данные!$B:$B,$A19,Данные!$A:$A,">="&C$1,Данные!$A:$A,"<="&C$2)} -> 0 | D19: {=SUMIFS(Данные!$D:$D,Данные!$B:$B,$A19,Данные!$A:$A,">="&D$1,Данные!$A:$A,"<="&D$2)} -> 324159.6 | E19: {=SUMIFS(Данные!$D:$D,Данные!$B:$B,$A19,Данные!$A:$A,">="&E$1,Данные!$A:$A,"<="&E$2)} -> 0 | F19: {=SUMIFS(Данные!$D:$D,Данные!$B:$B,$A19,Данные!$A:$A,">="&F$1,Данные!$A:$A,"<="&F$2)} -> 672233.3 | G19: {=SUMIFS(Данные!$D:$D,Данные!$B:$B,$A19,Данные!$A:$A,">="&G$1,Данные!$A:$A,"<="&G$2)} -> 94850.14 | H19: {=SUMIFS(Данные!$D:$D,Данные!$B:$B,$A19,Данные!$A:$A,">="&H$1,Данные!$A:$A,"<="&H$2)} -> 0 | I19: {=SUMIFS(Данные!$D:$D,Данные!$B:$B,$A19,Данные!$A:$A,">="&I$1,Данные!$A:$A,"<="&I$2)} -> 428309.52 | ... M19: {=SUMIFS(Данные!$D:$D,Данные!$B:$B,$A19,Данные!$A:$A,">="&M$1,Данные!$A:$A,"<="&M$2)} -> 0 | N19: {=SUM(B19:M19)} -> 1712653.2
A20: Итого группа 3 | B20: {=SUM(B15:B19)} -> 418931.44 | C20: {=SUM(C15:C19)} -> -52645.57 | D20: {=SUM(D15:D19)} -> 795754.32 | E20: {=SUM(E15:E19)} -> -82587.59 | F20: {=SUM(F15:F19)} -> 672233.3 | G20: {=SUM(G15:G19)} -> 470246.35 | H20: {=SUM(H15:H19)} -> 206380.17 | I20: {=SUM(I15:I19)} -> 1217189.3 | ... N20: {=SUM(N15:N19)} -> 5544844.5
A21: {=Статьи!A17} -> Связь 2 | B21: {=SUMIFS(Данные!$D:$D,Данные!$B:$B,$A21,Данные!$A:$A,">="&B$1,Данные!$A:$A,"<="&B$2)} -> 0 | C21: {=SUMIFS(Данные!$D:$D,Данные!$B:$B,$A21,Данные!$A:$A,">="&C$1,Данные!$A:$A,"<="&C$2)} -> 0 | D21: {=SUMIFS(Данные!$D:$D,Данные!$B:$B,$A21,Данные!$A:$A,">="&D$1,Данные!$A:$A,"<="&D$2)} -> 302502.66 | E21: {=SUMIFS(Данные!$D:$D,Данные!$B:$B,$A21,Данные!$A:$A,">="&E$1,Данные!$A:$A,"<="&E$2)} -> 0 | F21: {=SUMIFS(Данные!$D:$D,Данные!$B:$B,$A21,Данные!$A:$A,">="&F$1,Данные!$A:$A,"<="&F$2)} -> 17079.28 | G21: {=SUMIFS(Данные!$D:$D,Данные!$B:$B,$A21,Данные!$A:$A,">="&G$1,Данные!$A:$A,"<="&G$2)} -> 3338.13 | H21: {=SUMIFS(Данные!$D:$D,Данные!$B:$B,$A21,Данные!$A:$A,">="&H$1,Данные!$A:$A,"<="&H$2)} -> 0 | I21: {=SUMIFS(Данные!$D:$D,Данные!$B:$B,$A21,Данные!$A:$A,">="&I$1,Данные!$A:$A,"<="&I$2)} -> 369105.58 | ... M21: {=SUMIFS(Данные!$D:$D,Данные!$B:$B,$A21,Данные!$A:$A,">="&M$1,Данные!$A:$A,"<="&M$2)} -> 0 | N21: {=SUM(B21:M21)} -> 540928.25
A22: {=Статьи!A18} -> Налог 2 | B22: {=SUMIFS(Данные!$D:$D,Данные!$B:$B,$A22,Данные!$A:$A,">="&B$1,Данные!$A:$A,"<="&B$2)} -> 359900.52 | C22: {=SUMIFS(Данные!$D:$D,Данные!$B:$B,$A22,Данные!$A:$A,">="&C$1,Данные!$A:$A,"<="&C$2)} -> 0 | D22: {=SUMIFS(Данные!$D:$D,Данные!$B:$B,$A22,Данные!$A:$A,">="&D$1,Данные!$A:$A,"<="&D$2)} -> 0 | E22: {=SUMIFS(Данные!$D:$D,Данные!$B:$B,$A22,Данные!$A:$A,">="&E$1,Данные!$A:$A,"<="&E$2)} -> 0 | F22: {=SUMIFS(Данные!$D:$D,Данные!$B:$B,$A22,Данные!$A:$A,">="&F$1,Данные!$A:$A,"<="&F$2)} -> 0 | G22: {=SUMIFS(Данные!$D:$D,Данные!$B:$B,$A22,Данные!$A:$A,">="&G$1,Данные!$A:$A,"<="&G$2)} -> 0 | H22: {=SUMIFS(Данные!$D:$D,Данные!$B:$B,$A22,Данные!$A:$A,">="&H$1,Данные!$A:$A,"<="&H$2)} -> 146159.26 | I22: {=SUMIFS(Данные!$D:$D,Данные!$B:$B,$A22,Данные!$A:$A,">="&I$1,Данные!$A:$A,"<="&I$2)} -> -76742.92 | ... M22: {=SUMIFS(Данные!$D:$D,Данные!$B:$B,$A22,Данные!$A:$A,">="&M$1,Данные!$A:$A,"<="&M$2)} -> 0 | N22: {=SUM(B22:M22)} -> 1132300.7
A23: {=Статьи!A19} -> Доход 2 | B23: {=SUMIFS(Данные!$D:$D,Данные!$B:$B,$A23,Данные!$A:$A,">="&B$1,Данные!$A:$A,"<="&B$2)} -> 283598.73 | C23: {=SUMIFS(Данные!$D:$D,Данные!$B:$B,$A23,Данные!$A:$A,">="&C$1,Данные!$A:$A,"<="&C$2)} -> 0 | D23: {=SUMIFS(Данные!$D:$D,Данные!$B:$B,$A23,Данные!$A:$A,">="&D$1,Данные!$A:$A,"<="&D$2)} -> 0 | E23: {=SUMIFS(Данные!$D:$D,Данные!$B:$B,$A23,Данные!$A:$A,">="&E$1,Данные!$A:$A,"<="&E$2)} -> 0 | F23: {=SUMIFS(Данные!$D:$D,Данные!$B:$B,$A23,Данные!$A:$A,">="&F$1,Данные!$A:$A,"<="&F$2)} -> 321244.59 | G23: {=SUMIFS(Данные!$D:$D,Данные!$B:$B,$A23,Данные!$A:$A,">="&G$1,Данные!$A:$A,"<="&G$2)} -> 0 | H23: {=SUMIFS(Данные!$D:$D,Данные!$B:$B,$A23,Данные!$A:$A,">="&H$1,Данные!$A:$A,"<="&H$2)} -> 0 | I23: {=SUMIFS(Данные!$D:$D,Данные!$B:$B,$A23,Данные!$A:$A,">="&I$1,Данные!$A:$A,"<="&I$2)} -> 0 | ... M23: {=SUMIFS(Данные!$D:$D,Данные!$B:$B,$A23,Данные!$A:$A,">="&M$1,Данные!$A:$A,"<="&M$2)} -> 0 | N23: {=SUM(B23:M23)} -> 702919.91
A24: {=Статьи!A20} -> Сырьё 2 | B24: {=SUMIFS(Данные!$D:$D,Данные!$B:$B,$A24,Данные!$A:$A,">="&B$1,Данные!$A:$A,"<="&B$2)} -> 48723.82 | C24: {=SUMIFS(Данные!$D:$D,Данные!$B:$B,$A24,Данные!$A:$A,">="&C$1,Данные!$A:$A,"<="&C$2)} -> 29317.87 | D24: {=SUMIFS(Данные!$D:$D,Данные!$B:$B,$A24,Данные!$A:$A,">="&D$1,Данные!$A:$A,"<="&D$2)} -> 152209.67 | E24: {=SUMIFS(Данные!$D:$D,Данные!$B:$B,$A24,Данные!$A:$A,">="&E$1,Данные!$A:$A,"<="&E$2)} -> 292678.6 | F24: {=SUMIFS(Данные!$D:$D,Данные!$B:$B,$A24,Данные!$A:$A,">="&F$1,Данные!$A:$A,"<="&F$2)} -> 0 | G24: {=SUMIFS(Данные!$D:$D,Данные!$B:$B,$A24,Данные!$A:$A,">="&G$1,Данные!$A:$A,"<="&G$2)} -> 3.8050072e+08 | H24: {=SUMIFS(Данные!$D:$D,Данные!$B:$B,$A24,Данные!$A:$A,">="&H$1,Данные!$A:$A,"<="&H$2)} -> 332928.47 | I24: {=SUMIFS(Данные!$D:$D,Данные!$B:$B,$A24,Данные!$A:$A,">="&I$1,Данные!$A:$A,"<="&I$2)} -> 0 | ... M24: {=SUMIFS(Данные!$D:$D,Данные!$B:$B,$A24,Данные!$A:$A,">="&M$1,Данные!$A:$A,"<="&M$2)} -> 103867.83 | N24: {=SUM(B24:M24)} -> 3.8138789e+08
A25: {=Статьи!A21} -> Сырье 2 | B25: {=SUMIFS(Данные!$D:$D,Данные!$B:$B,$A25,Данные!$A:$A,">="&B$1,Данные!$A:$A,"<="&B$2)} -> -68476 | C25: {=SUMIFS(Данные!$D:$D,Данные!$B:$B,$A25,Данные!$A:$A,">="&C$1,Данные!$A:$A,"<="&C$2)} -> 0 | D25: {=SUMIFS(Данные!$D:$D,Данные!$B:$B,$A25,Данные!$A:$A,">="&D$1,Данные!$A:$A,"<="&D$2)} -> 221595.45 | E25: {=SUMIFS(Данные!$D:$D,Данные!$B:$B,$A25,Данные!$A:$A,">="&E$1,Данные!$A:$A,"<="&E$2)} -> 150781.73 | F25: {=SUMIFS(Данные!$D:$D,Данные!$B:$B,$A25,Данные!$A:$A,">="&F$1,Данные!$A:$A,"<="&F$2)} -> -42207.32 | G25: {=SUMIFS(Данные!$D:$D,Данные!$B:$B,$A25,Данные!$A:$A,">="&G$1,Данные!$A:$A,"<="&G$2)} -> 102310.79 | H25: {=SUMIFS(Данные!$D:$D,Данные!$B:$B,$A25,Данные!$A:$A,">="&H$1,Данные!$A:$A,"<="&H$2)} -> -61034.63 | I25: {=SUMIFS(Данные!$D:$D,Данные!$B:$B,$A25,Данные!$A:$A,">="&I$1,Данные!$A:$A,"<="&I$2)} -> 0 | ... M25: {=SUMIFS(Данные!$D:$D,Данные!$B:$B,$A25,Данные!$A:$A,">="&M$1,Данные!$A:$A,"<="&M$2)} -> -34400.87 | N25: {=SUM(B25:M25)} -> 268569.15
A26: Итого группа 4 | B26: {=SUM(B21:B25)} -> 623747.07 | C26: {=SUM(C21:C25)} -> 29317.87 | D26: {=SUM(D21:D25)} -> 676307.78 | E26: {=SUM(E21:E25)} -> 443460.33 | F26: {=SUM(F21:F25)} -> 296116.55 | G26: {=SUM(G21:G25)} -> 3.8060637e+08 | H26: {=SUM(H21:H25)} -> 418053.1 | I26: {=SUM(I21:I25)} -> 292362.66 | ... N26: {=SUM(N21:N25)} -> 3.840326e+08
A27: {=Статьи!A22} -> Чай 3 | B27: {=SUMIFS(Данные!$D:$D,Данные!$B:$B,$A27,Данные!$A:$A,">="&B$1,Данные!$A:$A,"<="&B$2)} -> 56606.62 | C27: {=SUMIFS(Данные!$D:$D,Данные!$B:$B,$A27,Данные!$A:$A,">="&C$1,Данные!$A:$A,"<="&C$2)} -> 0 | D27: {=SUMIFS(Данные!$D:$D,Данные!$B:$B,$A27,Данные!$A:$A,">="&D$1,Данные!$A:$A,"<="&D$2)} -> 265561.61 | E27: {=SUMIFS(Данные!$D:$D,Данные!$B:$B,$A27,Данные!$A:$A,">="&E$1,Данные!$A:$A,"<="&E$2)} -> 435406.09 | F27: {=SUMIFS(Данные!$D:$D,Данные!$B:$B,$A27,Данные!$A:$A,">="&F$1,Данные!$A:$A,"<="&F$2)} -> 72144.07 | G27: {=SUMIFS(Данные!$D:$D,Данные!$B:$B,$A27,Данные!$A:$A,">="&G$1,Данные!$A:$A,"<="&G$2)} -> 0 | H27: {=SUMIFS(Данные!$D:$D,Данные!$B:$B,$A27,Данные!$A:$A,">="&H$1,Данные!$A:$A,"<="&H$2)} -> 225608.62 | I27: {=SUMIFS(Данные!$D:$D,Данные!$B:$B,$A27,Данные!$A:$A,">="&I$1,Данные!$A:$A,"<="&I$2)} -> 0 | ... M27: {=SUMIFS(Данные!$D:$D,Данные!$B:$B,$A27,Данные!$A:$A,">="&M$1,Данные!$A:$A,"<="&M$2)} -> 298260.07 | N27: {=SUM(B27:M27)} -> 1669478.9
A28: {=Статьи!A23} -> Чаи 3 | B28: {=SUMIFS(Данные!$D:$D,Данные!$B:$B,$A28,Данные!$A:$A,">="&B$1,Данные!$A:$A,"<="&B$2)} -> 0 | C28: {=SUMIFS(Данные!$D:$D,Данные!$B:$B,$A28,Данные!$A:$A,">="&C$1,Данные!$A:$A,"<="&C$2)} -> 0 | D28: {=SUMIFS(Данные!$D:$D,Данные!$B:$B,$A28,Данные!$A:$A,">="&D$1,Данные!$A:$A,"<="&D$2)} -> 0 | E28: {=SUMIFS(Данные!$D:$D,Данные!$B:$B,$A28,Данные!$A:$A,">="&E$1,Данные!$A:$A,"<="&E$2)} -> 0 | F28: {=SUMIFS(Данные!$D:$D,Данные!$B:$B,$A28,Данные!$A:$A,">="&F$1,Данные!$A:$A,"<="&F$2)} -> 283986.55 | G28: {=SUMIFS(Данные!$D:$D,Данные!$B:$B,$A28,Данные!$A:$A,">="&G$1,Данные!$A:$A,"<="&G$2)} -> 315607.12 | H28: {=SUMIFS(Данные!$D:$D,Данные!$B:$B,$A28,Данные!$A:$A,">="&H$1,Данные!$A:$A,"<="&H$2)} -> 255552.73 | I28: {=SUMIFS(Данные!$D:$D,Данные!$B:$B,$A28,Данные!$A:$A,">="&I$1,Данные!$A:$A,"<="&I$2)} -> 0 | ... M28: {=SUMIFS(Данные!$D:$D,Данные!$B:$B,$A28,Данные!$A:$A,">="&M$1,Данные!$A:$A,"<="&M$2)} -> 346144.14 | N28: {=SUM(B28:M28)} -> 1133889
A29: {=Статьи!A24} -> Ёлка 3 | B29: {=SUMIFS(Данные!$D:$D,Данные!$B:$B,$A29,Данные!$A:$A,">="&B$1,Данные!$A:$A,"<="&B$2)} -> 379836.22 | C29: {=SUMIFS(Данные!$D:$D,Данные!$B:$B,$A29,Данные!$A:$A,">="&C$1,Данные!$A:$A,"<="&C$2)} -> 0 | D29: {=SUMIFS(Данные!$D:$D,Данные!$B:$B,$A29,Данные!$A:$A,">="&D$1,Данные!$A:$A,"<="&D$2)} -> 0 | E29: {=SUMIFS(Данные!$D:$D,Данные!$B:$B,$A29,Данные!$A:$A,">="&E$1,Данные!$A:$A,"<="&E$2)} -> 0 | F29: {=SUMIFS(Данные!$D:$D,Данные!$B:$B,$A29,Данные!$A:$A,">="&F$1,Данные!$A:$A,"<="&F$2)} -> 1.8817151e+09 | G29: {=SUMIFS(Данные!$D:$D,Данные!$B:$B,$A29,Данные!$A:$A,">="&G$1,Данные!$A:$A,"<="&G$2)} -> 185018.89 | H29: {=SUMIFS(Данные!$D:$D,Данные!$B:$B,$A29,Данные!$A:$A,">="&H$1,Данные!$A:$A,"<="&H$2)} -> 0 | I29: {=SUMIFS(Данные!$D:$D,Данные!$B:$B,$A29,Данные!$A:$A,">="&I$1,Данные!$A:$A,"<="&I$2)} -> 514835.97 | ... M29: {=SUMIFS(Данные!$D:$D,Данные!$B:$B,$A29,Данные!$A:$A,">="&M$1,Данные!$A:$A,"<="&M$2)} -> 87531.96 | N29: {=SUM(B29:M29)} -> 1.8830753e+09
A30: {=Статьи!A25} -> Елка 3 | B30: {=SUMIFS(Данные!$D:$D,Данные!$B:$B,$A30,Данные!$A:$A,">="&B$1,Данные!$A:$A,"<="&B$2)} -> 0 | C30: {=SUMIFS(Данные!$D:$D,Данные!$B:$B,$A30,Данные!$A:$A,">="&C$1,Данные!$A:$A,"<="&C$2)} -> 0 | D30: {=SUMIFS(Данные!$D:$D,Данные!$B:$B,$A30,Данные!$A:$A,">="&D$1,Данные!$A:$A,"<="&D$2)} -> 0 | E30: {=SUMIFS(Данные!$D:$D,Данные!$B:$B,$A30,Данные!$A:$A,">="&E$1,Данные!$A:$A,"<="&E$2)} -> 138812.72 | F30: {=SUMIFS(Данные!$D:$D,Данные!$B:$B,$A30,Данные!$A:$A,">="&F$1,Данные!$A:$A,"<="&F$2)} -> 38193.87 | G30: {=SUMIFS(Данные!$D:$D,Данные!$B:$B,$A30,Данные!$A:$A,">="&G$1,Данные!$A:$A,"<="&G$2)} -> 0 | H30: {=SUMIFS(Данные!$D:$D,Данные!$B:$B,$A30,Данные!$A:$A,">="&H$1,Данные!$A:$A,"<="&H$2)} -> 0 | I30: {=SUMIFS(Данные!$D:$D,Данные!$B:$B,$A30,Данные!$A:$A,">="&I$1,Данные!$A:$A,"<="&I$2)} -> 1.2815172e+09 | ... M30: {=SUMIFS(Данные!$D:$D,Данные!$B:$B,$A30,Данные!$A:$A,">="&M$1,Данные!$A:$A,"<="&M$2)} -> 0 | N30: {=SUM(B30:M30)} -> 1.2820175e+09
A31: {=Статьи!A26} -> Аренда 3 | B31: {=SUMIFS(Данные!$D:$D,Данные!$B:$B,$A31,Данные!$A:$A,">="&B$1,Данные!$A:$A,"<="&B$2)} -> 0 | C31: {=SUMIFS(Данные!$D:$D,Данные!$B:$B,$A31,Данные!$A:$A,">="&C$1,Данные!$A:$A,"<="&C$2)} -> 0 | D31: {=SUMIFS(Данные!$D:$D,Данные!$B:$B,$A31,Данные!$A:$A,">="&D$1,Данные!$A:$A,"<="&D$2)} -> 0 | E31: {=SUMIFS(Данные!$D:$D,Данные!$B:$B,$A31,Данные!$A:$A,">="&E$1,Данные!$A:$A,"<="&E$2)} -> 373909.42 | F31: {=SUMIFS(Данные!$D:$D,Данные!$B:$B,$A31,Данные!$A:$A,">="&F$1,Данные!$A:$A,"<="&F$2)} -> -2930.33 | G31: {=SUMIFS(Данные!$D:$D,Данные!$B:$B,$A31,Данные!$A:$A,">="&G$1,Данные!$A:$A,"<="&G$2)} -> 376896.25 | H31: {=SUMIFS(Данные!$D:$D,Данные!$B:$B,$A31,Данные!$A:$A,">="&H$1,Данные!$A:$A,"<="&H$2)} -> 0 | I31: {=SUMIFS(Данные!$D:$D,Данные!$B:$B,$A31,Данные!$A:$A,">="&I$1,Данные!$A:$A,"<="&I$2)} -> 0 | ... M31: {=SUMIFS(Данные!$D:$D,Данные!$B:$B,$A31,Данные!$A:$A,">="&M$1,Данные!$A:$A,"<="&M$2)} -> 0 | N31: {=SUM(B31:M31)} -> 1891179.2
A32: Итого группа 5 | B32: {=SUM(B27:B31)} -> 436442.84 | C32: {=SUM(C27:C31)} -> 0 | D32: {=SUM(D27:D31)} -> 265561.61 | E32: {=SUM(E27:E31)} -> 948128.23 | F32: {=SUM(F27:F31)} -> 1.8821064e+09 | G32: {=SUM(G27:G31)} -> 877522.26 | H32: {=SUM(H27:H31)} -> 481161.35 | I32: {=SUM(I27:I31)} -> 1.2820321e+09 | ... N32: {=SUM(N27:N31)} -> 3.1697873e+09
A33: {=Статьи!A27} -> Связь 3 | B33: {=SUMIFS(Данные!$D:$D,Данные!$B:$B,$A33,Данные!$A:$A,">="&B$1,Данные!$A:$A,"<="&B$2)} -> 27521.77 | C33: {=SUMIFS(Данные!$D:$D,Данные!$B:$B,$A33,Данные!$A:$A,">="&C$1,Данные!$A:$A,"<="&C$2)} -> 0 | D33: {=SUMIFS(Данные!$D:$D,Данные!$B:$B,$A33,Данные!$A:$A,">="&D$1,Данные!$A:$A,"<="&D$2)} -> 0 | E33: {=SUMIFS(Данные!$D:$D,Данные!$B:$B,$A33,Данные!$A:$A,">="&E$1,Данные!$A:$A,"<="&E$2)} -> 190699 | F33: {=SUMIFS(Данные!$D:$D,Данные!$B:$B,$A33,Данные!$A:$A,">="&F$1,Данные!$A:$A,"<="&F$2)} -> 93549.25 | G33: {=SUMIFS(Данные!$D:$D,Данные!$B:$B,$A33,Данные!$A:$A,">="&G$1,Данные!$A:$A,"<="&G$2)} -> 369197.94 | H33: {=SUMIFS(Данные!$D:$D,Данные!$B:$B,$A33,Данные!$A:$A,">="&H$1,Данные!$A:$A,"<="&H$2)} -> 132793.61 | I33: {=SUMIFS(Данные!$D:$D,Данные!$B:$B,$A33,Данные!$A:$A,">="&I$1,Данные!$A:$A,"<="&I$2)} -> 393482.97 | ... M33: {=SUMIFS(Данные!$D:$D,Данные!$B:$B,$A33,Данные!$A:$A,">="&M$1,Данные!$A:$A,"<="&M$2)} -> 159471.5 | N33: {=SUM(B33:M33)} -> 1852085.3
A34: {=Статьи!A28} -> Налог 3 | B34: {=SUMIFS(Данные!$D:$D,Данные!$B:$B,$A34,Данные!$A:$A,">="&B$1,Данные!$A:$A,"<="&B$2)} -> 0 | C34: {=SUMIFS(Данные!$D:$D,Данные!$B:$B,$A34,Данные!$A:$A,">="&C$1,Данные!$A:$A,"<="&C$2)} -> -59194.5 | D34: {=SUMIFS(Данные!$D:$D,Данные!$B:$B,$A34,Данные!$A:$A,">="&D$1,Данные!$A:$A,"<="&D$2)} -> 0 | E34: {=SUMIFS(Данные!$D:$D,Данные!$B:$B,$A34,Данные!$A:$A,">="&E$1,Данные!$A:$A,"<="&E$2)} -> 0 | F34: {=SUMIFS(Данные!$D:$D,Данные!$B:$B,$A34,Данные!$A:$A,">="&F$1,Данные!$A:$A,"<="&F$2)} -> 280166.41 | G34: {=SUMIFS(Данные!$D:$D,Данные!$B:$B,$A34,Данные!$A:$A,">="&G$1,Данные!$A:$A,"<="&G$2)} -> 0 | H34: {=SUMIFS(Данные!$D:$D,Данные!$B:$B,$A34,Данные!$A:$A,">="&H$1,Данные!$A:$A,"<="&H$2)} -> 0 | I34: {=SUMIFS(Данные!$D:$D,Данные!$B:$B,$A34,Данные!$A:$A,">="&I$1,Данные!$A:$A,"<="&I$2)} -> 295033.37 | ... M34: {=SUMIFS(Данные!$D:$D,Данные!$B:$B,$A34,Данные!$A:$A,">="&M$1,Данные!$A:$A,"<="&M$2)} -> 241153.62 | N34: {=SUM(B34:M34)} -> 933602.78
A35: {=Статьи!A29} -> Доход 3 | B35: {=SUMIFS(Данные!$D:$D,Данные!$B:$B,$A35,Данные!$A:$A,">="&B$1,Данные!$A:$A,"<="&B$2)} -> 371061.55 | C35: {=SUMIFS(Данные!$D:$D,Данные!$B:$B,$A35,Данные!$A:$A,">="&C$1,Данные!$A:$A,"<="&C$2)} -> 50413.46 | D35: {=SUMIFS(Данные!$D:$D,Данные!$B:$B,$A35,Данные!$A:$A,">="&D$1,Данные!$A:$A,"<="&D$2)} -> 387270.57 | E35: {=SUMIFS(Данные!$D:$D,Данные!$B:$B,$A35,Данные!$A:$A,">="&E$1,Данные!$A:$A,"<="&E$2)} -> -19894.29 | F35: {=SUMIFS(Данные!$D:$D,Данные!$B:$B,$A35,Данные!$A:$A,">="&F$1,Данные!$A:$A,"<="&F$2)} -> 320529.04 | G35: {=SUMIFS(Данные!$D:$D,Данные!$B:$B,$A35,Данные!$A:$A,">="&G$1,Данные!$A:$A,"<="&G$2)} -> 0 | H35: {=SUMIFS(Данные!$D:$D,Данные!$B:$B,$A35,Данные!$A:$A,">="&H$1,Данные!$A:$A,"<="&H$2)} -> 584926.12 | I35: {=SUMIFS(Данные!$D:$D,Данные!$B:$B,$A35,Данные!$A:$A,">="&I$1,Данные!$A:$A,"<="&I$2)} -> 0 | ... M35: {=SUMIFS(Данные!$D:$D,Данные!$B:$B,$A35,Данные!$A:$A,">="&M$1,Данные!$A:$A,"<="&M$2)} -> -100543.09 | N35: {=SUM(B35:M35)} -> 1974235.4
A36: {=Статьи!A30} -> Сырьё 3 | B36: {=SUMIFS(Данные!$D:$D,Данные!$B:$B,$A36,Данные!$A:$A,">="&B$1,Данные!$A:$A,"<="&B$2)} -> 354518.59 | C36: {=SUMIFS(Данные!$D:$D,Данные!$B:$B,$A36,Данные!$A:$A,">="&C$1,Данные!$A:$A,"<="&C$2)} -> 204939.46 | D36: {=SUMIFS(Данные!$D:$D,Данные!$B:$B,$A36,Данные!$A:$A,">="&D$1,Данные!$A:$A,"<="&D$2)} -> 191368.37 | E36: {=SUMIFS(Данные!$D:$D,Данные!$B:$B,$A36,Данные!$A:$A,">="&E$1,Данные!$A:$A,"<="&E$2)} -> 0 | F36: {=SUMIFS(Данные!$D:$D,Данные!$B:$B,$A36,Данные!$A:$A,">="&F$1,Данные!$A:$A,"<="&F$2)} -> 287101.89 | G36: {=SUMIFS(Данные!$D:$D,Данные!$B:$B,$A36,Данные!$A:$A,">="&G$1,Данные!$A:$A,"<="&G$2)} -> 644785.7 | H36: {=SUMIFS(Данные!$D:$D,Данные!$B:$B,$A36,Данные!$A:$A,">="&H$1,Данные!$A:$A,"<="&H$2)} -> 0 | I36: {=SUMIFS(Данные!$D:$D,Данные!$B:$B,$A36,Данные!$A:$A,">="&I$1,Данные!$A:$A,"<="&I$2)} -> 0 | ... M36: {=SUMIFS(Данные!$D:$D,Данные!$B:$B,$A36,Данные!$A:$A,">="&M$1,Данные!$A:$A,"<="&M$2)} -> 0 | N36: {=SUM(B36:M36)} -> 1656921
A37: {=Статьи!A31} -> Сырье 3 | B37: {=SUMIFS(Данные!$D:$D,Данные!$B:$B,$A37,Данные!$A:$A,">="&B$1,Данные!$A:$A,"<="&B$2)} -> 0 | C37: {=SUMIFS(Данные!$D:$D,Данные!$B:$B,$A37,Данные!$A:$A,">="&C$1,Данные!$A:$A,"<="&C$2)} -> 0 | D37: {=SUMIFS(Данные!$D:$D,Данные!$B:$B,$A37,Данные!$A:$A,">="&D$1,Данные!$A:$A,"<="&D$2)} -> 0 | E37: {=SUMIFS(Данные!$D:$D,Данные!$B:$B,$A37,Данные!$A:$A,">="&E$1,Данные!$A:$A,"<="&E$2)} -> 0 | F37: {=SUMIFS(Данные!$D:$D,Данные!$B:$B,$A37,Данные!$A:$A,">="&F$1,Данные!$A:$A,"<="&F$2)} -> 0 | G37: {=SUMIFS(Данные!$D:$D,Данные!$B:$B,$A37,Данные!$A:$A,">="&G$1,Данные!$A:$A,"<="&G$2)} -> 541045.82 | H37: {=SUMIFS(Данные!$D:$D,Данные!$B:$B,$A37,Данные!$A:$A,">="&H$1,Данные!$A:$A,"<="&H$2)} -> 167126.5 | I37: {=SUMIFS(Данные!$D:$D,Данные!$B:$B,$A37,Данные!$A:$A,">="&I$1,Данные!$A:$A,"<="&I$2)} -> 0 | ... M37: {=SUMIFS(Данные!$D:$D,Данные!$B:$B,$A37,Данные!$A:$A,">="&M$1,Данные!$A:$A,"<="&M$2)} -> 0 | N37: {=SUM(B37:M37)} -> 682903.28
A38: Итого группа 6 | B38: {=SUM(B33:B37)} -> 753101.91 | C38: {=SUM(C33:C37)} -> 196158.42 | D38: {=SUM(D33:D37)} -> 578638.94 | E38: {=SUM(E33:E37)} -> 170804.71 | F38: {=SUM(F33:F37)} -> 981346.59 | G38: {=SUM(G33:G37)} -> 1555029.5 | H38: {=SUM(H33:H37)} -> 884846.23 | I38: {=SUM(I33:I37)} -> 688516.34 | ... N38: {=SUM(N33:N37)} -> 7099747.8
A39: {=Статьи!A32} -> Чай 4 | B39: {=SUMIFS(Данные!$D:$D,Данные!$B:$B,$A39,Данные!$A:$A,">="&B$1,Данные!$A:$A,"<="&B$2)} -> 0 | C39: {=SUMIFS(Данные!$D:$D,Данные!$B:$B,$A39,Данные!$A:$A,">="&C$1,Данные!$A:$A,"<="&C$2)} -> 0 | D39: {=SUMIFS(Данные!$D:$D,Данные!$B:$B,$A39,Данные!$A:$A,">="&D$1,Данные!$A:$A,"<="&D$2)} -> 0 | E39: {=SUMIFS(Данные!$D:$D,Данные!$B:$B,$A39,Данные!$A:$A,">="&E$1,Данные!$A:$A,"<="&E$2)} -> 0 | F39: {=SUMIFS(Данные!$D:$D,Данные!$B:$B,$A39,Данные!$A:$A,">="&F$1,Данные!$A:$A,"<="&F$2)} -> 0 | G39: {=SUMIFS(Данные!$D:$D,Данные!$B:$B,$A39,Данные!$A:$A,">="&G$1,Данные!$A:$A,"<="&G$2)} -> 0 | H39: {=SUMIFS(Данные!$D:$D,Данные!$B:$B,$A39,Данные!$A:$A,">="&H$1,Данные!$A:$A,"<="&H$2)} -> 206502.25 | I39: {=SUMIFS(Данные!$D:$D,Данные!$B:$B,$A39,Данные!$A:$A,">="&I$1,Данные!$A:$A,"<="&I$2)} -> 412631.83 | ... M39: {=SUMIFS(Данные!$D:$D,Данные!$B:$B,$A39,Данные!$A:$A,">="&M$1,Данные!$A:$A,"<="&M$2)} -> 286133.45 | N39: {=SUM(B39:M39)} -> 814966.76
A40: {=Статьи!A33} -> Чаи 4 | B40: {=SUMIFS(Данные!$D:$D,Данные!$B:$B,$A40,Данные!$A:$A,">="&B$1,Данные!$A:$A,"<="&B$2)} -> 0 | C40: {=SUMIFS(Данные!$D:$D,Данные!$B:$B,$A40,Данные!$A:$A,">="&C$1,Данные!$A:$A,"<="&C$2)} -> -82546.68 | D40: {=SUMIFS(Данные!$D:$D,Данные!$B:$B,$A40,Данные!$A:$A,">="&D$1,Данные!$A:$A,"<="&D$2)} -> 0 | E40: {=SUMIFS(Данные!$D:$D,Данные!$B:$B,$A40,Данные!$A:$A,">="&E$1,Данные!$A:$A,"<="&E$2)} -> -1902.9 | F40: {=SUMIFS(Данные!$D:$D,Данные!$B:$B,$A40,Данные!$A:$A,">="&F$1,Данные!$A:$A,"<="&F$2)} -> 0 | G40: {=SUMIFS(Данные!$D:$D,Данные!$B:$B,$A40,Данные!$A:$A,">="&G$1,Данные!$A:$A,"<="&G$2)} -> -7931.29 | H40: {=SUMIFS(Данные!$D:$D,Данные!$B:$B,$A40,Данные!$A:$A,">="&H$1,Данные!$A:$A,"<="&H$2)} -> 0 | I40: {=SUMIFS(Данные!$D:$D,Данные!$B:$B,$A40,Данные!$A:$A,">="&I$1,Данные!$A:$A,"<="&I$2)} -> 0 | ... M40: {=SUMIFS(Данные!$D:$D,Данные!$B:$B,$A40,Данные!$A:$A,">="&M$1,Данные!$A:$A,"<="&M$2)} -> 0 | N40: {=SUM(B40:M40)} -> 378721.45
A41: {=Статьи!A34} -> Ёлка 4 | B41: {=SUMIFS(Данные!$D:$D,Данные!$B:$B,$A41,Данные!$A:$A,">="&B$1,Данные!$A:$A,"<="&B$2)} -> 0 | C41: {=SUMIFS(Данные!$D:$D,Данные!$B:$B,$A41,Данные!$A:$A,">="&C$1,Данные!$A:$A,"<="&C$2)} -> 0 | D41: {=SUMIFS(Данные!$D:$D,Данные!$B:$B,$A41,Данные!$A:$A,">="&D$1,Данные!$A:$A,"<="&D$2)} -> 237308.9 | E41: {=SUMIFS(Данные!$D:$D,Данные!$B:$B,$A41,Данные!$A:$A,">="&E$1,Данные!$A:$A,"<="&E$2)} -> 0 | F41: {=SUMIFS(Данные!$D:$D,Данные!$B:$B,$A41,Данные!$A:$A,">="&F$1,Данные!$A:$A,"<="&F$2)} -> 68375.15 | G41: {=SUMIFS(Данные!$D:$D,Данные!$B:$B,$A41,Данные!$A:$A,">="&G$1,Данные!$A:$A,"<="&G$2)} -> 233111.93 | H41: {=SUMIFS(Данные!$D:$D,Данные!$B:$B,$A41,Данные!$A:$A,">="&H$1,Данные!$A:$A,"<="&H$2)} -> -95339.57 | I41: {=SUMIFS(Данные!$D:$D,Данные!$B:$B,$A41,Данные!$A:$A,">="&I$1,Данные!$A:$A,"<="&I$2)} -> 0 | ... M41: {=SUMIFS(Данные!$D:$D,Данные!$B:$B,$A41,Данные!$A:$A,">="&M$1,Данные!$A:$A,"<="&M$2)} -> 0 | N41: {=SUM(B41:M41)} -> 495688.15
A42: {=Статьи!A35} -> Елка 4 | B42: {=SUMIFS(Данные!$D:$D,Данные!$B:$B,$A42,Данные!$A:$A,">="&B$1,Данные!$A:$A,"<="&B$2)} -> -53677.74 | C42: {=SUMIFS(Данные!$D:$D,Данные!$B:$B,$A42,Данные!$A:$A,">="&C$1,Данные!$A:$A,"<="&C$2)} -> 0 | D42: {=SUMIFS(Данные!$D:$D,Данные!$B:$B,$A42,Данные!$A:$A,">="&D$1,Данные!$A:$A,"<="&D$2)} -> -12007.38 | E42: {=SUMIFS(Данные!$D:$D,Данные!$B:$B,$A42,Данные!$A:$A,">="&E$1,Данные!$A:$A,"<="&E$2)} -> -95356.54 | F42: {=SUMIFS(Данные!$D:$D,Данные!$B:$B,$A42,Данные!$A:$A,">="&F$1,Данные!$A:$A,"<="&F$2)} -> 0 | G42: {=SUMIFS(Данные!$D:$D,Данные!$B:$B,$A42,Данные!$A:$A,">="&G$1,Данные!$A:$A,"<="&G$2)} -> 602594.26 | H42: {=SUMIFS(Данные!$D:$D,Данные!$B:$B,$A42,Данные!$A:$A,">="&H$1,Данные!$A:$A,"<="&H$2)} -> 0 | I42: {=SUMIFS(Данные!$D:$D,Данные!$B:$B,$A42,Данные!$A:$A,">="&I$1,Данные!$A:$A,"<="&I$2)} -> 0 | ... M42: {=SUMIFS(Данные!$D:$D,Данные!$B:$B,$A42,Данные!$A:$A,">="&M$1,Данные!$A:$A,"<="&M$2)} -> 0 | N42: {=SUM(B42:M42)} -> 796439
A43: {=Статьи!A36} -> Аренда 4 | B43: {=SUMIFS(Данные!$D:$D,Данные!$B:$B,$A43,Данные!$A:$A,">="&B$1,Данные!$A:$A,"<="&B$2)} -> 244646 | C43: {=SUMIFS(Данные!$D:$D,Данные!$B:$B,$A43,Данные!$A:$A,">="&C$1,Данные!$A:$A,"<="&C$2)} -> 8341.13 | D43: {=SUMIFS(Данные!$D:$D,Данные!$B:$B,$A43,Данные!$A:$A,">="&D$1,Данные!$A:$A,"<="&D$2)} -> 381705.97 | E43: {=SUMIFS(Данные!$D:$D,Данные!$B:$B,$A43,Данные!$A:$A,">="&E$1,Данные!$A:$A,"<="&E$2)} -> 0 | F43: {=SUMIFS(Данные!$D:$D,Данные!$B:$B,$A43,Данные!$A:$A,">="&F$1,Данные!$A:$A,"<="&F$2)} -> 0 | G43: {=SUMIFS(Данные!$D:$D,Данные!$B:$B,$A43,Данные!$A:$A,">="&G$1,Данные!$A:$A,"<="&G$2)} -> 0 | H43: {=SUMIFS(Данные!$D:$D,Данные!$B:$B,$A43,Данные!$A:$A,">="&H$1,Данные!$A:$A,"<="&H$2)} -> 46530.92 | I43: {=SUMIFS(Данные!$D:$D,Данные!$B:$B,$A43,Данные!$A:$A,">="&I$1,Данные!$A:$A,"<="&I$2)} -> 0 | ... M43: {=SUMIFS(Данные!$D:$D,Данные!$B:$B,$A43,Данные!$A:$A,">="&M$1,Данные!$A:$A,"<="&M$2)} -> 0 | N43: {=SUM(B43:M43)} -> 1061446
A44: Итого группа 7 | B44: {=SUM(B39:B43)} -> 190968.26 | C44: {=SUM(C39:C43)} -> -74205.55 | D44: {=SUM(D39:D43)} -> 607007.49 | E44: {=SUM(E39:E43)} -> -97259.44 | F44: {=SUM(F39:F43)} -> 68375.15 | G44: {=SUM(G39:G43)} -> 827774.9 | H44: {=SUM(H39:H43)} -> 157693.6 | I44: {=SUM(I39:I43)} -> 412631.83 | ... N44: {=SUM(N39:N43)} -> 3547261.3
A45: {=Статьи!A37} -> Связь 4 | B45: {=SUMIFS(Данные!$D:$D,Данные!$B:$B,$A45,Данные!$A:$A,">="&B$1,Данные!$A:$A,"<="&B$2)} -> 12844.7 | C45: {=SUMIFS(Данные!$D:$D,Данные!$B:$B,$A45,Данные!$A:$A,">="&C$1,Данные!$A:$A,"<="&C$2)} -> 263411.22 | D45: {=SUMIFS(Данные!$D:$D,Данные!$B:$B,$A45,Данные!$A:$A,">="&D$1,Данные!$A:$A,"<="&D$2)} -> 0 | E45: {=SUMIFS(Данные!$D:$D,Данные!$B:$B,$A45,Данные!$A:$A,">="&E$1,Данные!$A:$A,"<="&E$2)} -> 0 | F45: {=SUMIFS(Данные!$D:$D,Данные!$B:$B,$A45,Данные!$A:$A,">="&F$1,Данные!$A:$A,"<="&F$2)} -> 331308.82 | G45: {=SUMIFS(Данные!$D:$D,Данные!$B:$B,$A45,Данные!$A:$A,">="&G$1,Данные!$A:$A,"<="&G$2)} -> 302386.02 | H45: {=SUMIFS(Данные!$D:$D,Данные!$B:$B,$A45,Данные!$A:$A,">="&H$1,Данные!$A:$A,"<="&H$2)} -> 0 | I45: {=SUMIFS(Данные!$D:$D,Данные!$B:$B,$A45,Данные!$A:$A,">="&I$1,Данные!$A:$A,"<="&I$2)} -> 275085.8 | ... M45: {=SUMIFS(Данные!$D:$D,Данные!$B:$B,$A45,Данные!$A:$A,">="&M$1,Данные!$A:$A,"<="&M$2)} -> 206710.29 | N45: {=SUM(B45:M45)} -> 1391746.9
A46: {=Статьи!A38} -> Налог 4 | B46: {=SUMIFS(Данные!$D:$D,Данные!$B:$B,$A46,Данные!$A:$A,">="&B$1,Данные!$A:$A,"<="&B$2)} -> 0 | C46: {=SUMIFS(Данные!$D:$D,Данные!$B:$B,$A46,Данные!$A:$A,">="&C$1,Данные!$A:$A,"<="&C$2)} -> 0 | D46: {=SUMIFS(Данные!$D:$D,Данные!$B:$B,$A46,Данные!$A:$A,">="&D$1,Данные!$A:$A,"<="&D$2)} -> 0 | E46: {=SUMIFS(Данные!$D:$D,Данные!$B:$B,$A46,Данные!$A:$A,">="&E$1,Данные!$A:$A,"<="&E$2)} -> 0 | F46: {=SUMIFS(Данные!$D:$D,Данные!$B:$B,$A46,Данные!$A:$A,">="&F$1,Данные!$A:$A,"<="&F$2)} -> 297671.82 | G46: {=SUMIFS(Данные!$D:$D,Данные!$B:$B,$A46,Данные!$A:$A,">="&G$1,Данные!$A:$A,"<="&G$2)} -> 0 | H46: {=SUMIFS(Данные!$D:$D,Данные!$B:$B,$A46,Данные!$A:$A,">="&H$1,Данные!$A:$A,"<="&H$2)} -> 0 | I46: {=SUMIFS(Данные!$D:$D,Данные!$B:$B,$A46,Данные!$A:$A,">="&I$1,Данные!$A:$A,"<="&I$2)} -> 0 | ... M46: {=SUMIFS(Данные!$D:$D,Данные!$B:$B,$A46,Данные!$A:$A,">="&M$1,Данные!$A:$A,"<="&M$2)} -> 447307.16 | N46: {=SUM(B46:M46)} -> 962785.14
A47: {=Статьи!A39} -> Доход 4 | B47: {=SUMIFS(Данные!$D:$D,Данные!$B:$B,$A47,Данные!$A:$A,">="&B$1,Данные!$A:$A,"<="&B$2)} -> -60052.41 | C47: {=SUMIFS(Данные!$D:$D,Данные!$B:$B,$A47,Данные!$A:$A,">="&C$1,Данные!$A:$A,"<="&C$2)} -> -22998.85 | D47: {=SUMIFS(Данные!$D:$D,Данные!$B:$B,$A47,Данные!$A:$A,">="&D$1,Данные!$A:$A,"<="&D$2)} -> 165967.2 | E47: {=SUMIFS(Данные!$D:$D,Данные!$B:$B,$A47,Данные!$A:$A,">="&E$1,Данные!$A:$A,"<="&E$2)} -> 0 | F47: {=SUMIFS(Данные!$D:$D,Данные!$B:$B,$A47,Данные!$A:$A,">="&F$1,Данные!$A:$A,"<="&F$2)} -> 0 | G47: {=SUMIFS(Данные!$D:$D,Данные!$B:$B,$A47,Данные!$A:$A,">="&G$1,Данные!$A:$A,"<="&G$2)} -> 0 | H47: {=SUMIFS(Данные!$D:$D,Данные!$B:$B,$A47,Данные!$A:$A,">="&H$1,Данные!$A:$A,"<="&H$2)} -> 31149.1 | I47: {=SUMIFS(Данные!$D:$D,Данные!$B:$B,$A47,Данные!$A:$A,">="&I$1,Данные!$A:$A,"<="&I$2)} -> 179183.33 | ... M47: {=SUMIFS(Данные!$D:$D,Данные!$B:$B,$A47,Данные!$A:$A,">="&M$1,Данные!$A:$A,"<="&M$2)} -> 317210.93 | N47: {=SUM(B47:M47)} -> 796427.49
A48: {=Статьи!A40} -> Сырьё 4 | B48: {=SUMIFS(Данные!$D:$D,Данные!$B:$B,$A48,Данные!$A:$A,">="&B$1,Данные!$A:$A,"<="&B$2)} -> 0 | C48: {=SUMIFS(Данные!$D:$D,Данные!$B:$B,$A48,Данные!$A:$A,">="&C$1,Данные!$A:$A,"<="&C$2)} -> 301703.81 | D48: {=SUMIFS(Данные!$D:$D,Данные!$B:$B,$A48,Данные!$A:$A,">="&D$1,Данные!$A:$A,"<="&D$2)} -> -77915.36 | E48: {=SUMIFS(Данные!$D:$D,Данные!$B:$B,$A48,Данные!$A:$A,">="&E$1,Данные!$A:$A,"<="&E$2)} -> 555808.01 | F48: {=SUMIFS(Данные!$D:$D,Данные!$B:$B,$A48,Данные!$A:$A,">="&F$1,Данные!$A:$A,"<="&F$2)} -> 247002.34 | G48: {=SUMIFS(Данные!$D:$D,Данные!$B:$B,$A48,Данные!$A:$A,">="&G$1,Данные!$A:$A,"<="&G$2)} -> 332596.92 | H48: {=SUMIFS(Данные!$D:$D,Данные!$B:$B,$A48,Данные!$A:$A,">="&H$1,Данные!$A:$A,"<="&H$2)} -> 0 | I48: {=SUMIFS(Данные!$D:$D,Данные!$B:$B,$A48,Данные!$A:$A,">="&I$1,Данные!$A:$A,"<="&I$2)} -> 522692.59 | ... M48: {=SUMIFS(Данные!$D:$D,Данные!$B:$B,$A48,Данные!$A:$A,">="&M$1,Данные!$A:$A,"<="&M$2)} -> 0 | N48: {=SUM(B48:M48)} -> 2006191.4
A49: {=Статьи!A41} -> Сырье 4 | B49: {=SUMIFS(Данные!$D:$D,Данные!$B:$B,$A49,Данные!$A:$A,">="&B$1,Данные!$A:$A,"<="&B$2)} -> 2514.75 | C49: {=SUMIFS(Данные!$D:$D,Данные!$B:$B,$A49,Данные!$A:$A,">="&C$1,Данные!$A:$A,"<="&C$2)} -> 62537.84 | D49: {=SUMIFS(Данные!$D:$D,Данные!$B:$B,$A49,Данные!$A:$A,">="&D$1,Данные!$A:$A,"<="&D$2)} -> 153679.94 | E49: {=SUMIFS(Данные!$D:$D,Данные!$B:$B,$A49,Данные!$A:$A,">="&E$1,Данные!$A:$A,"<="&E$2)} -> 0 | F49: {=SUMIFS(Данные!$D:$D,Данные!$B:$B,$A49,Данные!$A:$A,">="&F$1,Данные!$A:$A,"<="&F$2)} -> 0 | G49: {=SUMIFS(Данные!$D:$D,Данные!$B:$B,$A49,Данные!$A:$A,">="&G$1,Данные!$A:$A,"<="&G$2)} -> 178646.95 | H49: {=SUMIFS(Данные!$D:$D,Данные!$B:$B,$A49,Данные!$A:$A,">="&H$1,Данные!$A:$A,"<="&H$2)} -> 0 | I49: {=SUMIFS(Данные!$D:$D,Данные!$B:$B,$A49,Данные!$A:$A,">="&I$1,Данные!$A:$A,"<="&I$2)} -> 0 | ... M49: {=SUMIFS(Данные!$D:$D,Данные!$B:$B,$A49,Данные!$A:$A,">="&M$1,Данные!$A:$A,"<="&M$2)} -> 0 | N49: {=SUM(B49:M49)} -> 529055.37
A50: Итого группа 8 | B50: {=SUM(B45:B49)} -> -44692.96 | C50: {=SUM(C45:C49)} -> 604654.02 | D50: {=SUM(D45:D49)} -> 241731.78 | E50: {=SUM(E45:E49)} -> 555808.01 | F50: {=SUM(F45:F49)} -> 875982.98 | G50: {=SUM(G45:G49)} -> 813629.89 | H50: {=SUM(H45:H49)} -> 31149.1 | I50: {=SUM(I45:I49)} -> 976961.72 | ... N50: {=SUM(N45:N49)} -> 5686206.3

Sheet ПоПроектам
A1: ПоПроектам | B1: П01 | C1: П02 | D1: П03 | E1: П04 | F1: П05 | G1: П06 | H1: П07 | I1: П08 | J1: П09 | K1: П10 | L1: П11 | M1: П12 | N1: П13 | O1: П14 | P1: П15
A2: {=Статьи!A2} -> Чай 1 | B2: {=SUMIFS(Данные!$D$2:$D$341,Данные!$B$2:$B$341,$A2,Данные!$F$2:$F$341,B$1,Данные!$A$2:$A$341,">="&Параметры!$B$1,Данные!$A$2:$A$341,"<="&Параметры!$B$2,Данные!$E$2:$E$341,Параметры!$B$4)} -> 0 | C2: {=SUMIFS(Данные!$D$2:$D$341,Данные!$B$2:$B$341,$A2,Данные!$F$2:$F$341,C$1,Данные!$A$2:$A$341,">="&Параметры!$B$1,Данные!$A$2:$A$341,"<="&Параметры!$B$2,Данные!$E$2:$E$341,Параметры!$B$4)} -> 275047.94 | D2: {=SUMIFS(Данные!$D$2:$D$341,Данные!$B$2:$B$341,$A2,Данные!$F$2:$F$341,D$1,Данные!$A$2:$A$341,">="&Параметры!$B$1,Данные!$A$2:$A$341,"<="&Параметры!$B$2,Данные!$E$2:$E$341,Параметры!$B$4)} -> 0 | E2: {=SUMIFS(Данные!$D$2:$D$341,Данные!$B$2:$B$341,$A2,Данные!$F$2:$F$341,E$1,Данные!$A$2:$A$341,">="&Параметры!$B$1,Данные!$A$2:$A$341,"<="&Параметры!$B$2,Данные!$E$2:$E$341,Параметры!$B$4)} -> 0 | F2: {=SUMIFS(Данные!$D$2:$D$341,Данные!$B$2:$B$341,$A2,Данные!$F$2:$F$341,F$1,Данные!$A$2:$A$341,">="&Параметры!$B$1,Данные!$A$2:$A$341,"<="&Параметры!$B$2,Данные!$E$2:$E$341,Параметры!$B$4)} -> 0 | G2: {=SUMIFS(Данные!$D$2:$D$341,Данные!$B$2:$B$341,$A2,Данные!$F$2:$F$341,G$1,Данные!$A$2:$A$341,">="&Параметры!$B$1,Данные!$A$2:$A$341,"<="&Параметры!$B$2,Данные!$E$2:$E$341,Параметры!$B$4)} -> 0 | H2: {=SUMIFS(Данные!$D$2:$D$341,Данные!$B$2:$B$341,$A2,Данные!$F$2:$F$341,H$1,Данные!$A$2:$A$341,">="&Параметры!$B$1,Данные!$A$2:$A$341,"<="&Параметры!$B$2,Данные!$E$2:$E$341,Параметры!$B$4)} -> 0 | I2: {=SUMIFS(Данные!$D$2:$D$341,Данные!$B$2:$B$341,$A2,Данные!$F$2:$F$341,I$1,Данные!$A$2:$A$341,">="&Параметры!$B$1,Данные!$A$2:$A$341,"<="&Параметры!$B$2,Данные!$E$2:$E$341,Параметры!$B$4)} -> 0 | ... P2: {=SUMIFS(Данные!$D$2:$D$341,Данные!$B$2:$B$341,$A2,Данные!$F$2:$F$341,P$1,Данные!$A$2:$A$341,">="&Параметры!$B$1,Данные!$A$2:$A$341,"<="&Параметры!$B$2,Данные!$E$2:$E$341,Параметры!$B$4)} -> 0 | Q2: {=SUM(B2:P2)} -> 788324.44
A3: {=Статьи!A3} -> Чаи 1 | B3: {=SUMIFS(Данные!$D$2:$D$341,Данные!$B$2:$B$341,$A3,Данные!$F$2:$F$341,B$1,Данные!$A$2:$A$341,">="&Параметры!$B$1,Данные!$A$2:$A$341,"<="&Параметры!$B$2,Данные!$E$2:$E$341,Параметры!$B$4)} -> 0 | C3: {=SUMIFS(Данные!$D$2:$D$341,Данные!$B$2:$B$341,$A3,Данные!$F$2:$F$341,C$1,Данные!$A$2:$A$341,">="&Параметры!$B$1,Данные!$A$2:$A$341,"<="&Параметры!$B$2,Данные!$E$2:$E$341,Параметры!$B$4)} -> -21827.39 | D3: {=SUMIFS(Данные!$D$2:$D$341,Данные!$B$2:$B$341,$A3,Данные!$F$2:$F$341,D$1,Данные!$A$2:$A$341,">="&Параметры!$B$1,Данные!$A$2:$A$341,"<="&Параметры!$B$2,Данные!$E$2:$E$341,Параметры!$B$4)} -> 0 | E3: {=SUMIFS(Данные!$D$2:$D$341,Данные!$B$2:$B$341,$A3,Данные!$F$2:$F$341,E$1,Данные!$A$2:$A$341,">="&Параметры!$B$1,Данные!$A$2:$A$341,"<="&Параметры!$B$2,Данные!$E$2:$E$341,Параметры!$B$4)} -> 0 | F3: {=SUMIFS(Данные!$D$2:$D$341,Данные!$B$2:$B$341,$A3,Данные!$F$2:$F$341,F$1,Данные!$A$2:$A$341,">="&Параметры!$B$1,Данные!$A$2:$A$341,"<="&Параметры!$B$2,Данные!$E$2:$E$341,Параметры!$B$4)} -> 0 | G3: {=SUMIFS(Данные!$D$2:$D$341,Данные!$B$2:$B$341,$A3,Данные!$F$2:$F$341,G$1,Данные!$A$2:$A$341,">="&Параметры!$B$1,Данные!$A$2:$A$341,"<="&Параметры!$B$2,Данные!$E$2:$E$341,Параметры!$B$4)} -> 635132.9 | H3: {=SUMIFS(Данные!$D$2:$D$341,Данные!$B$2:$B$341,$A3,Данные!$F$2:$F$341,H$1,Данные!$A$2:$A$341,">="&Параметры!$B$1,Данные!$A$2:$A$341,"<="&Параметры!$B$2,Данные!$E$2:$E$341,Параметры!$B$4)} -> 0 | I3: {=SUMIFS(Данные!$D$2:$D$341,Данные!$B$2:$B$341,$A3,Данные!$F$2:$F$341,I$1,Данные!$A$2:$A$341,">="&Параметры!$B$1,Данные!$A$2:$A$341,"<="&Параметры!$B$2,Данные!$E$2:$E$341,Параметры!$B$4)} -> -6678.65 | ... P3: {=SUMIFS(Данные!$D$2:$D$341,Данные!$B$2:$B$341,$A3,Данные!$F$2:$F$341,P$1,Данные!$A$2:$A$341,">="&Параметры!$B$1,Данные!$A$2:$A$341,"<="&Параметры!$B$2,Данные!$E$2:$E$341,Параметры!$B$4)} -> 0 | Q3: {=SUM(B3:P3)} -> 1345676.9
A4: {=Статьи!A4} -> Ёлка 1 | B4: {=SUMIFS(Данные!$D$2:$D$341,Данные!$B$2:$B$341,$A4,Данные!$F$2:$F$341,B$1,Данные!$A$2:$A$341,">="&Параметры!$B$1,Данные!$A$2:$A$341,"<="&Параметры!$B$2,Данные!$E$2:$E$341,Параметры!$B$4)} -> 0 | C4: {=SUMIFS(Данные!$D$2:$D$341,Данные!$B$2:$B$341,$A4,Данные!$F$2:$F$341,C$1,Данные!$A$2:$A$341,">="&Параметры!$B$1,Данные!$A$2:$A$341,"<="&Параметры!$B$2,Данные!$E$2:$E$341,Параметры!$B$4)} -> 0 | D4: {=SUMIFS(Данные!$D$2:$D$341,Данные!$B$2:$B$341,$A4,Данные!$F$2:$F$341,D$1,Данные!$A$2:$A$341,">="&Параметры!$B$1,Данные!$A$2:$A$341,"<="&Параметры!$B$2,Данные!$E$2:$E$341,Параметры!$B$4)} -> 0 | E4: {=SUMIFS(Данные!$D$2:$D$341,Данные!$B$2:$B$341,$A4,Данные!$F$2:$F$341,E$1,Данные!$A$2:$A$341,">="&Параметры!$B$1,Данные!$A$2:$A$341,"<="&Параметры!$B$2,Данные!$E$2:$E$341,Параметры!$B$4)} -> 0 | F4: {=SUMIFS(Данные!$D$2:$D$341,Данные!$B$2:$B$341,$A4,Данные!$F$2:$F$341,F$1,Данные!$A$2:$A$341,">="&Параметры!$B$1,Данные!$A$2:$A$341,"<="&Параметры!$B$2,Данные!$E$2:$E$341,Параметры!$B$4)} -> 0 | G4: {=SUMIFS(Данные!$D$2:$D$341,Данные!$B$2:$B$341,$A4,Данные!$F$2:$F$341,G$1,Данные!$A$2:$A$341,">="&Параметры!$B$1,Данные!$A$2:$A$341,"<="&Параметры!$B$2,Данные!$E$2:$E$341,Параметры!$B$4)} -> 222968.2 | H4: {=SUMIFS(Данные!$D$2:$D$341,Данные!$B$2:$B$341,$A4,Данные!$F$2:$F$341,H$1,Данные!$A$2:$A$341,">="&Параметры!$B$1,Данные!$A$2:$A$341,"<="&Параметры!$B$2,Данные!$E$2:$E$341,Параметры!$B$4)} -> 0 | I4: {=SUMIFS(Данные!$D$2:$D$341,Данные!$B$2:$B$341,$A4,Данные!$F$2:$F$341,I$1,Данные!$A$2:$A$341,">="&Параметры!$B$1,Данные!$A$2:$A$341,"<="&Параметры!$B$2,Данные!$E$2:$E$341,Параметры!$B$4)} -> 0 | ... P4: {=SUMIFS(Данные!$D$2:$D$341,Данные!$B$2:$B$341,$A4,Данные!$F$2:$F$341,P$1,Данные!$A$2:$A$341,">="&Параметры!$B$1,Данные!$A$2:$A$341,"<="&Параметры!$B$2,Данные!$E$2:$E$341,Параметры!$B$4)} -> 22033.51 | Q4: {=SUM(B4:P4)} -> 245001.71
A5: {=Статьи!A5} -> Елка 1 | B5: {=SUMIFS(Данные!$D$2:$D$341,Данные!$B$2:$B$341,$A5,Данные!$F$2:$F$341,B$1,Данные!$A$2:$A$341,">="&Параметры!$B$1,Данные!$A$2:$A$341,"<="&Параметры!$B$2,Данные!$E$2:$E$341,Параметры!$B$4)} -> 0 | C5: {=SUMIFS(Данные!$D$2:$D$341,Данные!$B$2:$B$341,$A5,Данные!$F$2:$F$341,C$1,Данные!$A$2:$A$341,">="&Параметры!$B$1,Данные!$A$2:$A$341,"<="&Параметры!$B$2,Данные!$E$2:$E$341,Параметры!$B$4)} -> 230678.07 | D5: {=SUMIFS(Данные!$D$2:$D$341,Данные!$B$2:$B$341,$A5,Данные!$F$2:$F$341,D$1,Данные!$A$2:$A$341,">="&Параметры!$B$1,Данные!$A$2:$A$341,"<="&Параметры!$B$2,Данные!$E$2:$E$341,Параметры!$B$4)} -> 0 | E5: {=SUMIFS(Данные!$D$2:$D$341,Данные!$B$2:$B$341,$A5,Данные!$F$2:$F$341,E$1,Данные!$A$2:$A$341,">="&Параметры!$B$1,Данные!$A$2:$A$341,"<="&Параметры!$B$2,Данные!$E$2:$E$341,Параметры!$B$4)} -> 147133.95 | F5: {=SUMIFS(Данные!$D$2:$D$341,Данные!$B$2:$B$341,$A5,Данные!$F$2:$F$341,F$1,Данные!$A$2:$A$341,">="&Параметры!$B$1,Данные!$A$2:$A$341,"<="&Параметры!$B$2,Данные!$E$2:$E$341,Параметры!$B$4)} -> -73227.26 | G5: {=SUMIFS(Данные!$D$2:$D$341,Данные!$B$2:$B$341,$A5,Данные!$F$2:$F$341,G$1,Данные!$A$2:$A$341,">="&Параметры!$B$1,Данные!$A$2:$A$341,"<="&Параметры!$B$2,Данные!$E$2:$E$341,Параметры!$B$4)} -> 285461.58 | H5: {=SUMIFS(Данные!$D$2:$D$341,Данные!$B$2:$B$341,$A5,Данные!$F$2:$F$341,H$1,Данные!$A$2:$A$341,">="&Параметры!$B$1,Данные!$A$2:$A$341,"<="&Параметры!$B$2,Данные!$E$2:$E$341,Параметры!$B$4)} -> 142440.89 | I5: {=SUMIFS(Данные!$D$2:$D$341,Данные!$B$2:$B$341,$A5,Данные!$F$2:$F$341,I$1,Данные!$A$2:$A$341,">="&Параметры!$B$1,Данные!$A$2:$A$341,"<="&Параметры!$B$2,Данные!$E$2:$E$341,Параметры!$B$4)} -> 0 | ... P5: {=SUMIFS(Данные!$D$2:$D$341,Данные!$B$2:$B$341,$A5,Данные!$F$2:$F$341,P$1,Данные!$A$2:$A$341,">="&Параметры!$B$1,Данные!$A$2:$A$341,"<="&Параметры!$B$2,Данные!$E$2:$E$341,Параметры!$B$4)} -> 0 | Q5: {=SUM(B5:P5)} -> 732487.23
A6: {=Статьи!A6} -> Аренда 1 | B6: {=SUMIFS(Данные!$D$2:$D$341,Данные!$B$2:$B$341,$A6,Данные!$F$2:$F$341,B$1,Данные!$A$2:$A$341,">="&Параметры!$B$1,Данные!$A$2:$A$341,"<="&Параметры!$B$2,Данные!$E$2:$E$341,Параметры!$B$4)} -> 345306.23 | C6: {=SUMIFS(Данные!$D$2:$D$341,Данные!$B$2:$B$341,$A6,Данные!$F$2:$F$341,C$1,Данные!$A$2:$A$341,">="&Параметры!$B$1,Данные!$A$2:$A$341,"<="&Параметры!$B$2,Данные!$E$2:$E$341,Параметры!$B$4)} -> 0 | D6: {=SUMIFS(Данные!$D$2:$D$341,Данные!$B$2:$B$341,$A6,Данные!$F$2:$F$341,D$1,Данные!$A$2:$A$341,">="&Параметры!$B$1,Данные!$A$2:$A$341,"<="&Параметры!$B$2,Данные!$E$2:$E$341,Параметры!$B$4)} -> 0 | E6: {=SUMIFS(Данные!$D$2:$D$341,Данные!$B$2:$B$341,$A6,Данные!$F$2:$F$341,E$1,Данные!$A$2:$A$341,">="&Параметры!$B$1,Данные!$A$2:$A$341,"<="&Параметры!$B$2,Данные!$E$2:$E$341,Параметры!$B$4)} -> 0 | F6: {=SUMIFS(Данные!$D$2:$D$341,Данные!$B$2:$B$341,$A6,Данные!$F$2:$F$341,F$1,Данные!$A$2:$A$341,">="&Параметры!$B$1,Данные!$A$2:$A$341,"<="&Параметры!$B$2,Данные!$E$2:$E$341,Параметры!$B$4)} -> 0 | G6: {=SUMIFS(Данные!$D$2:$D$341,Данные!$B$2:$B$341,$A6,Данные!$F$2:$F$341,G$1,Данные!$A$2:$A$341,">="&Параметры!$B$1,Данные!$A$2:$A$341,"<="&Параметры!$B$2,Данные!$E$2:$E$341,Параметры!$B$4)} -> 0 | H6: {=SUMIFS(Данные!$D$2:$D$341,Данные!$B$2:$B$341,$A6,Данные!$F$2:$F$341,H$1,Данные!$A$2:$A$341,">="&Параметры!$B$1,Данные!$A$2:$A$341,"<="&Параметры!$B$2,Данные!$E$2:$E$341,Параметры!$B$4)} -> 0 | I6: {=SUMIFS(Данные!$D$2:$D$341,Данные!$B$2:$B$341,$A6,Данные!$F$2:$F$341,I$1,Данные!$A$2:$A$341,">="&Параметры!$B$1,Данные!$A$2:$A$341,"<="&Параметры!$B$2,Данные!$E$2:$E$341,Параметры!$B$4)} -> 0 | ... P6: {=SUMIFS(Данные!$D$2:$D$341,Данные!$B$2:$B$341,$A6,Данные!$F$2:$F$341,P$1,Данные!$A$2:$A$341,">="&Параметры!$B$1,Данные!$A$2:$A$341,"<="&Параметры!$B$2,Данные!$E$2:$E$341,Параметры!$B$4)} -> 0 | Q6: {=SUM(B6:P6)} -> 552992.4
A7: Итого группа 1 | B7: {=SUM(B2:B6)} -> 345306.23 | C7: {=SUM(C2:C6)} -> 483898.62 | D7: {=SUM(D2:D6)} -> 0 | E7: {=SUM(E2:E6)} -> 147133.95 | F7: {=SUM(F2:F6)} -> -73227.26 | G7: {=SUM(G2:G6)} -> 1143562.7 | H7: {=SUM(H2:H6)} -> 142440.89 | I7: {=SUM(I2:I6)} -> -6678.65 | ... Q7: {=SUM(Q2:Q6)} -> 3664482.7
A8: {=Статьи!A7} -> Связь 1 | B8: {=SUMIFS(Данные!$D$2:$D$341,Данные!$B$2:$B$341,$A8,Данные!$F$2:$F$341,B$1,Данные!$A$2:$A$341,">="&Параметры!$B$1,Данные!$A$2:$A$341,"<="&Параметры!$B$2,Данные!$E$2:$E$341,Параметры!$B$4)} -> 0 | C8: {=SUMIFS(Данные!$D$2:$D$341,Данные!$B$2:$B$341,$A8,Данные!$F$2:$F$341,C$1,Данные!$A$2:$A$341,">="&Параметры!$B$1,Данные!$A$2:$A$341,"<="&Параметры!$B$2,Данные!$E$2:$E$341,Параметры!$B$4)} -> 0 | D8: {=SUMIFS(Данные!$D$2:$D$341,Данные!$B$2:$B$341,$A8,Данные!$F$2:$F$341,D$1,Данные!$A$2:$A$341,">="&Параметры!$B$1,Данные!$A$2:$A$341,"<="&Параметры!$B$2,Данные!$E$2:$E$341,Параметры!$B$4)} -> 78369.71 | E8: {=SUMIFS(Данные!$D$2:$D$341,Данные!$B$2:$B$341,$A8,Данные!$F$2:$F$341,E$1,Данные!$A$2:$A$341,">="&Параметры!$B$1,Данные!$A$2:$A$341,"<="&Параметры!$B$2,Данные!$E$2:$E$341,Параметры!$B$4)} -> 290338.51 | F8: {=SUMIFS(Данные!$D$2:$D$341,Данные!$B$2:$B$341,$A8,Данные!$F$2:$F$341,F$1,Данные!$A$2:$A$341,">="&Параметры!$B$1,Данные!$A$2:$A$341,"<="&Параметры!$B$2,Данные!$E$2:$E$341,Параметры!$B$4)} -> 0 | G8: {=SUMIFS(Данные!$D$2:$D$341,Данные!$B$2:$B$341,$A8,Данные!$F$2:$F$341,G$1,Данные!$A$2:$A$341,">="&Параметры!$B$1,Данные!$A$2:$A$341,"<="&Параметры!$B$2,Данные!$E$2:$E$341,Параметры!$B$4)} -> 0 | H8: {=SUMIFS(Данные!$D$2:$D$341,Данные!$B$2:$B$341,$A8,Данные!$F$2:$F$341,H$1,Данные!$A$2:$A$341,">="&Параметры!$B$1,Данные!$A$2:$A$341,"<="&Параметры!$B$2,Данные!$E$2:$E$341,Параметры!$B$4)} -> 0 | I8: {=SUMIFS(Данные!$D$2:$D$341,Данные!$B$2:$B$341,$A8,Данные!$F$2:$F$341,I$1,Данные!$A$2:$A$341,">="&Параметры!$B$1,Данные!$A$2:$A$341,"<="&Параметры!$B$2,Данные!$E$2:$E$341,Параметры!$B$4)} -> 0 | ... P8: {=SUMIFS(Данные!$D$2:$D$341,Данные!$B$2:$B$341,$A8,Данные!$F$2:$F$341,P$1,Данные!$A$2:$A$341,">="&Параметры!$B$1,Данные!$A$2:$A$341,"<="&Параметры!$B$2,Данные!$E$2:$E$341,Параметры!$B$4)} -> 0 | Q8: {=SUM(B8:P8)} -> 589986.43
A9: {=Статьи!A8} -> Налог 1 | B9: {=SUMIFS(Данные!$D$2:$D$341,Данные!$B$2:$B$341,$A9,Данные!$F$2:$F$341,B$1,Данные!$A$2:$A$341,">="&Параметры!$B$1,Данные!$A$2:$A$341,"<="&Параметры!$B$2,Данные!$E$2:$E$341,Параметры!$B$4)} -> 0 | C9: {=SUMIFS(Данные!$D$2:$D$341,Данные!$B$2:$B$341,$A9,Данные!$F$2:$F$341,C$1,Данные!$A$2:$A$341,">="&Параметры!$B$1,Данные!$A$2:$A$341,"<="&Параметры!$B$2,Данные!$E$2:$E$341,Параметры!$B$4)} -> 24606.32 | D9: {=SUMIFS(Данные!$D$2:$D$341,Данные!$B$2:$B$341,$A9,Данные!$F$2:$F$341,D$1,Данные!$A$2:$A$341,">="&Параметры!$B$1,Данные!$A$2:$A$341,"<="&Параметры!$B$2,Данные!$E$2:$E$341,Параметры!$B$4)} -> 0 | E9: {=SUMIFS(Данные!$D$2:$D$341,Данные!$B$2:$B$341,$A9,Данные!$F$2:$F$341,E$1,Данные!$A$2:$A$341,">="&Параметры!$B$1,Данные!$A$2:$A$341,"<="&Параметры!$B$2,Данные!$E$2:$E$341,Параметры!$B$4)} -> 94760.89 | F9: {=SUMIFS(Данные!$D$2:$D$341,Данные!$B$2:$B$341,$A9,Данные!$F$2:$F$341,F$1,Данные!$A$2:$A$341,">="&Параметры!$B$1,Данные!$A$2:$A$341,"<="&Параметры!$B$2,Данные!$E$2:$E$341,Параметры!$B$4)} -> 0 | G9: {=SUMIFS(Данные!$D$2:$D$341,Данные!$B$2:$B$341,$A9,Данные!$F$2:$F$341,G$1,Данные!$A$2:$A$341,">="&Параметры!$B$1,Данные!$A$2:$A$341,"<="&Параметры!$B$2,Данные!$E$2:$E$341,Параметры!$B$4)} -> 0 | H9: {=SUMIFS(Данные!$D$2:$D$341,Данные!$B$2:$B$341,$A9,Данные!$F$2:$F$341,H$1,Данные!$A$2:$A$341,">="&Параметры!$B$1,Данные!$A$2:$A$341,"<="&Параметры!$B$2,Данные!$E$2:$E$341,Параметры!$B$4)} -> 0 | I9: {=SUMIFS(Данные!$D$2:$D$341,Данные!$B$2:$B$341,$A9,Данные!$F$2:$F$341,I$1,Данные!$A$2:$A$341,">="&Параметры!$B$1,Данные!$A$2:$A$341,"<="&Параметры!$B$2,Данные!$E$2:$E$341,Параметры!$B$4)} -> 0 | ... P9: {=SUMIFS(Данные!$D$2:$D$341,Данные!$B$2:$B$341,$A9,Данные!$F$2:$F$341,P$1,Данные!$A$2:$A$341,">="&Параметры!$B$1,Данные!$A$2:$A$341,"<="&Параметры!$B$2,Данные!$E$2:$E$341,Параметры!$B$4)} -> 0 | Q9: {=SUM(B9:P9)} -> 458743.56
A10: {=Статьи!A9} -> Доход 1 | B10: {=SUMIFS(Данные!$D$2:$D$341,Данные!$B$2:$B$341,$A10,Данные!$F$2:$F$341,B$1,Данные!$A$2:$A$341,">="&Параметры!$B$1,Данные!$A$2:$A$341,"<="&Параметры!$B$2,Данные!$E$2:$E$341,Параметры!$B$4)} -> 242812.16 | C10: {=SUMIFS(Данные!$D$2:$D$341,Данные!$B$2:$B$341,$A10,Данные!$F$2:$F$341,C$1,Данные!$A$2:$A$341,">="&Параметры!$B$1,Данные!$A$2:$A$341,"<="&Параметры!$B$2,Данные!$E$2:$E$341,Параметры!$B$4)} -> 0 | D10: {=SUMIFS(Данные!$D$2:$D$341,Данные!$B$2:$B$341,$A10,Данные!$F$2:$F$341,D$1,Данные!$A$2:$A$341,">="&Параметры!$B$1,Данные!$A$2:$A$341,"<="&Параметры!$B$2,Данные!$E$2:$E$341,Параметры!$B$4)} -> 147137.49 | E10: {=SUMIFS(Данные!$D$2:$D$341,Данные!$B$2:$B$341,$A10,Данные!$F$2:$F$341,E$1,Данные!$A$2:$A$341,">="&Параметры!$B$1,Данные!$A$2:$A$341,"<="&Параметры!$B$2,Данные!$E$2:$E$341,Параметры!$B$4)} -> 0 | F10: {=SUMIFS(Данные!$D$2:$D$341,Данные!$B$2:$B$341,$A10,Данные!$F$2:$F$341,F$1,Данные!$A$2:$A$341,">="&Параметры!$B$1,Данные!$A$2:$A$341,"<="&Параметры!$B$2,Данные!$E$2:$E$341,Параметры!$B$4)} -> 0 | G10: {=SUMIFS(Данные!$D$2:$D$341,Данные!$B$2:$B$341,$A10,Данные!$F$2:$F$341,G$1,Данные!$A$2:$A$341,">="&Параметры!$B$1,Данные!$A$2:$A$341,"<="&Параметры!$B$2,Данные!$E$2:$E$341,Параметры!$B$4)} -> 0 | H10: {=SUMIFS(Данные!$D$2:$D$341,Данные!$B$2:$B$341,$A10,Данные!$F$2:$F$341,H$1,Данные!$A$2:$A$341,">="&Параметры!$B$1,Данные!$A$2:$A$341,"<="&Параметры!$B$2,Данные!$E$2:$E$341,Параметры!$B$4)} -> 0 | I10: {=SUMIFS(Данные!$D$2:$D$341,Данные!$B$2:$B$341,$A10,Данные!$F$2:$F$341,I$1,Данные!$A$2:$A$341,">="&Параметры!$B$1,Данные!$A$2:$A$341,"<="&Параметры!$B$2,Данные!$E$2:$E$341,Параметры!$B$4)} -> 0 | ... P10: {=SUMIFS(Данные!$D$2:$D$341,Данные!$B$2:$B$341,$A10,Данные!$F$2:$F$341,P$1,Данные!$A$2:$A$341,">="&Параметры!$B$1,Данные!$A$2:$A$341,"<="&Параметры!$B$2,Данные!$E$2:$E$341,Параметры!$B$4)} -> 0 | Q10: {=SUM(B10:P10)} -> 776275.7
A11: {=Статьи!A10} -> Сырьё 1 | B11: {=SUMIFS(Данные!$D$2:$D$341,Данные!$B$2:$B$341,$A11,Данные!$F$2:$F$341,B$1,Данные!$A$2:$A$341,">="&Параметры!$B$1,Данные!$A$2:$A$341,"<="&Параметры!$B$2,Данные!$E$2:$E$341,Параметры!$B$4)} -> -11898.35 | C11: {=SUMIFS(Данные!$D$2:$D$341,Данные!$B$2:$B$341,$A11,Данные!$F$2:$F$341,C$1,Данные!$A$2:$A$341,">="&Параметры!$B$1,Данные!$A$2:$A$341,"<="&Параметры!$B$2,Данные!$E$2:$E$341,Параметры!$B$4)} -> 258321.64 | D11: {=SUMIFS(Данные!$D$2:$D$341,Данные!$B$2:$B$341,$A11,Данные!$F$2:$F$341,D$1,Данные!$A$2:$A$341,">="&Параметры!$B$1,Данные!$A$2:$A$341,"<="&Параметры!$B$2,Данные!$E$2:$E$341,Параметры!$B$4)} -> 326886.85 | E11: {=SUMIFS(Данные!$D$2:$D$341,Данные!$B$2:$B$341,$A11,Данные!$F$2:$F$341,E$1,Данные!$A$2:$A$341,">="&Параметры!$B$1,Данные!$A$2:$A$341,"<="&Параметры!$B$2,Данные!$E$2:$E$341,Параметры!$B$4)} -> 160679.83 | F11: {=SUMIFS(Данные!$D$2:$D$341,Данные!$B$2:$B$341,$A11,Данные!$F$2:$F$341,F$1,Данные!$A$2:$A$341,">="&Параметры!$B$1,Данные!$A$2:$A$341,"<="&Параметры!$B$2,Данные!$E$2:$E$341,Параметры!$B$4)} -> 207081.28 | G11: {=SUMIFS(Данные!$D$2:$D$341,Данные!$B$2:$B$341,$A11,Данные!$F$2:$F$341,G$1,Данные!$A$2:$A$341,">="&Параметры!$B$1,Данные!$A$2:$A$341,"<="&Параметры!$B$2,Данные!$E$2:$E$341,Параметры!$B$4)} -> 0 | H11: {=SUMIFS(Данные!$D$2:$D$341,Данные!$B$2:$B$341,$A11,Данные!$F$2:$F$341,H$1,Данные!$A$2:$A$341,">="&Параметры!$B$1,Данные!$A$2:$A$341,"<="&Параметры!$B$2,Данные!$E$2:$E$341,Параметры!$B$4)} -> 0 | I11: {=SUMIFS(Данные!$D$2:$D$341,Данные!$B$2:$B$341,$A11,Данные!$F$2:$F$341,I$1,Данные!$A$2:$A$341,">="&Параметры!$B$1,Данные!$A$2:$A$341,"<="&Параметры!$B$2,Данные!$E$2:$E$341,Параметры!$B$4)} -> 0 | ... P11: {=SUMIFS(Данные!$D$2:$D$341,Данные!$B$2:$B$341,$A11,Данные!$F$2:$F$341,P$1,Данные!$A$2:$A$341,">="&Параметры!$B$1,Данные!$A$2:$A$341,"<="&Параметры!$B$2,Данные!$E$2:$E$341,Параметры!$B$4)} -> 53759.45 | Q11: {=SUM(B11:P11)} -> 1344615.9
A12: {=Статьи!A11} -> Сырье 1 | B12: {=SUMIFS(Данные!$D$2:$D$341,Данные!$B$2:$B$341,$A12,Данные!$F$2:$F$341,B$1,Данные!$A$2:$A$341,">="&Параметры!$B$1,Данные!$A$2:$A$341,"<="&Параметры!$B$2,Данные!$E$2:$E$341,Параметры!$B$4)} -> 0 | C12: {=SUMIFS(Данные!$D$2:$D$341,Данные!$B$2:$B$341,$A12,Данные!$F$2:$F$341,C$1,Данные!$A$2:$A$341,">="&Параметры!$B$1,Данные!$A$2:$A$341,"<="&Параметры!$B$2,Данные!$E$2:$E$341,Параметры!$B$4)} -> -31559.73 | D12: {=SUMIFS(Данные!$D$2:$D$341,Данные!$B$2:$B$341,$A12,Данные!$F$2:$F$341,D$1,Данные!$A$2:$A$341,">="&Параметры!$B$1,Данные!$A$2:$A$341,"<="&Параметры!$B$2,Данные!$E$2:$E$341,Параметры!$B$4)} -> 0 | E12: {=SUMIFS(Данные!$D$2:$D$341,Данные!$B$2:$B$341,$A12,Данные!$F$2:$F$341,E$1,Данные!$A$2:$A$341,">="&Параметры!$B$1,Данные!$A$2:$A$341,"<="&Параметры!$B$2,Данные!$E$2:$E$341,Параметры!$B$4)} -> 0 | F12: {=SUMIFS(Данные!$D$2:$D$341,Данные!$B$2:$B$341,$A12,Данные!$F$2:$F$341,F$1,Данные!$A$2:$A$341,">="&Параметры!$B$1,Данные!$A$2:$A$341,"<="&Параметры!$B$2,Данные!$E$2:$E$341,Параметры!$B$4)} -> 0 | G12: {=SUMIFS(Данные!$D$2:$D$341,Данные!$B$2:$B$341,$A12,Данные!$F$2:$F$341,G$1,Данные!$A$2:$A$341,">="&Параметры!$B$1,Данные!$A$2:$A$341,"<="&Параметры!$B$2,Данные!$E$2:$E$341,Параметры!$B$4)} -> 0 | H12: {=SUMIFS(Данные!$D$2:$D$341,Данные!$B$2:$B$341,$A12,Данные!$F$2:$F$341,H$1,Данные!$A$2:$A$341,">="&Параметры!$B$1,Данные!$A$2:$A$341,"<="&Параметры!$B$2,Данные!$E$2:$E$341,Параметры!$B$4)} -> 212505.77 | I12: {=SUMIFS(Данные!$D$2:$D$341,Данные!$B$2:$B$341,$A12,Данные!$F$2:$F$341,I$1,Данные!$A$2:$A$341,">="&Параметры!$B$1,Данные!$A$2:$A$341,"<="&Параметры!$B$2,Данные!$E$2:$E$341,Параметры!$B$4)} -> -7891.15 | ... P12: {=SUMIFS(Данные!$D$2:$D$341,Данные!$B$2:$B$341,$A12,Данные!$F$2:$F$341,P$1,Данные!$A$2:$A$341,">="&Параметры!$B$1,Данные!$A$2:$A$341,"<="&Параметры!$B$2,Данные!$E$2:$E$341,Параметры!$B$4)} -> 0 | Q12: {=SUM(B12:P12)} -> 206419.52
A13: Итого группа 2 | B13: {=SUM(B8:B12)} -> 230913.81 | C13: {=SUM(C8:C12)} -> 251368.23 | D13: {=SUM(D8:D12)} -> 552394.05 | E13: {=SUM(E8:E12)} -> 545779.23 | F13: {=SUM(F8:F12)} -> 207081.28 | G13: {=SUM(G8:G12)} -> 0 | H13: {=SUM(H8:H12)} -> 212505.77 | I13: {=SUM(I8:I12)} -> -7891.15 | ... Q13: {=SUM(Q8:Q12)} -> 3376041.1
A14: {=Статьи!A12} -> Чай 2 | B14: {=SUMIFS(Данные!$D$2:$D$341,Данные!$B$2:$B$341,$A14,Данные!$F$2:$F$341,B$1,Данные!$A$2:$A$341,">="&Параметры!$B$1,Данные!$A$2:$A$341,"<="&Параметры!$B$2,Данные!$E$2:$E$341,Параметры!$B$4)} -> 0 | C14: {=SUMIFS(Данные!$D$2:$D$341,Данные!$B$2:$B$341,$A14,Данные!$F$2:$F$341,C$1,Данные!$A$2:$A$341,">="&Параметры!$B$1,Данные!$A$2:$A$341,"<="&Параметры!$B$2,Данные!$E$2:$E$341,Параметры!$B$4)} -> 321586.93 | D14: {=SUMIFS(Данные!$D$2:$D$341,Данные!$B$2:$B$341,$A14,Данные!$F$2:$F$341,D$1,Данные!$A$2:$A$341,">="&Параметры!$B$1,Данные!$A$2:$A$341,"<="&Параметры!$B$2,Данные!$E$2:$E$341,Параметры!$B$4)} -> 0 | E14: {=SUMIFS(Данные!$D$2:$D$341,Данные!$B$2:$B$341,$A14,Данные!$F$2:$F$341,E$1,Данные!$A$2:$A$341,">="&Параметры!$B$1,Данные!$A$2:$A$341,"<="&Параметры!$B$2,Данные!$E$2:$E$341,Параметры!$B$4)} -> 0 | F14: {=SUMIFS(Данные!$D$2:$D$341,Данные!$B$2:$B$341,$A14,Данные!$F$2:$F$341,F$1,Данные!$A$2:$A$341,">="&Параметры!$B$1,Данные!$A$2:$A$341,"<="&Параметры!$B$2,Данные!$E$2:$E$341,Параметры!$B$4)} -> 261512.61 | G14: {=SUMIFS(Данные!$D$2:$D$341,Данные!$B$2:$B$341,$A14,Данные!$F$2:$F$341,G$1,Данные!$A$2:$A$341,">="&Параметры!$B$1,Данные!$A$2:$A$341,"<="&Параметры!$B$2,Данные!$E$2:$E$341,Параметры!$B$4)} -> 0 | H14: {=SUMIFS(Данные!$D$2:$D$341,Данные!$B$2:$B$341,$A14,Данные!$F$2:$F$341,H$1,Данные!$A$2:$A$341,">="&Параметры!$B$1,Данные!$A$2:$A$341,"<="&Параметры!$B$2,Данные!$E$2:$E$341,Параметры!$B$4)} -> 0 | I14: {=SUMIFS(Данные!$D$2:$D$341,Данные!$B$2:$B$341,$A14,Данные!$F$2:$F$341,I$1,Данные!$A$2:$A$341,">="&Параметры!$B$1,Данные!$A$2:$A$341,"<="&Параметры!$B$2,Данные!$E$2:$E$341,Параметры!$B$4)} -> -29513.86 | ... P14: {=SUMIFS(Данные!$D$2:$D$341,Данные!$B$2:$B$341,$A14,Данные!$F$2:$F$341,P$1,Данные!$A$2:$A$341,">="&Параметры!$B$1,Данные!$A$2:$A$341,"<="&Параметры!$B$2,Данные!$E$2:$E$341,Параметры!$B$4)} -> 0 | Q14: {=SUM(B14:P14)} -> 1536173.7
A15: {=Статьи!A13} -> Чаи 2 | B15: {=SUMIFS(Данные!$D$2:$D$341,Данные!$B$2:$B$341,$A15,Данные!$F$2:$F$341,B$1,Данные!$A$2:$A$341,">="&Параметры!$B$1,Данные!$A$2:$A$341,"<="&Параметры!$B$2,Данные!$E$2:$E$341,Параметры!$B$4)} -> 0 | C15: {=SUMIFS(Данные!$D$2:$D$341,Данные!$B$2:$B$341,$A15,Данные!$F$2:$F$341,C$1,Данные!$A$2:$A$341,">="&Параметры!$B$1,Данные!$A$2:$A$341,"<="&Параметры!$B$2,Данные!$E$2:$E$341,Параметры!$B$4)} -> 0 | D15: {=SUMIFS(Данные!$D$2:$D$341,Данные!$B$2:$B$341,$A15,Данные!$F$2:$F$341,D$1,Данные!$A$2:$A$341,">="&Параметры!$B$1,Данные!$A$2:$A$341,"<="&Параметры!$B$2,Данные!$E$2:$E$341,Параметры!$B$4)} -> 73165.31 | E15: {=SUMIFS(Данные!$D$2:$D$341,Данные!$B$2:$B$341,$A15,Данные!$F$2:$F$341,E$1,Данные!$A$2:$A$341,">="&Параметры!$B$1,Данные!$A$2:$A$341,"<="&Параметры!$B$2,Данные!$E$2:$E$341,Параметры!$B$4)} -> 0 | F15: {=SUMIFS(Данные!$D$2:$D$341,Данные!$B$2:$B$341,$A15,Данные!$F$2:$F$341,F$1,Данные!$A$2:$A$341,">="&Параметры!$B$1,Данные!$A$2:$A$341,"<="&Параметры!$B$2,Данные!$E$2:$E$341,Параметры!$B$4)} -> 0 | G15: {=SUMIFS(Данные!$D$2:$D$341,Данные!$B$2:$B$341,$A15,Данные!$F$2:$F$341,G$1,Данные!$A$2:$A$341,">="&Параметры!$B$1,Данные!$A$2:$A$341,"<="&Параметры!$B$2,Данные!$E$2:$E$341,Параметры!$B$4)} -> 0 | H15: {=SUMIFS(Данные!$D$2:$D$341,Данные!$B$2:$B$341,$A15,Данные!$F$2:$F$341,H$1,Данные!$A$2:$A$341,">="&Параметры!$B$1,Данные!$A$2:$A$341,"<="&Параметры!$B$2,Данные!$E$2:$E$341,Параметры!$B$4)} -> 0 | I15: {=SUMIFS(Данные!$D$2:$D$341,Данные!$B$2:$B$341,$A15,Данные!$F$2:$F$341,I$1,Данные!$A$2:$A$341,">="&Параметры!$B$1,Данные!$A$2:$A$341,"<="&Параметры!$B$2,Данные!$E$2:$E$341,Параметры!$B$4)} -> 261256.09 | ... P15: {=SUMIFS(Данные!$D$2:$D$341,Данные!$B$2:$B$341,$A15,Данные!$F$2:$F$341,P$1,Данные!$A$2:$A$341,">="&Параметры!$B$1,Данные!$A$2:$A$341,"<="&Параметры!$B$2,Данные!$E$2:$E$341,Параметры!$B$4)} -> 0 | Q15: {=SUM(B15:P15)} -> 334421.4
A16: {=Статьи!A14} -> Ёлка 2 | B16: {=SUMIFS(Данные!$D$2:$D$341,Данные!$B$2:$B$341,$A16,Данные!$F$2:$F$341,B$1,Данные!$A$2:$A$341,">="&Параметры!$B$1,Данные!$A$2:$A$341,"<="&Параметры!$B$2,Данные!$E$2:$E$341,Параметры!$B$4)} -> 0 | C16: {=SUMIFS(Данные!$D$2:$D$341,Данные!$B$2:$B$341,$A16,Данные!$F$2:$F$341,C$1,Данные!$A$2:$A$341,">="&Параметры!$B$1,Данные!$A$2:$A$341,"<="&Параметры!$B$2,Данные!$E$2:$E$341,Параметры!$B$4)} -> 17122.95 | D16: {=SUMIFS(Данные!$D$2:$D$341,Данные!$B$2:$B$341,$A16,Данные!$F$2:$F$341,D$1,Данные!$A$2:$A$341,">="&Параметры!$B$1,Данные!$A$2:$A$341,"<="&Параметры!$B$2,Данные!$E$2:$E$341,Параметры!$B$4)} -> 0 | E16: {=SUMIFS(Данные!$D$2:$D$341,Данные!$B$2:$B$341,$A16,Данные!$F$2:$F$341,E$1,Данные!$A$2:$A$341,">="&Параметры!$B$1,Данные!$A$2:$A$341,"<="&Параметры!$B$2,Данные!$E$2:$E$341,Параметры!$B$4)} -> 0 | F16: {=SUMIFS(Данные!$D$2:$D$341,Данные!$B$2:$B$341,$A16,Данные!$F$2:$F$341,F$1,Данные!$A$2:$A$341,">="&Параметры!$B$1,Данные!$A$2:$A$341,"<="&Параметры!$B$2,Данные!$E$2:$E$341,Параметры!$B$4)} -> -52645.57 | G16: {=SUMIFS(Данные!$D$2:$D$341,Данные!$B$2:$B$341,$A16,Данные!$F$2:$F$341,G$1,Данные!$A$2:$A$341,">="&Параметры!$B$1,Данные!$A$2:$A$341,"<="&Параметры!$B$2,Данные!$E$2:$E$341,Параметры!$B$4)} -> 70013.85 | H16: {=SUMIFS(Данные!$D$2:$D$341,Данные!$B$2:$B$341,$A16,Данные!$F$2:$F$341,H$1,Данные!$A$2:$A$341,">="&Параметры!$B$1,Данные!$A$2:$A$341,"<="&Параметры!$B$2,Данные!$E$2:$E$341,Параметры!$B$4)} -> 0 | I16: {=SUMIFS(Данные!$D$2:$D$341,Данные!$B$2:$B$341,$A16,Данные!$F$2:$F$341,I$1,Данные!$A$2:$A$341,">="&Параметры!$B$1,Данные!$A$2:$A$341,"<="&Параметры!$B$2,Данные!$E$2:$E$341,Параметры!$B$4)} -> 0 | ... P16: {=SUMIFS(Данные!$D$2:$D$341,Данные!$B$2:$B$341,$A16,Данные!$F$2:$F$341,P$1,Данные!$A$2:$A$341,">="&Параметры!$B$1,Данные!$A$2:$A$341,"<="&Параметры!$B$2,Данные!$E$2:$E$341,Параметры!$B$4)} -> 0 | Q16: {=SUM(B16:P16)} -> 260322.04
A17: {=Статьи!A15} -> Елка 2 | B17: {=SUMIFS(Данные!$D$2:$D$341,Данные!$B$2:$B$341,$A17,Данные!$F$2:$F$341,B$1,Данные!$A$2:$A$341,">="&Параметры!$B$1,Данные!$A$2:$A$341,"<="&Параметры!$B$2,Данные!$E$2:$E$341,Параметры!$B$4)} -> 0 | C17: {=SUMIFS(Данные!$D$2:$D$341,Данные!$B$2:$B$341,$A17,Данные!$F$2:$F$341,C$1,Данные!$A$2:$A$341,">="&Параметры!$B$1,Данные!$A$2:$A$341,"<="&Параметры!$B$2,Данные!$E$2:$E$341,Параметры!$B$4)} -> 0 | D17: {=SUMIFS(Данные!$D$2:$D$341,Данные!$B$2:$B$341,$A17,Данные!$F$2:$F$341,D$1,Данные!$A$2:$A$341,">="&Параметры!$B$1,Данные!$A$2:$A$341,"<="&Параметры!$B$2,Данные!$E$2:$E$341,Параметры!$B$4)} -> 0 | E17: {=SUMIFS(Данные!$D$2:$D$341,Данные!$B$2:$B$341,$A17,Данные!$F$2:$F$341,E$1,Данные!$A$2:$A$341,">="&Параметры!$B$1,Данные!$A$2:$A$341,"<="&Параметры!$B$2,Данные!$E$2:$E$341,Параметры!$B$4)} -> 0 | F17: {=SUMIFS(Данные!$D$2:$D$341,Данные!$B$2:$B$341,$A17,Данные!$F$2:$F$341,F$1,Данные!$A$2:$A$341,">="&Параметры!$B$1,Данные!$A$2:$A$341,"<="&Параметры!$B$2,Данные!$E$2:$E$341,Параметры!$B$4)} -> 0 | G17: {=SUMIFS(Данные!$D$2:$D$341,Данные!$B$2:$B$341,$A17,Данные!$F$2:$F$341,G$1,Данные!$A$2:$A$341,">="&Параметры!$B$1,Данные!$A$2:$A$341,"<="&Параметры!$B$2,Данные!$E$2:$E$341,Параметры!$B$4)} -> 0 | H17: {=SUMIFS(Данные!$D$2:$D$341,Данные!$B$2:$B$341,$A17,Данные!$F$2:$F$341,H$1,Данные!$A$2:$A$341,">="&Параметры!$B$1,Данные!$A$2:$A$341,"<="&Параметры!$B$2,Данные!$E$2:$E$341,Параметры!$B$4)} -> 0 | I17: {=SUMIFS(Данные!$D$2:$D$341,Данные!$B$2:$B$341,$A17,Данные!$F$2:$F$341,I$1,Данные!$A$2:$A$341,">="&Параметры!$B$1,Данные!$A$2:$A$341,"<="&Параметры!$B$2,Данные!$E$2:$E$341,Параметры!$B$4)} -> 0 | ... P17: {=SUMIFS(Данные!$D$2:$D$341,Данные!$B$2:$B$341,$A17,Данные!$F$2:$F$341,P$1,Данные!$A$2:$A$341,">="&Параметры!$B$1,Данные!$A$2:$A$341,"<="&Параметры!$B$2,Данные!$E$2:$E$341,Параметры!$B$4)} -> 0 | Q17: {=SUM(B17:P17)} -> 292044.24
A18: {=Статьи!A16} -> Аренда 2 | B18: {=SUMIFS(Данные!$D$2:$D$341,Данные!$B$2:$B$341,$A18,Данные!$F$2:$F$341,B$1,Данные!$A$2:$A$341,">="&Параметры!$B$1,Данные!$A$2:$A$341,"<="&Параметры!$B$2,Данные!$E$2:$E$341,Параметры!$B$4)} -> 204895.21 | C18: {=SUMIFS(Данные!$D$2:$D$341,Данные!$B$2:$B$341,$A18,Данные!$F$2:$F$341,C$1,Данные!$A$2:$A$341,">="&Параметры!$B$1,Данные!$A$2:$A$341,"<="&Параметры!$B$2,Данные!$E$2:$E$341,Параметры!$B$4)} -> 118667.62 | D18: {=SUMIFS(Данные!$D$2:$D$341,Данные!$B$2:$B$341,$A18,Данные!$F$2:$F$341,D$1,Данные!$A$2:$A$341,">="&Параметры!$B$1,Данные!$A$2:$A$341,"<="&Параметры!$B$2,Данные!$E$2:$E$341,Параметры!$B$4)} -> 0 | E18: {=SUMIFS(Данные!$D$2:$D$341,Данные!$B$2:$B$341,$A18,Данные!$F$2:$F$341,E$1,Данные!$A$2:$A$341,">="&Параметры!$B$1,Данные!$A$2:$A$341,"<="&Параметры!$B$2,Данные!$E$2:$E$341,Параметры!$B$4)} -> 0 | F18: {=SUMIFS(Данные!$D$2:$D$341,Данные!$B$2:$B$341,$A18,Данные!$F$2:$F$341,F$1,Данные!$A$2:$A$341,">="&Параметры!$B$1,Данные!$A$2:$A$341,"<="&Параметры!$B$2,Данные!$E$2:$E$341,Параметры!$B$4)} -> 0 | G18: {=SUMIFS(Данные!$D$2:$D$341,Данные!$B$2:$B$341,$A18,Данные!$F$2:$F$341,G$1,Данные!$A$2:$A$341,">="&Параметры!$B$1,Данные!$A$2:$A$341,"<="&Параметры!$B$2,Данные!$E$2:$E$341,Параметры!$B$4)} -> 0 | H18: {=SUMIFS(Данные!$D$2:$D$341,Данные!$B$2:$B$341,$A18,Данные!$F$2:$F$341,H$1,Данные!$A$2:$A$341,">="&Параметры!$B$1,Данные!$A$2:$A$341,"<="&Параметры!$B$2,Данные!$E$2:$E$341,Параметры!$B$4)} -> 0 | I18: {=SUMIFS(Данные!$D$2:$D$341,Данные!$B$2:$B$341,$A18,Данные!$F$2:$F$341,I$1,Данные!$A$2:$A$341,">="&Параметры!$B$1,Данные!$A$2:$A$341,"<="&Параметры!$B$2,Данные!$E$2:$E$341,Параметры!$B$4)} -> 0 | ... P18: {=SUMIFS(Данные!$D$2:$D$341,Данные!$B$2:$B$341,$A18,Данные!$F$2:$F$341,P$1,Данные!$A$2:$A$341,">="&Параметры!$B$1,Данные!$A$2:$A$341,"<="&Параметры!$B$2,Данные!$E$2:$E$341,Параметры!$B$4)} -> 0 | Q18: {=SUM(B18:P18)} -> 891941.73
A19: Итого группа 3 | B19: {=SUM(B14:B18)} -> 204895.21 | C19: {=SUM(C14:C18)} -> 457377.5 | D19: {=SUM(D14:D18)} -> 73165.31 | E19: {=SUM(E14:E18)} -> 0 | F19: {=SUM(F14:F18)} -> 208867.04 | G19: {=SUM(G14:G18)} -> 70013.85 | H19: {=SUM(H14:H18)} -> 0 | I19: {=SUM(I14:I18)} -> 231742.23 | ... Q19: {=SUM(Q14:Q18)} -> 3314903.1
A20: {=Статьи!A17} -> Связь 2 | B20: {=SUMIFS(Данные!$D$2:$D$341,Данные!$B$2:$B$341,$A20,Данные!$F$2:$F$341,B$1,Данные!$A$2:$A$341,">="&Параметры!$B$1,Данные!$A$2:$A$341,"<="&Параметры!$B$2,Данные!$E$2:$E$341,Параметры!$B$4)} -> 0 | C20: {=SUMIFS(Данные!$D$2:$D$341,Данные!$B$2:$B$341,$A20,Данные!$F$2:$F$341,C$1,Данные!$A$2:$A$341,">="&Параметры!$B$1,Данные!$A$2:$A$341,"<="&Параметры!$B$2,Данные!$E$2:$E$341,Параметры!$B$4)} -> 0 | D20: {=SUMIFS(Данные!$D$2:$D$341,Данные!$B$2:$B$341,$A20,Данные!$F$2:$F$341,D$1,Данные!$A$2:$A$341,">="&Параметры!$B$1,Данные!$A$2:$A$341,"<="&Параметры!$B$2,Данные!$E$2:$E$341,Параметры!$B$4)} -> 0 | E20: {=SUMIFS(Данные!$D$2:$D$341,Данные!$B$2:$B$341,$A20,Данные!$F$2:$F$341,E$1,Данные!$A$2:$A$341,">="&Параметры!$B$1,Данные!$A$2:$A$341,"<="&Параметры!$B$2,Данные!$E$2:$E$341,Параметры!$B$4)} -> -32180.28 | F20: {=SUMIFS(Данные!$D$2:$D$341,Данные!$B$2:$B$341,$A20,Данные!$F$2:$F$341,F$1,Данные!$A$2:$A$341,">="&Параметры!$B$1,Данные!$A$2:$A$341,"<="&Параметры!$B$2,Данные!$E$2:$E$341,Параметры!$B$4)} -> -65506.47 | G20: {=SUMIFS(Данные!$D$2:$D$341,Данные!$B$2:$B$341,$A20,Данные!$F$2:$F$341,G$1,Данные!$A$2:$A$341,">="&Параметры!$B$1,Данные!$A$2:$A$341,"<="&Параметры!$B$2,Данные!$E$2:$E$341,Параметры!$B$4)} -> 17079.28 | H20: {=SUMIFS(Данные!$D$2:$D$341,Данные!$B$2:$B$341,$A20,Данные!$F$2:$F$341,H$1,Данные!$A$2:$A$341,">="&Параметры!$B$1,Данные!$A$2:$A$341,"<="&Параметры!$B$2,Данные!$E$2:$E$341,Параметры!$B$4)} -> 0 | I20: {=SUMIFS(Данные!$D$2:$D$341,Данные!$B$2:$B$341,$A20,Данные!$F$2:$F$341,I$1,Данные!$A$2:$A$341,">="&Параметры!$B$1,Данные!$A$2:$A$341,"<="&Параметры!$B$2,Данные!$E$2:$E$341,Параметры!$B$4)} -> 0 | ... P20: {=SUMIFS(Данные!$D$2:$D$341,Данные!$B$2:$B$341,$A20,Данные!$F$2:$F$341,P$1,Данные!$A$2:$A$341,">="&Параметры!$B$1,Данные!$A$2:$A$341,"<="&Параметры!$B$2,Данные!$E$2:$E$341,Параметры!$B$4)} -> 0 | Q20: {=SUM(B20:P20)} -> -80607.47
A21: {=Статьи!A18} -> Налог 2 | B21: {=SUMIFS(Данные!$D$2:$D$341,Данные!$B$2:$B$341,$A21,Данные!$F$2:$F$341,B$1,Данные!$A$2:$A$341,">="&Параметры!$B$1,Данные!$A$2:$A$341,"<="&Параметры!$B$2,Данные!$E$2:$E$341,Параметры!$B$4)} -> 0 | C21: {=SUMIFS(Данные!$D$2:$D$341,Данные!$B$2:$B$341,$A21,Данные!$F$2:$F$341,C$1,Данные!$A$2:$A$341,">="&Параметры!$B$1,Данные!$A$2:$A$341,"<="&Параметры!$B$2,Данные!$E$2:$E$341,Параметры!$B$4)} -> 0 | D21: {=SUMIFS(Данные!$D$2:$D$341,Данные!$B$2:$B$341,$A21,Данные!$F$2:$F$341,D$1,Данные!$A$2:$A$341,">="&Параметры!$B$1,Данные!$A$2:$A$341,"<="&Параметры!$B$2,Данные!$E$2:$E$341,Параметры!$B$4)} -> 0 | E21: {=SUMIFS(Данные!$D$2:$D$341,Данные!$B$2:$B$341,$A21,Данные!$F$2:$F$341,E$1,Данные!$A$2:$A$341,">="&Параметры!$B$1,Данные!$A$2:$A$341,"<="&Параметры!$B$2,Данные!$E$2:$E$341,Параметры!$B$4)} -> -63273.16 | F21: {=SUMIFS(Данные!$D$2:$D$341,Данные!$B$2:$B$341,$A21,Данные!$F$2:$F$341,F$1,Данные!$A$2:$A$341,">="&Параметры!$B$1,Данные!$A$2:$A$341,"<="&Параметры!$B$2,Данные!$E$2:$E$341,Параметры!$B$4)} -> 502462.47 | G21: {=SUMIFS(Данные!$D$2:$D$341,Данные!$B$2:$B$341,$A21,Данные!$F$2:$F$341,G$1,Данные!$A$2:$A$341,">="&Параметры!$B$1,Данные!$A$2:$A$341,"<="&Параметры!$B$2,Данные!$E$2:$E$341,Параметры!$B$4)} -> 0 | H21: {=SUMIFS(Данные!$D$2:$D$341,Данные!$B$2:$B$341,$A21,Данные!$F$2:$F$341,H$1,Данные!$A$2:$A$341,">="&Параметры!$B$1,Данные!$A$2:$A$341,"<="&Параметры!$B$2,Данные!$E$2:$E$341,Параметры!$B$4)} -> 0 | I21: {=SUMIFS(Данные!$D$2:$D$341,Данные!$B$2:$B$341,$A21,Данные!$F$2:$F$341,I$1,Данные!$A$2:$A$341,">="&Параметры!$B$1,Данные!$A$2:$A$341,"<="&Параметры!$B$2,Данные!$E$2:$E$341,Параметры!$B$4)} -> 263181.07 | ... P21: {=SUMIFS(Данные!$D$2:$D$341,Данные!$B$2:$B$341,$A21,Данные!$F$2:$F$341,P$1,Данные!$A$2:$A$341,">="&Параметры!$B$1,Данные!$A$2:$A$341,"<="&Параметры!$B$2,Данные!$E$2:$E$341,Параметры!$B$4)} -> 0 | Q21: {=SUM(B21:P21)} -> 1020334.3
A22: {=Статьи!A19} -> Доход 2 | B22: {=SUMIFS(Данные!$D$2:$D$341,Данные!$B$2:$B$341,$A22,Данные!$F$2:$F$341,B$1,Данные!$A$2:$A$341,">="&Параметры!$B$1,Данные!$A$2:$A$341,"<="&Параметры!$B$2,Данные!$E$2:$E$341,Параметры!$B$4)} -> 0 | C22: {=SUMIFS(Данные!$D$2:$D$341,Данные!$B$2:$B$341,$A22,Данные!$F$2:$F$341,C$1,Данные!$A$2:$A$341,">="&Параметры!$B$1,Данные!$A$2:$A$341,"<="&Параметры!$B$2,Данные!$E$2:$E$341,Параметры!$B$4)} -> 0 | D22: {=SUMIFS(Данные!$D$2:$D$341,Данные!$B$2:$B$341,$A22,Данные!$F$2:$F$341,D$1,Данные!$A$2:$A$341,">="&Параметры!$B$1,Данные!$A$2:$A$341,"<="&Параметры!$B$2,Данные!$E$2:$E$341,Параметры!$B$4)} -> 0 | E22: {=SUMIFS(Данные!$D$2:$D$341,Данные!$B$2:$B$341,$A22,Данные!$F$2:$F$341,E$1,Данные!$A$2:$A$341,">="&Параметры!$B$1,Данные!$A$2:$A$341,"<="&Параметры!$B$2,Данные!$E$2:$E$341,Параметры!$B$4)} -> 0 | F22: {=SUMIFS(Данные!$D$2:$D$341,Данные!$B$2:$B$341,$A22,Данные!$F$2:$F$341,F$1,Данные!$A$2:$A$341,">="&Параметры!$B$1,Данные!$A$2:$A$341,"<="&Параметры!$B$2,Данные!$E$2:$E$341,Параметры!$B$4)} -> -78635.15 | G22: {=SUMIFS(Данные!$D$2:$D$341,Данные!$B$2:$B$341,$A22,Данные!$F$2:$F$341,G$1,Данные!$A$2:$A$341,">="&Параметры!$B$1,Данные!$A$2:$A$341,"<="&Параметры!$B$2,Данные!$E$2:$E$341,Параметры!$B$4)} -> 0 | H22: {=SUMIFS(Данные!$D$2:$D$341,Данные!$B$2:$B$341,$A22,Данные!$F$2:$F$341,H$1,Данные!$A$2:$A$341,">="&Параметры!$B$1,Данные!$A$2:$A$341,"<="&Параметры!$B$2,Данные!$E$2:$E$341,Параметры!$B$4)} -> 0 | I22: {=SUMIFS(Данные!$D$2:$D$341,Данные!$B$2:$B$341,$A22,Данные!$F$2:$F$341,I$1,Данные!$A$2:$A$341,">="&Параметры!$B$1,Данные!$A$2:$A$341,"<="&Параметры!$B$2,Данные!$E$2:$E$341,Параметры!$B$4)} -> 283598.73 | ... P22: {=SUMIFS(Данные!$D$2:$D$341,Данные!$B$2:$B$341,$A22,Данные!$F$2:$F$341,P$1,Данные!$A$2:$A$341,">="&Параметры!$B$1,Данные!$A$2:$A$341,"<="&Параметры!$B$2,Данные!$E$2:$E$341,Параметры!$B$4)} -> 0 | Q22: {=SUM(B22:P22)} -> 526208.17
A23: {=Статьи!A20} -> Сырьё 2 | B23: {=SUMIFS(Данные!$D$2:$D$341,Данные!$B$2:$B$341,$A23,Данные!$F$2:$F$341,B$1,Данные!$A$2:$A$341,">="&Параметры!$B$1,Данные!$A$2:$A$341,"<="&Параметры!$B$2,Данные!$E$2:$E$341,Параметры!$B$4)} -> 0 | C23: {=SUMIFS(Данные!$D$2:$D$341,Данные!$B$2:$B$341,$A23,Данные!$F$2:$F$341,C$1,Данные!$A$2:$A$341,">="&Параметры!$B$1,Данные!$A$2:$A$341,"<="&Параметры!$B$2,Данные!$E$2:$E$341,Параметры!$B$4)} -> 292678.6 | D23: {=SUMIFS(Данные!$D$2:$D$341,Данные!$B$2:$B$341,$A23,Данные!$F$2:$F$341,D$1,Данные!$A$2:$A$341,">="&Параметры!$B$1,Данные!$A$2:$A$341,"<="&Параметры!$B$2,Данные!$E$2:$E$341,Параметры!$B$4)} -> 0 | E23: {=SUMIFS(Данные!$D$2:$D$341,Данные!$B$2:$B$341,$A23,Данные!$F$2:$F$341,E$1,Данные!$A$2:$A$341,">="&Параметры!$B$1,Данные!$A$2:$A$341,"<="&Параметры!$B$2,Данные!$E$2:$E$341,Параметры!$B$4)} -> 0 | F23: {=SUMIFS(Данные!$D$2:$D$341,Данные!$B$2:$B$341,$A23,Данные!$F$2:$F$341,F$1,Данные!$A$2:$A$341,">="&Параметры!$B$1,Данные!$A$2:$A$341,"<="&Параметры!$B$2,Данные!$E$2:$E$341,Параметры!$B$4)} -> 0 | G23: {=SUMIFS(Данные!$D$2:$D$341,Данные!$B$2:$B$341,$A23,Данные!$F$2:$F$341,G$1,Данные!$A$2:$A$341,">="&Параметры!$B$1,Данные!$A$2:$A$341,"<="&Параметры!$B$2,Данные!$E$2:$E$341,Параметры!$B$4)} -> 0 | H23: {=SUMIFS(Данные!$D$2:$D$341,Данные!$B$2:$B$341,$A23,Данные!$F$2:$F$341,H$1,Данные!$A$2:$A$341,">="&Параметры!$B$1,Данные!$A$2:$A$341,"<="&Параметры!$B$2,Данные!$E$2:$E$341,Параметры!$B$4)} -> 0 | I23: {=SUMIFS(Данные!$D$2:$D$341,Данные!$B$2:$B$341,$A23,Данные!$F$2:$F$341,I$1,Данные!$A$2:$A$341,">="&Параметры!$B$1,Данные!$A$2:$A$341,"<="&Параметры!$B$2,Данные!$E$2:$E$341,Параметры!$B$4)} -> 103867.83 | ... P23: {=SUMIFS(Данные!$D$2:$D$341,Данные!$B$2:$B$341,$A23,Данные!$F$2:$F$341,P$1,Данные!$A$2:$A$341,">="&Параметры!$B$1,Данные!$A$2:$A$341,"<="&Параметры!$B$2,Данные!$E$2:$E$341,Параметры!$B$4)} -> 48723.82 | Q23: {=SUM(B23:P23)} -> 372711.64
A24: {=Статьи!A21} -> Сырье 2 | B24: {=SUMIFS(Данные!$D$2:$D$341,Данные!$B$2:$B$341,$A24,Данные!$F$2:$F$341,B$1,Данные!$A$2:$A$341,">="&Параметры!$B$1,Данные!$A$2:$A$341,"<="&Параметры!$B$2,Данные!$E$2:$E$341,Параметры!$B$4)} -> 0 | C24: {=SUMIFS(Данные!$D$2:$D$341,Данные!$B$2:$B$341,$A24,Данные!$F$2:$F$341,C$1,Данные!$A$2:$A$341,">="&Параметры!$B$1,Данные!$A$2:$A$341,"<="&Параметры!$B$2,Данные!$E$2:$E$341,Параметры!$B$4)} -> 0 | D24: {=SUMIFS(Данные!$D$2:$D$341,Данные!$B$2:$B$341,$A24,Данные!$F$2:$F$341,D$1,Данные!$A$2:$A$341,">="&Параметры!$B$1,Данные!$A$2:$A$341,"<="&Параметры!$B$2,Данные!$E$2:$E$341,Параметры!$B$4)} -> 0 | E24: {=SUMIFS(Данные!$D$2:$D$341,Данные!$B$2:$B$341,$A24,Данные!$F$2:$F$341,E$1,Данные!$A$2:$A$341,">="&Параметры!$B$1,Данные!$A$2:$A$341,"<="&Параметры!$B$2,Данные!$E$2:$E$341,Параметры!$B$4)} -> -34400.87 | F24: {=SUMIFS(Данные!$D$2:$D$341,Данные!$B$2:$B$341,$A24,Данные!$F$2:$F$341,F$1,Данные!$A$2:$A$341,">="&Параметры!$B$1,Данные!$A$2:$A$341,"<="&Параметры!$B$2,Данные!$E$2:$E$341,Параметры!$B$4)} -> 0 | G24: {=SUMIFS(Данные!$D$2:$D$341,Данные!$B$2:$B$341,$A24,Данные!$F$2:$F$341,G$1,Данные!$A$2:$A$341,">="&Параметры!$B$1,Данные!$A$2:$A$341,"<="&Параметры!$B$2,Данные!$E$2:$E$341,Параметры!$B$4)} -> 0 | H24: {=SUMIFS(Данные!$D$2:$D$341,Данные!$B$2:$B$341,$A24,Данные!$F$2:$F$341,H$1,Данные!$A$2:$A$341,">="&Параметры!$B$1,Данные!$A$2:$A$341,"<="&Параметры!$B$2,Данные!$E$2:$E$341,Параметры!$B$4)} -> 0 | I24: {=SUMIFS(Данные!$D$2:$D$341,Данные!$B$2:$B$341,$A24,Данные!$F$2:$F$341,I$1,Данные!$A$2:$A$341,">="&Параметры!$B$1,Данные!$A$2:$A$341,"<="&Параметры!$B$2,Данные!$E$2:$E$341,Параметры!$B$4)} -> 0 | ... P24: {=SUMIFS(Данные!$D$2:$D$341,Данные!$B$2:$B$341,$A24,Данные!$F$2:$F$341,P$1,Данные!$A$2:$A$341,">="&Параметры!$B$1,Данные!$A$2:$A$341,"<="&Параметры!$B$2,Данные!$E$2:$E$341,Параметры!$B$4)} -> 0 | Q24: {=SUM(B24:P24)} -> 125769.41
A25: Итого группа 4 | B25: {=SUM(B20:B24)} -> 0 | C25: {=SUM(C20:C24)} -> 292678.6 | D25: {=SUM(D20:D24)} -> 0 | E25: {=SUM(E20:E24)} -> -129854.31 | F25: {=SUM(F20:F24)} -> 358320.85 | G25: {=SUM(G20:G24)} -> 17079.28 | H25: {=SUM(H20:H24)} -> 0 | I25: {=SUM(I20:I24)} -> 650647.63 | ... Q25: {=SUM(Q20:Q24)} -> 1964416
A26: {=Статьи!A22} -> Чай 3 | B26: {=SUMIFS(Данные!$D$2:$D$341,Данные!$B$2:$B$341,$A26,Данные!$F$2:$F$341,B$1,Данные!$A$2:$A$341,">="&Параметры!$B$1,Данные!$A$2:$A$341,"<="&Параметры!$B$2,Данные!$E$2:$E$341,Параметры!$B$4)} -> 0 | C26: {=SUMIFS(Данные!$D$2:$D$341,Данные!$B$2:$B$341,$A26,Данные!$F$2:$F$341,C$1,Данные!$A$2:$A$341,">="&Параметры!$B$1,Данные!$A$2:$A$341,"<="&Параметры!$B$2,Данные!$E$2:$E$341,Параметры!$B$4)} -> 392435.78 | D26: {=SUMIFS(Данные!$D$2:$D$341,Данные!$B$2:$B$341,$A26,Данные!$F$2:$F$341,D$1,Данные!$A$2:$A$341,">="&Параметры!$B$1,Данные!$A$2:$A$341,"<="&Параметры!$B$2,Данные!$E$2:$E$341,Параметры!$B$4)} -> 0 | E26: {=SUMIFS(Данные!$D$2:$D$341,Данные!$B$2:$B$341,$A26,Данные!$F$2:$F$341,E$1,Данные!$A$2:$A$341,">="&Параметры!$B$1,Данные!$A$2:$A$341,"<="&Параметры!$B$2,Данные!$E$2:$E$341,Параметры!$B$4)} -> -6603.37 | F26: {=SUMIFS(Данные!$D$2:$D$341,Данные!$B$2:$B$341,$A26,Данные!$F$2:$F$341,F$1,Данные!$A$2:$A$341,">="&Параметры!$B$1,Данные!$A$2:$A$341,"<="&Параметры!$B$2,Данные!$E$2:$E$341,Параметры!$B$4)} -> 56606.62 | G26: {=SUMIFS(Данные!$D$2:$D$341,Данные!$B$2:$B$341,$A26,Данные!$F$2:$F$341,G$1,Данные!$A$2:$A$341,">="&Параметры!$B$1,Данные!$A$2:$A$341,"<="&Параметры!$B$2,Данные!$E$2:$E$341,Параметры!$B$4)} -> 0 | H26: {=SUMIFS(Данные!$D$2:$D$341,Данные!$B$2:$B$341,$A26,Данные!$F$2:$F$341,H$1,Данные!$A$2:$A$341,">="&Параметры!$B$1,Данные!$A$2:$A$341,"<="&Параметры!$B$2,Данные!$E$2:$E$341,Параметры!$B$4)} -> 0 | I26: {=SUMIFS(Данные!$D$2:$D$341,Данные!$B$2:$B$341,$A26,Данные!$F$2:$F$341,I$1,Данные!$A$2:$A$341,">="&Параметры!$B$1,Данные!$A$2:$A$341,"<="&Параметры!$B$2,Данные!$E$2:$E$341,Параметры!$B$4)} -> 0 | ... P26: {=SUMIFS(Данные!$D$2:$D$341,Данные!$B$2:$B$341,$A26,Данные!$F$2:$F$341,P$1,Данные!$A$2:$A$341,">="&Параметры!$B$1,Данные!$A$2:$A$341,"<="&Параметры!$B$2,Данные!$E$2:$E$341,Параметры!$B$4)} -> 0 | Q26: {=SUM(B26:P26)} -> 1190033.3
A27: {=Статьи!A23} -> Чаи 3 | B27: {=SUMIFS(Данные!$D$2:$D$341,Данные!$B$2:$B$341,$A27,Данные!$F$2:$F$341,B$1,Данные!$A$2:$A$341,">="&Параметры!$B$1,Данные!$A$2:$A$341,"<="&Параметры!$B$2,Данные!$E$2:$E$341,Параметры!$B$4)} -> 0 | C27: {=SUMIFS(Данные!$D$2:$D$341,Данные!$B$2:$B$341,$A27,Данные!$F$2:$F$341,C$1,Данные!$A$2:$A$341,">="&Параметры!$B$1,Данные!$A$2:$A$341,"<="&Параметры!$B$2,Данные!$E$2:$E$341,Параметры!$B$4)} -> 0 | D27: {=SUMIFS(Данные!$D$2:$D$341,Данные!$B$2:$B$341,$A27,Данные!$F$2:$F$341,D$1,Данные!$A$2:$A$341,">="&Параметры!$B$1,Данные!$A$2:$A$341,"<="&Параметры!$B$2,Данные!$E$2:$E$341,Параметры!$B$4)} -> 0 | E27: {=SUMIFS(Данные!$D$2:$D$341,Данные!$B$2:$B$341,$A27,Данные!$F$2:$F$341,E$1,Данные!$A$2:$A$341,">="&Параметры!$B$1,Данные!$A$2:$A$341,"<="&Параметры!$B$2,Данные!$E$2:$E$341,Параметры!$B$4)} -> 0 | F27: {=SUMIFS(Данные!$D$2:$D$341,Данные!$B$2:$B$341,$A27,Данные!$F$2:$F$341,F$1,Данные!$A$2:$A$341,">="&Параметры!$B$1,Данные!$A$2:$A$341,"<="&Параметры!$B$2,Данные!$E$2:$E$341,Параметры!$B$4)} -> 0 | G27: {=SUMIFS(Данные!$D$2:$D$341,Данные!$B$2:$B$341,$A27,Данные!$F$2:$F$341,G$1,Данные!$A$2:$A$341,">="&Параметры!$B$1,Данные!$A$2:$A$341,"<="&Параметры!$B$2,Данные!$E$2:$E$341,Параметры!$B$4)} -> 346144.14 | H27: {=SUMIFS(Данные!$D$2:$D$341,Данные!$B$2:$B$341,$A27,Данные!$F$2:$F$341,H$1,Данные!$A$2:$A$341,">="&Параметры!$B$1,Данные!$A$2:$A$341,"<="&Параметры!$B$2,Данные!$E$2:$E$341,Параметры!$B$4)} -> 0 | I27: {=SUMIFS(Данные!$D$2:$D$341,Данные!$B$2:$B$341,$A27,Данные!$F$2:$F$341,I$1,Данные!$A$2:$A$341,">="&Параметры!$B$1,Данные!$A$2:$A$341,"<="&Параметры!$B$2,Данные!$E$2:$E$341,Параметры!$B$4)} -> 315607.12 | ... P27: {=SUMIFS(Данные!$D$2:$D$341,Данные!$B$2:$B$341,$A27,Данные!$F$2:$F$341,P$1,Данные!$A$2:$A$341,">="&Параметры!$B$1,Данные!$A$2:$A$341,"<="&Параметры!$B$2,Данные!$E$2:$E$341,Параметры!$B$4)} -> 0 | Q27: {=SUM(B27:P27)} -> 661751.26
A28: {=Статьи!A24} -> Ёлка 3 | B28: {=SUMIFS(Данные!$D$2:$D$341,Данные!$B$2:$B$341,$A28,Данные!$F$2:$F$341,B$1,Данные!$A$2:$A$341,">="&Параметры!$B$1,Данные!$A$2:$A$341,"<="&Параметры!$B$2,Данные!$E$2:$E$341,Параметры!$B$4)} -> 185018.89 | C28: {=SUMIFS(Данные!$D$2:$D$341,Данные!$B$2:$B$341,$A28,Данные!$F$2:$F$341,C$1,Данные!$A$2:$A$341,">="&Параметры!$B$1,Данные!$A$2:$A$341,"<="&Параметры!$B$2,Данные!$E$2:$E$341,Параметры!$B$4)} -> 0 | D28: {=SUMIFS(Данные!$D$2:$D$341,Данные!$B$2:$B$341,$A28,Данные!$F$2:$F$341,D$1,Данные!$A$2:$A$341,">="&Параметры!$B$1,Данные!$A$2:$A$341,"<="&Параметры!$B$2,Данные!$E$2:$E$341,Параметры!$B$4)} -> 164087.92 | E28: {=SUMIFS(Данные!$D$2:$D$341,Данные!$B$2:$B$341,$A28,Данные!$F$2:$F$341,E$1,Данные!$A$2:$A$341,">="&Параметры!$B$1,Данные!$A$2:$A$341,"<="&Параметры!$B$2,Данные!$E$2:$E$341,Параметры!$B$4)} -> -58420.79 | F28: {=SUMIFS(Данные!$D$2:$D$341,Данные!$B$2:$B$341,$A28,Данные!$F$2:$F$341,F$1,Данные!$A$2:$A$341,">="&Параметры!$B$1,Данные!$A$2:$A$341,"<="&Параметры!$B$2,Данные!$E$2:$E$341,Параметры!$B$4)} -> 0 | G28: {=SUMIFS(Данные!$D$2:$D$341,Данные!$B$2:$B$341,$A28,Данные!$F$2:$F$341,G$1,Данные!$A$2:$A$341,">="&Параметры!$B$1,Данные!$A$2:$A$341,"<="&Параметры!$B$2,Данные!$E$2:$E$341,Параметры!$B$4)} -> 0 | H28: {=SUMIFS(Данные!$D$2:$D$341,Данные!$B$2:$B$341,$A28,Данные!$F$2:$F$341,H$1,Данные!$A$2:$A$341,">="&Параметры!$B$1,Данные!$A$2:$A$341,"<="&Параметры!$B$2,Данные!$E$2:$E$341,Параметры!$B$4)} -> 0 | I28: {=SUMIFS(Данные!$D$2:$D$341,Данные!$B$2:$B$341,$A28,Данные!$F$2:$F$341,I$1,Данные!$A$2:$A$341,">="&Параметры!$B$1,Данные!$A$2:$A$341,"<="&Параметры!$B$2,Данные!$E$2:$E$341,Параметры!$B$4)} -> 0 | ... P28: {=SUMIFS(Данные!$D$2:$D$341,Данные!$B$2:$B$341,$A28,Данные!$F$2:$F$341,P$1,Данные!$A$2:$A$341,">="&Параметры!$B$1,Данные!$A$2:$A$341,"<="&Параметры!$B$2,Данные!$E$2:$E$341,Параметры!$B$4)} -> 344795.87 | Q28: {=SUM(B28:P28)} -> 1.8826521e+09
A29: {=Статьи!A25} -> Елка 3 | B29: {=SUMIFS(Данные!$D$2:$D$341,Данные!$B$2:$B$341,$A29,Данные!$F$2:$F$341,B$1,Данные!$A$2:$A$341,">="&Параметры!$B$1,Данные!$A$2:$A$341,"<="&Параметры!$B$2,Данные!$E$2:$E$341,Параметры!$B$4)} -> 0 | C29: {=SUMIFS(Данные!$D$2:$D$341,Данные!$B$2:$B$341,$A29,Данные!$F$2:$F$341,C$1,Данные!$A$2:$A$341,">="&Параметры!$B$1,Данные!$A$2:$A$341,"<="&Параметры!$B$2,Данные!$E$2:$E$341,Параметры!$B$4)} -> 138812.72 | D29: {=SUMIFS(Данные!$D$2:$D$341,Данные!$B$2:$B$341,$A29,Данные!$F$2:$F$341,D$1,Данные!$A$2:$A$341,">="&Параметры!$B$1,Данные!$A$2:$A$341,"<="&Параметры!$B$2,Данные!$E$2:$E$341,Параметры!$B$4)} -> 0 | E29: {=SUMIFS(Данные!$D$2:$D$341,Данные!$B$2:$B$341,$A29,Данные!$F$2:$F$341,E$1,Данные!$A$2:$A$341,">="&Параметры!$B$1,Данные!$A$2:$A$341,"<="&Параметры!$B$2,Данные!$E$2:$E$341,Параметры!$B$4)} -> 0 | F29: {=SUMIFS(Данные!$D$2:$D$341,Данные!$B$2:$B$341,$A29,Данные!$F$2:$F$341,F$1,Данные!$A$2:$A$341,">="&Параметры!$B$1,Данные!$A$2:$A$341,"<="&Параметры!$B$2,Данные!$E$2:$E$341,Параметры!$B$4)} -> 0 | G29: {=SUMIFS(Данные!$D$2:$D$341,Данные!$B$2:$B$341,$A29,Данные!$F$2:$F$341,G$1,Данные!$A$2:$A$341,">="&Параметры!$B$1,Данные!$A$2:$A$341,"<="&Параметры!$B$2,Данные!$E$2:$E$341,Параметры!$B$4)} -> 0 | H29: {=SUMIFS(Данные!$D$2:$D$341,Данные!$B$2:$B$341,$A29,Данные!$F$2:$F$341,H$1,Данные!$A$2:$A$341,">="&Параметры!$B$1,Данные!$A$2:$A$341,"<="&Параметры!$B$2,Данные!$E$2:$E$341,Параметры!$B$4)} -> 0 | I29: {=SUMIFS(Данные!$D$2:$D$341,Данные!$B$2:$B$341,$A29,Данные!$F$2:$F$341,I$1,Данные!$A$2:$A$341,">="&Параметры!$B$1,Данные!$A$2:$A$341,"<="&Параметры!$B$2,Данные!$E$2:$E$341,Параметры!$B$4)} -> -46189.52 | ... P29: {=SUMIFS(Данные!$D$2:$D$341,Данные!$B$2:$B$341,$A29,Данные!$F$2:$F$341,P$1,Данные!$A$2:$A$341,">="&Параметры!$B$1,Данные!$A$2:$A$341,"<="&Параметры!$B$2,Данные!$E$2:$E$341,Параметры!$B$4)} -> 0 | Q29: {=SUM(B29:P29)} -> 92623.2
A30: {=Статьи!A26} -> Аренда 3 | B30: {=SUMIFS(Данные!$D$2:$D$341,Данные!$B$2:$B$341,$A30,Данные!$F$2:$F$341,B$1,Данные!$A$2:$A$341,">="&Параметры!$B$1,Данные!$A$2:$A$341,"<="&Параметры!$B$2,Данные!$E$2:$E$341,Параметры!$B$4)} -> 0 | C30: {=SUMIFS(Данные!$D$2:$D$341,Данные!$B$2:$B$341,$A30,Данные!$F$2:$F$341,C$1,Данные!$A$2:$A$341,">="&Параметры!$B$1,Данные!$A$2:$A$341,"<="&Параметры!$B$2,Данные!$E$2:$E$341,Параметры!$B$4)} -> 0 | D30: {=SUMIFS(Данные!$D$2:$D$341,Данные!$B$2:$B$341,$A30,Данные!$F$2:$F$341,D$1,Данные!$A$2:$A$341,">="&Параметры!$B$1,Данные!$A$2:$A$341,"<="&Параметры!$B$2,Данные!$E$2:$E$341,Параметры!$B$4)} -> 0 | E30: {=SUMIFS(Данные!$D$2:$D$341,Данные!$B$2:$B$341,$A30,Данные!$F$2:$F$341,E$1,Данные!$A$2:$A$341,">="&Параметры!$B$1,Данные!$A$2:$A$341,"<="&Параметры!$B$2,Данные!$E$2:$E$341,Параметры!$B$4)} -> 282022.53 | F30: {=SUMIFS(Данные!$D$2:$D$341,Данные!$B$2:$B$341,$A30,Данные!$F$2:$F$341,F$1,Данные!$A$2:$A$341,">="&Параметры!$B$1,Данные!$A$2:$A$341,"<="&Параметры!$B$2,Данные!$E$2:$E$341,Параметры!$B$4)} -> 0 | G30: {=SUMIFS(Данные!$D$2:$D$341,Данные!$B$2:$B$341,$A30,Данные!$F$2:$F$341,G$1,Данные!$A$2:$A$341,">="&Параметры!$B$1,Данные!$A$2:$A$341,"<="&Параметры!$B$2,Данные!$E$2:$E$341,Параметры!$B$4)} -> 387119 | H30: {=SUMIFS(Данные!$D$2:$D$341,Данные!$B$2:$B$341,$A30,Данные!$F$2:$F$341,H$1,Данные!$A$2:$A$341,">="&Параметры!$B$1,Данные!$A$2:$A$341,"<="&Параметры!$B$2,Данные!$E$2:$E$341,Параметры!$B$4)} -> 0 | I30: {=SUMIFS(Данные!$D$2:$D$341,Данные!$B$2:$B$341,$A30,Данные!$F$2:$F$341,I$1,Данные!$A$2:$A$341,">="&Параметры!$B$1,Данные!$A$2:$A$341,"<="&Параметры!$B$2,Данные!$E$2:$E$341,Параметры!$B$4)} -> 198357.66 | ... P30: {=SUMIFS(Данные!$D$2:$D$341,Данные!$B$2:$B$341,$A30,Данные!$F$2:$F$341,P$1,Данные!$A$2:$A$341,">="&Параметры!$B$1,Данные!$A$2:$A$341,"<="&Параметры!$B$2,Данные!$E$2:$E$341,Параметры!$B$4)} -> 0 | Q30: {=SUM(B30:P30)} -> 1206089.8
A31: Итого группа 5 | B31: {=SUM(B26:B30)} -> 185018.89 | C31: {=SUM(C26:C30)} -> 531248.5 | D31: {=SUM(D26:D30)} -> 164087.92 | E31: {=SUM(E26:E30)} -> 216998.37 | F31: {=SUM(F26:F30)} -> 56606.62 | G31: {=SUM(G26:G30)} -> 733263.14 | H31: {=SUM(H26:H30)} -> 0 | I31: {=SUM(I26:I30)} -> 467775.26 | ... Q31: {=SUM(Q26:Q30)} -> 1.8858026e+09
A32: {=Статьи!A27} -> Связь 3 | B32: {=SUMIFS(Данные!$D$2:$D$341,Данные!$B$2:$B$341,$A32,Данные!$F$2:$F$341,B$1,Данные!$A$2:$A$341,">="&Параметры!$B$1,Данные!$A$2:$A$341,"<="&Параметры!$B$2,Данные!$E$2:$E$341,Параметры!$B$4)} -> 0 | C32: {=SUMIFS(Данные!$D$2:$D$341,Данные!$B$2:$B$341,$A32,Данные!$F$2:$F$341,C$1,Данные!$A$2:$A$341,">="&Параметры!$B$1,Данные!$A$2:$A$341,"<="&Параметры!$B$2,Данные!$E$2:$E$341,Параметры!$B$4)} -> 0 | D32: {=SUMIFS(Данные!$D$2:$D$341,Данные!$B$2:$B$341,$A32,Данные!$F$2:$F$341,D$1,Данные!$A$2:$A$341,">="&Параметры!$B$1,Данные!$A$2:$A$341,"<="&Параметры!$B$2,Данные!$E$2:$E$341,Параметры!$B$4)} -> 190699 | E32: {=SUMIFS(Данные!$D$2:$D$341,Данные!$B$2:$B$341,$A32,Данные!$F$2:$F$341,E$1,Данные!$A$2:$A$341,">="&Параметры!$B$1,Данные!$A$2:$A$341,"<="&Параметры!$B$2,Данные!$E$2:$E$341,Параметры!$B$4)} -> 0 | F32: {=SUMIFS(Данные!$D$2:$D$341,Данные!$B$2:$B$341,$A32,Данные!$F$2:$F$341,F$1,Данные!$A$2:$A$341,">="&Параметры!$B$1,Данные!$A$2:$A$341,"<="&Параметры!$B$2,Данные!$E$2:$E$341,Параметры!$B$4)} -> 0 | G32: {=SUMIFS(Данные!$D$2:$D$341,Данные!$B$2:$B$341,$A32,Данные!$F$2:$F$341,G$1,Данные!$A$2:$A$341,">="&Параметры!$B$1,Данные!$A$2:$A$341,"<="&Параметры!$B$2,Данные!$E$2:$E$341,Параметры!$B$4)} -> 0 | H32: {=SUMIFS(Данные!$D$2:$D$341,Данные!$B$2:$B$341,$A32,Данные!$F$2:$F$341,H$1,Данные!$A$2:$A$341,">="&Параметры!$B$1,Данные!$A$2:$A$341,"<="&Параметры!$B$2,Данные!$E$2:$E$341,Параметры!$B$4)} -> 0 | I32: {=SUMIFS(Данные!$D$2:$D$341,Данные!$B$2:$B$341,$A32,Данные!$F$2:$F$341,I$1,Данные!$A$2:$A$341,">="&Параметры!$B$1,Данные!$A$2:$A$341,"<="&Параметры!$B$2,Данные!$E$2:$E$341,Параметры!$B$4)} -> 0 | ... P32: {=SUMIFS(Данные!$D$2:$D$341,Данные!$B$2:$B$341,$A32,Данные!$F$2:$F$341,P$1,Данные!$A$2:$A$341,">="&Параметры!$B$1,Данные!$A$2:$A$341,"<="&Параметры!$B$2,Данные!$E$2:$E$341,Параметры!$B$4)} -> 24029.74 | Q32: {=SUM(B32:P32)} -> 1036729.5
A33: {=Статьи!A28} -> Налог 3 | B33: {=SUMIFS(Данные!$D$2:$D$341,Данные!$B$2:$B$341,$A33,Данные!$F$2:$F$341,B$1,Данные!$A$2:$A$341,">="&Параметры!$B$1,Данные!$A$2:$A$341,"<="&Параметры!$B$2,Данные!$E$2:$E$341,Параметры!$B$4)} -> 0 | C33: {=SUMIFS(Данные!$D$2:$D$341,Данные!$B$2:$B$341,$A33,Данные!$F$2:$F$341,C$1,Данные!$A$2:$A$341,">="&Параметры!$B$1,Данные!$A$2:$A$341,"<="&Параметры!$B$2,Данные!$E$2:$E$341,Параметры!$B$4)} -> 62162.46 | D33: {=SUMIFS(Данные!$D$2:$D$341,Данные!$B$2:$B$341,$A33,Данные!$F$2:$F$341,D$1,Данные!$A$2:$A$341,">="&Параметры!$B$1,Данные!$A$2:$A$341,"<="&Параметры!$B$2,Данные!$E$2:$E$341,Параметры!$B$4)} -> 249404.63 | E33: {=SUMIFS(Данные!$D$2:$D$341,Данные!$B$2:$B$341,$A33,Данные!$F$2:$F$341,E$1,Данные!$A$2:$A$341,">="&Параметры!$B$1,Данные!$A$2:$A$341,"<="&Параметры!$B$2,Данные!$E$2:$E$341,Параметры!$B$4)} -> 0 | F33: {=SUMIFS(Данные!$D$2:$D$341,Данные!$B$2:$B$341,$A33,Данные!$F$2:$F$341,F$1,Данные!$A$2:$A$341,">="&Параметры!$B$1,Данные!$A$2:$A$341,"<="&Параметры!$B$2,Данные!$E$2:$E$341,Параметры!$B$4)} -> 0 | G33: {=SUMIFS(Данные!$D$2:$D$341,Данные!$B$2:$B$341,$A33,Данные!$F$2:$F$341,G$1,Данные!$A$2:$A$341,">="&Параметры!$B$1,Данные!$A$2:$A$341,"<="&Параметры!$B$2,Данные!$E$2:$E$341,Параметры!$B$4)} -> 0 | H33: {=SUMIFS(Данные!$D$2:$D$341,Данные!$B$2:$B$341,$A33,Данные!$F$2:$F$341,H$1,Данные!$A$2:$A$341,">="&Параметры!$B$1,Данные!$A$2:$A$341,"<="&Параметры!$B$2,Данные!$E$2:$E$341,Параметры!$B$4)} -> 0 | I33: {=SUMIFS(Данные!$D$2:$D$341,Данные!$B$2:$B$341,$A33,Данные!$F$2:$F$341,I$1,Данные!$A$2:$A$341,">="&Параметры!$B$1,Данные!$A$2:$A$341,"<="&Параметры!$B$2,Данные!$E$2:$E$341,Параметры!$B$4)} -> 0 | ... P33: {=SUMIFS(Данные!$D$2:$D$341,Данные!$B$2:$B$341,$A33,Данные!$F$2:$F$341,P$1,Данные!$A$2:$A$341,">="&Параметры!$B$1,Данные!$A$2:$A$341,"<="&Параметры!$B$2,Данные!$E$2:$E$341,Параметры!$B$4)} -> 0 | Q33: {=SUM(B33:P33)} -> 397415.79
A34: {=Статьи!A29} -> Доход 3 | B34: {=SUMIFS(Данные!$D$2:$D$341,Данные!$B$2:$B$341,$A34,Данные!$F$2:$F$341,B$1,Данные!$A$2:$A$341,">="&Параметры!$B$1,Данные!$A$2:$A$341,"<="&Параметры!$B$2,Данные!$E$2:$E$341,Параметры!$B$4)} -> 0 | C34: {=SUMIFS(Данные!$D$2:$D$341,Данные!$B$2:$B$341,$A34,Данные!$F$2:$F$341,C$1,Данные!$A$2:$A$341,">="&Параметры!$B$1,Данные!$A$2:$A$341,"<="&Параметры!$B$2,Данные!$E$2:$E$341,Параметры!$B$4)} -> 356468.5 | D34: {=SUMIFS(Данные!$D$2:$D$341,Данные!$B$2:$B$341,$A34,Данные!$F$2:$F$341,D$1,Данные!$A$2:$A$341,">="&Параметры!$B$1,Данные!$A$2:$A$341,"<="&Параметры!$B$2,Данные!$E$2:$E$341,Параметры!$B$4)} -> 0 | E34: {=SUMIFS(Данные!$D$2:$D$341,Данные!$B$2:$B$341,$A34,Данные!$F$2:$F$341,E$1,Данные!$A$2:$A$341,">="&Параметры!$B$1,Данные!$A$2:$A$341,"<="&Параметры!$B$2,Данные!$E$2:$E$341,Параметры!$B$4)} -> 0 | F34: {=SUMIFS(Данные!$D$2:$D$341,Данные!$B$2:$B$341,$A34,Данные!$F$2:$F$341,F$1,Данные!$A$2:$A$341,">="&Параметры!$B$1,Данные!$A$2:$A$341,"<="&Параметры!$B$2,Данные!$E$2:$E$341,Параметры!$B$4)} -> 0 | G34: {=SUMIFS(Данные!$D$2:$D$341,Данные!$B$2:$B$341,$A34,Данные!$F$2:$F$341,G$1,Данные!$A$2:$A$341,">="&Параметры!$B$1,Данные!$A$2:$A$341,"<="&Параметры!$B$2,Данные!$E$2:$E$341,Параметры!$B$4)} -> 0 | H34: {=SUMIFS(Данные!$D$2:$D$341,Данные!$B$2:$B$341,$A34,Данные!$F$2:$F$341,H$1,Данные!$A$2:$A$341,">="&Параметры!$B$1,Данные!$A$2:$A$341,"<="&Параметры!$B$2,Данные!$E$2:$E$341,Параметры!$B$4)} -> -10345.15 | I34: {=SUMIFS(Данные!$D$2:$D$341,Данные!$B$2:$B$341,$A34,Данные!$F$2:$F$341,I$1,Данные!$A$2:$A$341,">="&Параметры!$B$1,Данные!$A$2:$A$341,"<="&Параметры!$B$2,Данные!$E$2:$E$341,Параметры!$B$4)} -> 245538.09 | ... P34: {=SUMIFS(Данные!$D$2:$D$341,Данные!$B$2:$B$341,$A34,Данные!$F$2:$F$341,P$1,Данные!$A$2:$A$341,">="&Параметры!$B$1,Данные!$A$2:$A$341,"<="&Параметры!$B$2,Данные!$E$2:$E$341,Параметры!$B$4)} -> 46015.65 | Q34: {=SUM(B34:P34)} -> 908195.55
A35: {=Статьи!A30} -> Сырьё 3 | B35: {=SUMIFS(Данные!$D$2:$D$341,Данные!$B$2:$B$341,$A35,Данные!$F$2:$F$341,B$1,Данные!$A$2:$A$341,">="&Параметры!$B$1,Данные!$A$2:$A$341,"<="&Параметры!$B$2,Данные!$E$2:$E$341,Параметры!$B$4)} -> 0 | C35: {=SUMIFS(Данные!$D$2:$D$341,Данные!$B$2:$B$341,$A35,Данные!$F$2:$F$341,C$1,Данные!$A$2:$A$341,">="&Параметры!$B$1,Данные!$A$2:$A$341,"<="&Параметры!$B$2,Данные!$E$2:$E$341,Параметры!$B$4)} -> 0 | D35: {=SUMIFS(Данные!$D$2:$D$341,Данные!$B$2:$B$341,$A35,Данные!$F$2:$F$341,D$1,Данные!$A$2:$A$341,">="&Параметры!$B$1,Данные!$A$2:$A$341,"<="&Параметры!$B$2,Данные!$E$2:$E$341,Параметры!$B$4)} -> 0 | E35: {=SUMIFS(Данные!$D$2:$D$341,Данные!$B$2:$B$341,$A35,Данные!$F$2:$F$341,E$1,Данные!$A$2:$A$341,">="&Параметры!$B$1,Данные!$A$2:$A$341,"<="&Параметры!$B$2,Данные!$E$2:$E$341,Параметры!$B$4)} -> 0 | F35: {=SUMIFS(Данные!$D$2:$D$341,Данные!$B$2:$B$341,$A35,Данные!$F$2:$F$341,F$1,Данные!$A$2:$A$341,">="&Параметры!$B$1,Данные!$A$2:$A$341,"<="&Параметры!$B$2,Данные!$E$2:$E$341,Параметры!$B$4)} -> 0 | G35: {=SUMIFS(Данные!$D$2:$D$341,Данные!$B$2:$B$341,$A35,Данные!$F$2:$F$341,G$1,Данные!$A$2:$A$341,">="&Параметры!$B$1,Данные!$A$2:$A$341,"<="&Параметры!$B$2,Данные!$E$2:$E$341,Параметры!$B$4)} -> 0 | H35: {=SUMIFS(Данные!$D$2:$D$341,Данные!$B$2:$B$341,$A35,Данные!$F$2:$F$341,H$1,Данные!$A$2:$A$341,">="&Параметры!$B$1,Данные!$A$2:$A$341,"<="&Параметры!$B$2,Данные!$E$2:$E$341,Параметры!$B$4)} -> 0 | I35: {=SUMIFS(Данные!$D$2:$D$341,Данные!$B$2:$B$341,$A35,Данные!$F$2:$F$341,I$1,Данные!$A$2:$A$341,">="&Параметры!$B$1,Данные!$A$2:$A$341,"<="&Параметры!$B$2,Данные!$E$2:$E$341,Параметры!$B$4)} -> 54402.51 | ... P35: {=SUMIFS(Данные!$D$2:$D$341,Данные!$B$2:$B$341,$A35,Данные!$F$2:$F$341,P$1,Данные!$A$2:$A$341,">="&Параметры!$B$1,Данные!$A$2:$A$341,"<="&Параметры!$B$2,Данные!$E$2:$E$341,Параметры!$B$4)} -> 0 | Q35: {=SUM(B35:P35)} -> 1004846.8
A36: {=Статьи!A31} -> Сырье 3 | B36: {=SUMIFS(Данные!$D$2:$D$341,Данные!$B$2:$B$341,$A36,Данные!$F$2:$F$341,B$1,Данные!$A$2:$A$341,">="&Параметры!$B$1,Данные!$A$2:$A$341,"<="&Параметры!$B$2,Данные!$E$2:$E$341,Параметры!$B$4)} -> 0 | C36: {=SUMIFS(Данные!$D$2:$D$341,Данные!$B$2:$B$341,$A36,Данные!$F$2:$F$341,C$1,Данные!$A$2:$A$341,">="&Параметры!$B$1,Данные!$A$2:$A$341,"<="&Параметры!$B$2,Данные!$E$2:$E$341,Параметры!$B$4)} -> 0 | D36: {=SUMIFS(Данные!$D$2:$D$341,Данные!$B$2:$B$341,$A36,Данные!$F$2:$F$341,D$1,Данные!$A$2:$A$341,">="&Параметры!$B$1,Данные!$A$2:$A$341,"<="&Параметры!$B$2,Данные!$E$2:$E$341,Параметры!$B$4)} -> 0 | E36: {=SUMIFS(Данные!$D$2:$D$341,Данные!$B$2:$B$341,$A36,Данные!$F$2:$F$341,E$1,Данные!$A$2:$A$341,">="&Параметры!$B$1,Данные!$A$2:$A$341,"<="&Параметры!$B$2,Данные!$E$2:$E$341,Параметры!$B$4)} -> 0 | F36: {=SUMIFS(Данные!$D$2:$D$341,Данные!$B$2:$B$341,$A36,Данные!$F$2:$F$341,F$1,Данные!$A$2:$A$341,">="&Параметры!$B$1,Данные!$A$2:$A$341,"<="&Параметры!$B$2,Данные!$E$2:$E$341,Параметры!$B$4)} -> 0 | G36: {=SUMIFS(Данные!$D$2:$D$341,Данные!$B$2:$B$341,$A36,Данные!$F$2:$F$341,G$1,Данные!$A$2:$A$341,">="&Параметры!$B$1,Данные!$A$2:$A$341,"<="&Параметры!$B$2,Данные!$E$2:$E$341,Параметры!$B$4)} -> 0 | H36: {=SUMIFS(Данные!$D$2:$D$341,Данные!$B$2:$B$341,$A36,Данные!$F$2:$F$341,H$1,Данные!$A$2:$A$341,">="&Параметры!$B$1,Данные!$A$2:$A$341,"<="&Параметры!$B$2,Данные!$E$2:$E$341,Параметры!$B$4)} -> 0 | I36: {=SUMIFS(Данные!$D$2:$D$341,Данные!$B$2:$B$341,$A36,Данные!$F$2:$F$341,I$1,Данные!$A$2:$A$341,">="&Параметры!$B$1,Данные!$A$2:$A$341,"<="&Параметры!$B$2,Данные!$E$2:$E$341,Параметры!$B$4)} -> 0 | ... P36: {=SUMIFS(Данные!$D$2:$D$341,Данные!$B$2:$B$341,$A36,Данные!$F$2:$F$341,P$1,Данные!$A$2:$A$341,">="&Параметры!$B$1,Данные!$A$2:$A$341,"<="&Параметры!$B$2,Данные!$E$2:$E$341,Параметры!$B$4)} -> 0 | Q36: {=SUM(B36:P36)} -> 335621.85
A37: Итого группа 6 | B37: {=SUM(B32:B36)} -> 0 | C37: {=SUM(C32:C36)} -> 418630.96 | D37: {=SUM(D32:D36)} -> 440103.63 | E37: {=SUM(E32:E36)} -> 0 | F37: {=SUM(F32:F36)} -> 0 | G37: {=SUM(G32:G36)} -> 0 | H37: {=SUM(H32:H36)} -> -10345.15 | I37: {=SUM(I32:I36)} -> 299940.6 | ... Q37: {=SUM(Q32:Q36)} -> 3682809.4
A38: {=Статьи!A32} -> Чай 4 | B38: {=SUMIFS(Данные!$D$2:$D$341,Данные!$B$2:$B$341,$A38,Данные!$F$2:$F$341,B$1,Данные!$A$2:$A$341,">="&Параметры!$B$1,Данные!$A$2:$A$341,"<="&Параметры!$B$2,Данные!$E$2:$E$341,Параметры!$B$4)} -> 0 | C38: {=SUMIFS(Данные!$D$2:$D$341,Данные!$B$2:$B$341,$A38,Данные!$F$2:$F$341,C$1,Данные!$A$2:$A$341,">="&Параметры!$B$1,Данные!$A$2:$A$341,"<="&Параметры!$B$2,Данные!$E$2:$E$341,Параметры!$B$4)} -> 0 | D38: {=SUMIFS(Данные!$D$2:$D$341,Данные!$B$2:$B$341,$A38,Данные!$F$2:$F$341,D$1,Данные!$A$2:$A$341,">="&Параметры!$B$1,Данные!$A$2:$A$341,"<="&Параметры!$B$2,Данные!$E$2:$E$341,Параметры!$B$4)} -> 67332.71 | E38: {=SUMIFS(Данные!$D$2:$D$341,Данные!$B$2:$B$341,$A38,Данные!$F$2:$F$341,E$1,Данные!$A$2:$A$341,">="&Параметры!$B$1,Данные!$A$2:$A$341,"<="&Параметры!$B$2,Данные!$E$2:$E$341,Параметры!$B$4)} -> 0 | F38: {=SUMIFS(Данные!$D$2:$D$341,Данные!$B$2:$B$341,$A38,Данные!$F$2:$F$341,F$1,Данные!$A$2:$A$341,">="&Параметры!$B$1,Данные!$A$2:$A$341,"<="&Параметры!$B$2,Данные!$E$2:$E$341,Параметры!$B$4)} -> 339125.22 | G38: {=SUMIFS(Данные!$D$2:$D$341,Данные!$B$2:$B$341,$A38,Данные!$F$2:$F$341,G$1,Данные!$A$2:$A$341,">="&Параметры!$B$1,Данные!$A$2:$A$341,"<="&Параметры!$B$2,Данные!$E$2:$E$341,Параметры!$B$4)} -> 286133.45 | H38: {=SUMIFS(Данные!$D$2:$D$341,Данные!$B$2:$B$341,$A38,Данные!$F$2:$F$341,H$1,Данные!$A$2:$A$341,">="&Параметры!$B$1,Данные!$A$2:$A$341,"<="&Параметры!$B$2,Данные!$E$2:$E$341,Параметры!$B$4)} -> 0 | I38: {=SUMIFS(Данные!$D$2:$D$341,Данные!$B$2:$B$341,$A38,Данные!$F$2:$F$341,I$1,Данные!$A$2:$A$341,">="&Параметры!$B$1,Данные!$A$2:$A$341,"<="&Параметры!$B$2,Данные!$E$2:$E$341,Параметры!$B$4)} -> 0 | ... P38: {=SUMIFS(Данные!$D$2:$D$341,Данные!$B$2:$B$341,$A38,Данные!$F$2:$F$341,P$1,Данные!$A$2:$A$341,">="&Параметры!$B$1,Данные!$A$2:$A$341,"<="&Параметры!$B$2,Данные!$E$2:$E$341,Параметры!$B$4)} -> 0 | Q38: {=SUM(B38:P38)} -> 899093.63
A39: {=Статьи!A33} -> Чаи 4 | B39: {=SUMIFS(Данные!$D$2:$D$341,Данные!$B$2:$B$341,$A39,Данные!$F$2:$F$341,B$1,Данные!$A$2:$A$341,">="&Параметры!$B$1,Данные!$A$2:$A$341,"<="&Параметры!$B$2,Данные!$E$2:$E$341,Параметры!$B$4)} -> 0 | C39: {=SUMIFS(Данные!$D$2:$D$341,Данные!$B$2:$B$341,$A39,Данные!$F$2:$F$341,C$1,Данные!$A$2:$A$341,">="&Параметры!$B$1,Данные!$A$2:$A$341,"<="&Параметры!$B$2,Данные!$E$2:$E$341,Параметры!$B$4)} -> -7931.29 | D39: {=SUMIFS(Данные!$D$2:$D$341,Данные!$B$2:$B$341,$A39,Данные!$F$2:$F$341,D$1,Данные!$A$2:$A$341,">="&Параметры!$B$1,Данные!$A$2:$A$341,"<="&Параметры!$B$2,Данные!$E$2:$E$341,Параметры!$B$4)} -> 0 | E39: {=SUMIFS(Данные!$D$2:$D$341,Данные!$B$2:$B$341,$A39,Данные!$F$2:$F$341,E$1,Данные!$A$2:$A$341,">="&Параметры!$B$1,Данные!$A$2:$A$341,"<="&Параметры!$B$2,Данные!$E$2:$E$341,Параметры!$B$4)} -> -43783.02 | F39: {=SUMIFS(Данные!$D$2:$D$341,Данные!$B$2:$B$341,$A39,Данные!$F$2:$F$341,F$1,Данные!$A$2:$A$341,">="&Параметры!$B$1,Данные!$A$2:$A$341,"<="&Параметры!$B$2,Данные!$E$2:$E$341,Параметры!$B$4)} -> 0 | G39: {=SUMIFS(Данные!$D$2:$D$341,Данные!$B$2:$B$341,$A39,Данные!$F$2:$F$341,G$1,Данные!$A$2:$A$341,">="&Параметры!$B$1,Данные!$A$2:$A$341,"<="&Параметры!$B$2,Данные!$E$2:$E$341,Параметры!$B$4)} -> 0 | H39: {=SUMIFS(Данные!$D$2:$D$341,Данные!$B$2:$B$341,$A39,Данные!$F$2:$F$341,H$1,Данные!$A$2:$A$341,">="&Параметры!$B$1,Данные!$A$2:$A$341,"<="&Параметры!$B$2,Данные!$E$2:$E$341,Параметры!$B$4)} -> 0 | I39: {=SUMIFS(Данные!$D$2:$D$341,Данные!$B$2:$B$341,$A39,Данные!$F$2:$F$341,I$1,Данные!$A$2:$A$341,">="&Параметры!$B$1,Данные!$A$2:$A$341,"<="&Параметры!$B$2,Данные!$E$2:$E$341,Параметры!$B$4)} -> 0 | ... P39: {=SUMIFS(Данные!$D$2:$D$341,Данные!$B$2:$B$341,$A39,Данные!$F$2:$F$341,P$1,Данные!$A$2:$A$341,">="&Параметры!$B$1,Данные!$A$2:$A$341,"<="&Параметры!$B$2,Данные!$E$2:$E$341,Параметры!$B$4)} -> 0 | Q39: {=SUM(B39:P39)} -> 234897.76
A40: {=Статьи!A34} -> Ёлка 4 | B40: {=SUMIFS(Данные!$D$2:$D$341,Данные!$B$2:$B$341,$A40,Данные!$F$2:$F$341,B$1,Данные!$A$2:$A$341,">="&Параметры!$B$1,Данные!$A$2:$A$341,"<="&Параметры!$B$2,Данные!$E$2:$E$341,Параметры!$B$4)} -> 0 | C40: {=SUMIFS(Данные!$D$2:$D$341,Данные!$B$2:$B$341,$A40,Данные!$F$2:$F$341,C$1,Данные!$A$2:$A$341,">="&Параметры!$B$1,Данные!$A$2:$A$341,"<="&Параметры!$B$2,Данные!$E$2:$E$341,Параметры!$B$4)} -> 52231.74 | D40: {=SUMIFS(Данные!$D$2:$D$341,Данные!$B$2:$B$341,$A40,Данные!$F$2:$F$341,D$1,Данные!$A$2:$A$341,">="&Параметры!$B$1,Данные!$A$2:$A$341,"<="&Параметры!$B$2,Данные!$E$2:$E$341,Параметры!$B$4)} -> 0 | E40: {=SUMIFS(Данные!$D$2:$D$341,Данные!$B$2:$B$341,$A40,Данные!$F$2:$F$341,E$1,Данные!$A$2:$A$341,">="&Параметры!$B$1,Данные!$A$2:$A$341,"<="&Параметры!$B$2,Данные!$E$2:$E$341,Параметры!$B$4)} -> 0 | F40: {=SUMIFS(Данные!$D$2:$D$341,Данные!$B$2:$B$341,$A40,Данные!$F$2:$F$341,F$1,Данные!$A$2:$A$341,">="&Параметры!$B$1,Данные!$A$2:$A$341,"<="&Параметры!$B$2,Данные!$E$2:$E$341,Параметры!$B$4)} -> 0 | G40: {=SUMIFS(Данные!$D$2:$D$341,Данные!$B$2:$B$341,$A40,Данные!$F$2:$F$341,G$1,Данные!$A$2:$A$341,">="&Параметры!$B$1,Данные!$A$2:$A$341,"<="&Параметры!$B$2,Данные!$E$2:$E$341,Параметры!$B$4)} -> 0 | H40: {=SUMIFS(Данные!$D$2:$D$341,Данные!$B$2:$B$341,$A40,Данные!$F$2:$F$341,H$1,Данные!$A$2:$A$341,">="&Параметры!$B$1,Данные!$A$2:$A$341,"<="&Параметры!$B$2,Данные!$E$2:$E$341,Параметры!$B$4)} -> 0 | I40: {=SUMIFS(Данные!$D$2:$D$341,Данные!$B$2:$B$341,$A40,Данные!$F$2:$F$341,I$1,Данные!$A$2:$A$341,">="&Параметры!$B$1,Данные!$A$2:$A$341,"<="&Параметры!$B$2,Данные!$E$2:$E$341,Параметры!$B$4)} -> 0 | ... P40: {=SUMIFS(Данные!$D$2:$D$341,Данные!$B$2:$B$341,$A40,Данные!$F$2:$F$341,P$1,Данные!$A$2:$A$341,">="&Параметры!$B$1,Данные!$A$2:$A$341,"<="&Параметры!$B$2,Данные!$E$2:$E$341,Параметры!$B$4)} -> 0 | Q40: {=SUM(B40:P40)} -> 285343.67
A41: {=Статьи!A35} -> Елка 4 | B41: {=SUMIFS(Данные!$D$2:$D$341,Данные!$B$2:$B$341,$A41,Данные!$F$2:$F$341,B$1,Данные!$A$2:$A$341,">="&Параметры!$B$1,Данные!$A$2:$A$341,"<="&Параметры!$B$2,Данные!$E$2:$E$341,Параметры!$B$4)} -> 0 | C41: {=SUMIFS(Данные!$D$2:$D$341,Данные!$B$2:$B$341,$A41,Данные!$F$2:$F$341,C$1,Данные!$A$2:$A$341,">="&Параметры!$B$1,Данные!$A$2:$A$341,"<="&Параметры!$B$2,Данные!$E$2:$E$341,Параметры!$B$4)} -> 0 | D41: {=SUMIFS(Данные!$D$2:$D$341,Данные!$B$2:$B$341,$A41,Данные!$F$2:$F$341,D$1,Данные!$A$2:$A$341,">="&Параметры!$B$1,Данные!$A$2:$A$341,"<="&Параметры!$B$2,Данные!$E$2:$E$341,Параметры!$B$4)} -> 0 | E41: {=SUMIFS(Данные!$D$2:$D$341,Данные!$B$2:$B$341,$A41,Данные!$F$2:$F$341,E$1,Данные!$A$2:$A$341,">="&Параметры!$B$1,Данные!$A$2:$A$341,"<="&Параметры!$B$2,Данные!$E$2:$E$341,Параметры!$B$4)} -> 0 | F41: {=SUMIFS(Данные!$D$2:$D$341,Данные!$B$2:$B$341,$A41,Данные!$F$2:$F$341,F$1,Данные!$A$2:$A$341,">="&Параметры!$B$1,Данные!$A$2:$A$341,"<="&Параметры!$B$2,Данные!$E$2:$E$341,Параметры!$B$4)} -> 0 | G41: {=SUMIFS(Данные!$D$2:$D$341,Данные!$B$2:$B$341,$A41,Данные!$F$2:$F$341,G$1,Данные!$A$2:$A$341,">="&Параметры!$B$1,Данные!$A$2:$A$341,"<="&Параметры!$B$2,Данные!$E$2:$E$341,Параметры!$B$4)} -> 307485.51 | H41: {=SUMIFS(Данные!$D$2:$D$341,Данные!$B$2:$B$341,$A41,Данные!$F$2:$F$341,H$1,Данные!$A$2:$A$341,">="&Параметры!$B$1,Данные!$A$2:$A$341,"<="&Параметры!$B$2,Данные!$E$2:$E$341,Параметры!$B$4)} -> 0 | I41: {=SUMIFS(Данные!$D$2:$D$341,Данные!$B$2:$B$341,$A41,Данные!$F$2:$F$341,I$1,Данные!$A$2:$A$341,">="&Параметры!$B$1,Данные!$A$2:$A$341,"<="&Параметры!$B$2,Данные!$E$2:$E$341,Параметры!$B$4)} -> 0 | ... P41: {=SUMIFS(Данные!$D$2:$D$341,Данные!$B$2:$B$341,$A41,Данные!$F$2:$F$341,P$1,Данные!$A$2:$A$341,">="&Параметры!$B$1,Данные!$A$2:$A$341,"<="&Параметры!$B$2,Данные!$E$2:$E$341,Параметры!$B$4)} -> 0 | Q41: {=SUM(B41:P41)} -> 554119.53
A42: {=Статьи!A36} -> Аренда 4 | B42: {=SUMIFS(Данные!$D$2:$D$341,Данные!$B$2:$B$341,$A42,Данные!$F$2:$F$341,B$1,Данные!$A$2:$A$341,">="&Параметры!$B$1,Данные!$A$2:$A$341,"<="&Параметры!$B$2,Данные!$E$2:$E$341,Параметры!$B$4)} -> 0 | C42: {=SUMIFS(Данные!$D$2:$D$341,Данные!$B$2:$B$341,$A42,Данные!$F$2:$F$341,C$1,Данные!$A$2:$A$341,">="&Параметры!$B$1,Данные!$A$2:$A$341,"<="&Параметры!$B$2,Данные!$E$2:$E$341,Параметры!$B$4)} -> 0 | D42: {=SUMIFS(Данные!$D$2:$D$341,Данные!$B$2:$B$341,$A42,Данные!$F$2:$F$341,D$1,Данные!$A$2:$A$341,">="&Параметры!$B$1,Данные!$A$2:$A$341,"<="&Параметры!$B$2,Данные!$E$2:$E$341,Параметры!$B$4)} -> 0 | E42: {=SUMIFS(Данные!$D$2:$D$341,Данные!$B$2:$B$341,$A42,Данные!$F$2:$F$341,E$1,Данные!$A$2:$A$341,">="&Параметры!$B$1,Данные!$A$2:$A$341,"<="&Параметры!$B$2,Данные!$E$2:$E$341,Параметры!$B$4)} -> 0 | F42: {=SUMIFS(Данные!$D$2:$D$341,Данные!$B$2:$B$341,$A42,Данные!$F$2:$F$341,F$1,Данные!$A$2:$A$341,">="&Параметры!$B$1,Данные!$A$2:$A$341,"<="&Параметры!$B$2,Данные!$E$2:$E$341,Параметры!$B$4)} -> 0 | G42: {=SUMIFS(Данные!$D$2:$D$341,Данные!$B$2:$B$341,$A42,Данные!$F$2:$F$341,G$1,Данные!$A$2:$A$341,">="&Параметры!$B$1,Данные!$A$2:$A$341,"<="&Параметры!$B$2,Данные!$E$2:$E$341,Параметры!$B$4)} -> 0 | H42: {=SUMIFS(Данные!$D$2:$D$341,Данные!$B$2:$B$341,$A42,Данные!$F$2:$F$341,H$1,Данные!$A$2:$A$341,">="&Параметры!$B$1,Данные!$A$2:$A$341,"<="&Параметры!$B$2,Данные!$E$2:$E$341,Параметры!$B$4)} -> 0 | I42: {=SUMIFS(Данные!$D$2:$D$341,Данные!$B$2:$B$341,$A42,Данные!$F$2:$F$341,I$1,Данные!$A$2:$A$341,">="&Параметры!$B$1,Данные!$A$2:$A$341,"<="&Параметры!$B$2,Данные!$E$2:$E$341,Параметры!$B$4)} -> 8341.13 | ... P42: {=SUMIFS(Данные!$D$2:$D$341,Данные!$B$2:$B$341,$A42,Данные!$F$2:$F$341,P$1,Данные!$A$2:$A$341,">="&Параметры!$B$1,Данные!$A$2:$A$341,"<="&Параметры!$B$2,Данные!$E$2:$E$341,Параметры!$B$4)} -> 0 | Q42: {=SUM(B42:P42)} -> 285340.48
A43: Итого группа 7 | B43: {=SUM(B38:B42)} -> 0 | C43: {=SUM(C38:C42)} -> 44300.45 | D43: {=SUM(D38:D42)} -> 67332.71 | E43: {=SUM(E38:E42)} -> -43783.02 | F43: {=SUM(F38:F42)} -> 339125.22 | G43: {=SUM(G38:G42)} -> 593618.96 | H43: {=SUM(H38:H42)} -> 0 | I43: {=SUM(I38:I42)} -> 8341.13 | ... Q43: {=SUM(Q38:Q42)} -> 2258795.1
A44: {=Статьи!A37} -> Связь 4 | B44: {=SUMIFS(Данные!$D$2:$D$341,Данные!$B$2:$B$341,$A44,Данные!$F$2:$F$341,B$1,Данные!$A$2:$A$341,">="&Параметры!$B$1,Данные!$A$2:$A$341,"<="&Параметры!$B$2,Данные!$E$2:$E$341,Параметры!$B$4)} -> 206710.29 | C44: {=SUMIFS(Данные!$D$2:$D$341,Данные!$B$2:$B$341,$A44,Данные!$F$2:$F$341,C$1,Данные!$A$2:$A$341,">="&Параметры!$B$1,Данные!$A$2:$A$341,"<="&Параметры!$B$2,Данные!$E$2:$E$341,Параметры!$B$4)} -> 263411.22 | D44: {=SUMIFS(Данные!$D$2:$D$341,Данные!$B$2:$B$341,$A44,Данные!$F$2:$F$341,D$1,Данные!$A$2:$A$341,">="&Параметры!$B$1,Данные!$A$2:$A$341,"<="&Параметры!$B$2,Данные!$E$2:$E$341,Параметры!$B$4)} -> 0 | E44: {=SUMIFS(Данные!$D$2:$D$341,Данные!$B$2:$B$341,$A44,Данные!$F$2:$F$341,E$1,Данные!$A$2:$A$341,">="&Параметры!$B$1,Данные!$A$2:$A$341,"<="&Параметры!$B$2,Данные!$E$2:$E$341,Параметры!$B$4)} -> 0 | F44: {=SUMIFS(Данные!$D$2:$D$341,Данные!$B$2:$B$341,$A44,Данные!$F$2:$F$341,F$1,Данные!$A$2:$A$341,">="&Параметры!$B$1,Данные!$A$2:$A$341,"<="&Параметры!$B$2,Данные!$E$2:$E$341,Параметры!$B$4)} -> 0 | G44: {=SUMIFS(Данные!$D$2:$D$341,Данные!$B$2:$B$341,$A44,Данные!$F$2:$F$341,G$1,Данные!$A$2:$A$341,">="&Параметры!$B$1,Данные!$A$2:$A$341,"<="&Параметры!$B$2,Данные!$E$2:$E$341,Параметры!$B$4)} -> 331308.82 | H44: {=SUMIFS(Данные!$D$2:$D$341,Данные!$B$2:$B$341,$A44,Данные!$F$2:$F$341,H$1,Данные!$A$2:$A$341,">="&Параметры!$B$1,Данные!$A$2:$A$341,"<="&Параметры!$B$2,Данные!$E$2:$E$341,Параметры!$B$4)} -> 0 | I44: {=SUMIFS(Данные!$D$2:$D$341,Данные!$B$2:$B$341,$A44,Данные!$F$2:$F$341,I$1,Данные!$A$2:$A$341,">="&Параметры!$B$1,Данные!$A$2:$A$341,"<="&Параметры!$B$2,Данные!$E$2:$E$341,Параметры!$B$4)} -> 0 | ... P44: {=SUMIFS(Данные!$D$2:$D$341,Данные!$B$2:$B$341,$A44,Данные!$F$2:$F$341,P$1,Данные!$A$2:$A$341,">="&Параметры!$B$1,Данные!$A$2:$A$341,"<="&Параметры!$B$2,Данные!$E$2:$E$341,Параметры!$B$4)} -> 0 | Q44: {=SUM(B44:P44)} -> 1076516.1
A45: {=Статьи!A38} -> Налог 4 | B45: {=SUMIFS(Данные!$D$2:$D$341,Данные!$B$2:$B$341,$A45,Данные!$F$2:$F$341,B$1,Данные!$A$2:$A$341,">="&Параметры!$B$1,Данные!$A$2:$A$341,"<="&Параметры!$B$2,Данные!$E$2:$E$341,Параметры!$B$4)} -> 0 | C45: {=SUMIFS(Данные!$D$2:$D$341,Данные!$B$2:$B$341,$A45,Данные!$F$2:$F$341,C$1,Данные!$A$2:$A$341,">="&Параметры!$B$1,Данные!$A$2:$A$341,"<="&Параметры!$B$2,Данные!$E$2:$E$341,Параметры!$B$4)} -> 0 | D45: {=SUMIFS(Данные!$D$2:$D$341,Данные!$B$2:$B$341,$A45,Данные!$F$2:$F$341,D$1,Данные!$A$2:$A$341,">="&Параметры!$B$1,Данные!$A$2:$A$341,"<="&Параметры!$B$2,Данные!$E$2:$E$341,Параметры!$B$4)} -> 0 | E45: {=SUMIFS(Данные!$D$2:$D$341,Данные!$B$2:$B$341,$A45,Данные!$F$2:$F$341,E$1,Данные!$A$2:$A$341,">="&Параметры!$B$1,Данные!$A$2:$A$341,"<="&Параметры!$B$2,Данные!$E$2:$E$341,Параметры!$B$4)} -> 49937.77 | F45: {=SUMIFS(Данные!$D$2:$D$341,Данные!$B$2:$B$341,$A45,Данные!$F$2:$F$341,F$1,Данные!$A$2:$A$341,">="&Параметры!$B$1,Данные!$A$2:$A$341,"<="&Параметры!$B$2,Данные!$E$2:$E$341,Параметры!$B$4)} -> 0 | G45: {=SUMIFS(Данные!$D$2:$D$341,Данные!$B$2:$B$341,$A45,Данные!$F$2:$F$341,G$1,Данные!$A$2:$A$341,">="&Параметры!$B$1,Данные!$A$2:$A$341,"<="&Параметры!$B$2,Данные!$E$2:$E$341,Параметры!$B$4)} -> 0 | H45: {=SUMIFS(Данные!$D$2:$D$341,Данные!$B$2:$B$341,$A45,Данные!$F$2:$F$341,H$1,Данные!$A$2:$A$341,">="&Параметры!$B$1,Данные!$A$2:$A$341,"<="&Параметры!$B$2,Данные!$E$2:$E$341,Параметры!$B$4)} -> 0 | I45: {=SUMIFS(Данные!$D$2:$D$341,Данные!$B$2:$B$341,$A45,Данные!$F$2:$F$341,I$1,Данные!$A$2:$A$341,">="&Параметры!$B$1,Данные!$A$2:$A$341,"<="&Параметры!$B$2,Данные!$E$2:$E$341,Параметры!$B$4)} -> 0 | ... P45: {=SUMIFS(Данные!$D$2:$D$341,Данные!$B$2:$B$341,$A45,Данные!$F$2:$F$341,P$1,Данные!$A$2:$A$341,">="&Параметры!$B$1,Данные!$A$2:$A$341,"<="&Параметры!$B$2,Данные!$E$2:$E$341,Параметры!$B$4)} -> 0 | Q45: {=SUM(B45:P45)} -> 701762.03
A46: {=Статьи!A39} -> Доход 4 | B46: {=SUMIFS(Данные!$D$2:$D$341,Данные!$B$2:$B$341,$A46,Данные!$F$2:$F$341,B$1,Данные!$A$2:$A$341,">="&Параметры!$B$1,Данные!$A$2:$A$341,"<="&Параметры!$B$2,Данные!$E$2:$E$341,Параметры!$B$4)} -> 179183.33 | C46: {=SUMIFS(Данные!$D$2:$D$341,Данные!$B$2:$B$341,$A46,Данные!$F$2:$F$341,C$1,Данные!$A$2:$A$341,">="&Параметры!$B$1,Данные!$A$2:$A$341,"<="&Параметры!$B$2,Данные!$E$2:$E$341,Параметры!$B$4)} -> 285593.17 | D46: {=SUMIFS(Данные!$D$2:$D$341,Данные!$B$2:$B$341,$A46,Данные!$F$2:$F$341,D$1,Данные!$A$2:$A$341,">="&Параметры!$B$1,Данные!$A$2:$A$341,"<="&Параметры!$B$2,Данные!$E$2:$E$341,Параметры!$B$4)} -> 0 | E46: {=SUMIFS(Данные!$D$2:$D$341,Данные!$B$2:$B$341,$A46,Данные!$F$2:$F$341,E$1,Данные!$A$2:$A$341,">="&Параметры!$B$1,Данные!$A$2:$A$341,"<="&Параметры!$B$2,Данные!$E$2:$E$341,Параметры!$B$4)} -> 0 | F46: {=SUMIFS(Данные!$D$2:$D$341,Данные!$B$2:$B$341,$A46,Данные!$F$2:$F$341,F$1,Данные!$A$2:$A$341,">="&Параметры!$B$1,Данные!$A$2:$A$341,"<="&Параметры!$B$2,Данные!$E$2:$E$341,Параметры!$B$4)} -> 0 | G46: {=SUMIFS(Данные!$D$2:$D$341,Данные!$B$2:$B$341,$A46,Данные!$F$2:$F$341,G$1,Данные!$A$2:$A$341,">="&Параметры!$B$1,Данные!$A$2:$A$341,"<="&Параметры!$B$2,Данные!$E$2:$E$341,Параметры!$B$4)} -> 0 | H46: {=SUMIFS(Данные!$D$2:$D$341,Данные!$B$2:$B$341,$A46,Данные!$F$2:$F$341,H$1,Данные!$A$2:$A$341,">="&Параметры!$B$1,Данные!$A$2:$A$341,"<="&Параметры!$B$2,Данные!$E$2:$E$341,Параметры!$B$4)} -> 0 | I46: {=SUMIFS(Данные!$D$2:$D$341,Данные!$B$2:$B$341,$A46,Данные!$F$2:$F$341,I$1,Данные!$A$2:$A$341,">="&Параметры!$B$1,Данные!$A$2:$A$341,"<="&Параметры!$B$2,Данные!$E$2:$E$341,Параметры!$B$4)} -> 0 | ... P46: {=SUMIFS(Данные!$D$2:$D$341,Данные!$B$2:$B$341,$A46,Данные!$F$2:$F$341,P$1,Данные!$A$2:$A$341,">="&Параметры!$B$1,Данные!$A$2:$A$341,"<="&Параметры!$B$2,Данные!$E$2:$E$341,Параметры!$B$4)} -> 0 | Q46: {=SUM(B46:P46)} -> 342152.67
A47: {=Статьи!A40} -> Сырьё 4 | B47: {=SUMIFS(Данные!$D$2:$D$341,Данные!$B$2:$B$341,$A47,Данные!$F$2:$F$341,B$1,Данные!$A$2:$A$341,">="&Параметры!$B$1,Данные!$A$2:$A$341,"<="&Параметры!$B$2,Данные!$E$2:$E$341,Параметры!$B$4)} -> 0 | C47: {=SUMIFS(Данные!$D$2:$D$341,Данные!$B$2:$B$341,$A47,Данные!$F$2:$F$341,C$1,Данные!$A$2:$A$341,">="&Параметры!$B$1,Данные!$A$2:$A$341,"<="&Параметры!$B$2,Данные!$E$2:$E$341,Параметры!$B$4)} -> 0 | D47: {=SUMIFS(Данные!$D$2:$D$341,Данные!$B$2:$B$341,$A47,Данные!$F$2:$F$341,D$1,Данные!$A$2:$A$341,">="&Параметры!$B$1,Данные!$A$2:$A$341,"<="&Параметры!$B$2,Данные!$E$2:$E$341,Параметры!$B$4)} -> 253436.52 | E47: {=SUMIFS(Данные!$D$2:$D$341,Данные!$B$2:$B$341,$A47,Данные!$F$2:$F$341,E$1,Данные!$A$2:$A$341,">="&Параметры!$B$1,Данные!$A$2:$A$341,"<="&Параметры!$B$2,Данные!$E$2:$E$341,Параметры!$B$4)} -> 0 | F47: {=SUMIFS(Данные!$D$2:$D$341,Данные!$B$2:$B$341,$A47,Данные!$F$2:$F$341,F$1,Данные!$A$2:$A$341,">="&Параметры!$B$1,Данные!$A$2:$A$341,"<="&Параметры!$B$2,Данные!$E$2:$E$341,Параметры!$B$4)} -> 0 | G47: {=SUMIFS(Данные!$D$2:$D$341,Данные!$B$2:$B$341,$A47,Данные!$F$2:$F$341,G$1,Данные!$A$2:$A$341,">="&Параметры!$B$1,Данные!$A$2:$A$341,"<="&Параметры!$B$2,Данные!$E$2:$E$341,Параметры!$B$4)} -> 144828.35 | H47: {=SUMIFS(Данные!$D$2:$D$341,Данные!$B$2:$B$341,$A47,Данные!$F$2:$F$341,H$1,Данные!$A$2:$A$341,">="&Параметры!$B$1,Данные!$A$2:$A$341,"<="&Параметры!$B$2,Данные!$E$2:$E$341,Параметры!$B$4)} -> 0 | I47: {=SUMIFS(Данные!$D$2:$D$341,Данные!$B$2:$B$341,$A47,Данные!$F$2:$F$341,I$1,Данные!$A$2:$A$341,">="&Параметры!$B$1,Данные!$A$2:$A$341,"<="&Параметры!$B$2,Данные!$E$2:$E$341,Параметры!$B$4)} -> 0 | ... P47: {=SUMIFS(Данные!$D$2:$D$341,Данные!$B$2:$B$341,$A47,Данные!$F$2:$F$341,P$1,Данные!$A$2:$A$341,">="&Параметры!$B$1,Данные!$A$2:$A$341,"<="&Параметры!$B$2,Данные!$E$2:$E$341,Параметры!$B$4)} -> 385103.67 | Q47: {=SUM(B47:P47)} -> 1297304
A48: {=Статьи!A41} -> Сырье 4 | B48: {=SUMIFS(Данные!$D$2:$D$341,Данные!$B$2:$B$341,$A48,Данные!$F$2:$F$341,B$1,Данные!$A$2:$A$341,">="&Параметры!$B$1,Данные!$A$2:$A$341,"<="&Параметры!$B$2,Данные!$E$2:$E$341,Параметры!$B$4)} -> 62537.84 | C48: {=SUMIFS(Данные!$D$2:$D$341,Данные!$B$2:$B$341,$A48,Данные!$F$2:$F$341,C$1,Данные!$A$2:$A$341,">="&Параметры!$B$1,Данные!$A$2:$A$341,"<="&Параметры!$B$2,Данные!$E$2:$E$341,Параметры!$B$4)} -> 131675.89 | D48: {=SUMIFS(Данные!$D$2:$D$341,Данные!$B$2:$B$341,$A48,Данные!$F$2:$F$341,D$1,Данные!$A$2:$A$341,">="&Параметры!$B$1,Данные!$A$2:$A$341,"<="&Параметры!$B$2,Данные!$E$2:$E$341,Параметры!$B$4)} -> 199150.01 | E48: {=SUMIFS(Данные!$D$2:$D$341,Данные!$B$2:$B$341,$A48,Данные!$F$2:$F$341,E$1,Данные!$A$2:$A$341,">="&Параметры!$B$1,Данные!$A$2:$A$341,"<="&Параметры!$B$2,Данные!$E$2:$E$341,Параметры!$B$4)} -> 0 | F48: {=SUMIFS(Данные!$D$2:$D$341,Данные!$B$2:$B$341,$A48,Данные!$F$2:$F$341,F$1,Данные!$A$2:$A$341,">="&Параметры!$B$1,Данные!$A$2:$A$341,"<="&Параметры!$B$2,Данные!$E$2:$E$341,Параметры!$B$4)} -> 0 | G48: {=SUMIFS(Данные!$D$2:$D$341,Данные!$B$2:$B$341,$A48,Данные!$F$2:$F$341,G$1,Данные!$A$2:$A$341,">="&Параметры!$B$1,Данные!$A$2:$A$341,"<="&Параметры!$B$2,Данные!$E$2:$E$341,Параметры!$B$4)} -> 0 | H48: {=SUMIFS(Данные!$D$2:$D$341,Данные!$B$2:$B$341,$A48,Данные!$F$2:$F$341,H$1,Данные!$A$2:$A$341,">="&Параметры!$B$1,Данные!$A$2:$A$341,"<="&Параметры!$B$2,Данные!$E$2:$E$341,Параметры!$B$4)} -> 2514.75 | I48: {=SUMIFS(Данные!$D$2:$D$341,Данные!$B$2:$B$341,$A48,Данные!$F$2:$F$341,I$1,Данные!$A$2:$A$341,">="&Параметры!$B$1,Данные!$A$2:$A$341,"<="&Параметры!$B$2,Данные!$E$2:$E$341,Параметры!$B$4)} -> 0 | ... P48: {=SUMIFS(Данные!$D$2:$D$341,Данные!$B$2:$B$341,$A48,Данные!$F$2:$F$341,P$1,Данные!$A$2:$A$341,">="&Параметры!$B$1,Данные!$A$2:$A$341,"<="&Параметры!$B$2,Данные!$E$2:$E$341,Параметры!$B$4)} -> 0 | Q48: {=SUM(B48:P48)} -> 529055.37
A49: Итого группа 8 | B49: {=SUM(B44:B48)} -> 448431.46 | C49: {=SUM(C44:C48)} -> 680680.28 | D49: {=SUM(D44:D48)} -> 452586.53 | E49: {=SUM(E44:E48)} -> 49937.77 | F49: {=SUM(F44:F48)} -> 0 | G49: {=SUM(G44:G48)} -> 476137.17 | H49: {=SUM(H44:H48)} -> 2514.75 | I49: {=SUM(I44:I48)} -> 0 | ... Q49: {=SUM(Q44:Q48)} -> 3946790.2

Sheet ПоКатегориям
A1: ПоКатегориям | B1: Кат-01 | C1: Кат-02 | D1: Кат-03 | E1: Кат-04 | F1: Кат-05 | G1: Кат-06 | H1: Кат-07 | I1: Кат-08 | J1: Кат-09 | K1: Кат-10 | L1: Кат-11 | M1: Кат-12 | N1: Кат-13 | O1: Кат-14 | P1: Кат-15 | Q1: Кат-16 | R1: Кат-17 | S1: Кат-18 | T1: Кат-19 | U1: Кат-20
A2: {=Статьи!A2} -> Чай 1 | B2: {=SUMIFS(data_amt,data_item,$A2,data_cat,B$1,data_dir,Параметры!$B$3)} -> 0 | C2: {=SUMIFS(data_amt,data_item,$A2,data_cat,C$1,data_dir,Параметры!$B$3)} -> 0 | D2: {=SUMIFS(data_amt,data_item,$A2,data_cat,D$1,data_dir,Параметры!$B$3)} -> 407112.34 | E2: {=SUMIFS(data_amt,data_item,$A2,data_cat,E$1,data_dir,Параметры!$B$3)} -> 303298.19 | F2: {=SUMIFS(data_amt,data_item,$A2,data_cat,F$1,data_dir,Параметры!$B$3)} -> 0 | G2: {=SUMIFS(data_amt,data_item,$A2,data_cat,G$1,data_dir,Параметры!$B$3)} -> 0 | H2: {=SUMIFS(data_amt,data_item,$A2,data_cat,H$1,data_dir,Параметры!$B$3)} -> 0 | I2: {=SUMIFS(data_amt,data_item,$A2,data_cat,I$1,data_dir,Параметры!$B$3)} -> 239810.47 | ... U2: {=SUMIFS(data_amt,data_item,$A2,data_cat,U$1,data_dir,Параметры!$B$3)} -> 0 | V2: {=SUM(B2:U2)} -> 1095843.6
A3: {=Статьи!A3} -> Чаи 1 | B3: {=SUMIFS(data_amt,data_item,$A3,data_cat,B$1,data_dir,Параметры!$B$3)} -> 0 | C3: {=SUMIFS(data_amt,data_item,$A3,data_cat,C$1,data_dir,Параметры!$B$3)} -> -96224.34 | D3: {=SUMIFS(data_amt,data_item,$A3,data_cat,D$1,data_dir,Параметры!$B$3)} -> 348412.93 | E3: {=SUMIFS(data_amt,data_item,$A3,data_cat,E$1,data_dir,Параметры!$B$3)} -> 0 | F3: {=SUMIFS(data_amt,data_item,$A3,data_cat,F$1,data_dir,Параметры!$B$3)} -> 0 | G3: {=SUMIFS(data_amt,data_item,$A3,data_cat,G$1,data_dir,Параметры!$B$3)} -> 0 | H3: {=SUMIFS(data_amt,data_item,$A3,data_cat,H$1,data_dir,Параметры!$B$3)} -> 150225.98 | I3: {=SUMIFS(data_amt,data_item,$A3,data_cat,I$1,data_dir,Параметры!$B$3)} -> -21565.47 | ... U3: {=SUMIFS(data_amt,data_item,$A3,data_cat,U$1,data_dir,Параметры!$B$3)} -> 0 | V3: {=SUM(B3:U3)} -> 440931.37
A4: {=Статьи!A4} -> Ёлка 1 | B4: {=SUMIFS(data_amt,data_item,$A4,data_cat,B$1,data_dir,Параметры!$B$3)} -> 0 | C4: {=SUMIFS(data_amt,data_item,$A4,data_cat,C$1,data_dir,Параметры!$B$3)} -> 0 | D4: {=SUMIFS(data_amt,data_item,$A4,data_cat,D$1,data_dir,Параметры!$B$3)} -> 0 | E4: {=SUMIFS(data_amt,data_item,$A4,data_cat,E$1,data_dir,Параметры!$B$3)} -> 87697.93 | F4: {=SUMIFS(data_amt,data_item,$A4,data_cat,F$1,data_dir,Параметры!$B$3)} -> 0 | G4: {=SUMIFS(data_amt,data_item,$A4,data_cat,G$1,data_dir,Параметры!$B$3)} -> 239698.95 | H4: {=SUMIFS(data_amt,data_item,$A4,data_cat,H$1,data_dir,Параметры!$B$3)} -> 0 | I4: {=SUMIFS(data_amt,data_item,$A4,data_cat,I$1,data_dir,Параметры!$B$3)} -> 0 | ... U4: {=SUMIFS(data_amt,data_item,$A4,data_cat,U$1,data_dir,Параметры!$B$3)} -> 766210.76 | V4: {=SUM(B4:U4)} -> 1694259.8
A5: {=Статьи!A5} -> Елка 1 | B5: {=SUMIFS(data_amt,data_item,$A5,data_cat,B$1,data_dir,Параметры!$B$3)} -> 131126.71 | C5: {=SUMIFS(data_amt,data_item,$A5,data_cat,C$1,data_dir,Параметры!$B$3)} -> 0 | D5: {=SUMIFS(data_amt,data_item,$A5,data_cat,D$1,data_dir,Параметры!$B$3)} -> -69574.18 | E5: {=SUMIFS(data_amt,data_item,$A5,data_cat,E$1,data_dir,Параметры!$B$3)} -> 295683.49 | F5: {=SUMIFS(data_amt,data_item,$A5,data_cat,F$1,data_dir,Параметры!$B$3)} -> -23248.9 | G5: {=SUMIFS(data_amt,data_item,$A5,data_cat,G$1,data_dir,Параметры!$B$3)} -> 0 | H5: {=SUMIFS(data_amt,data_item,$A5,data_cat,H$1,data_dir,Параметры!$B$3)} -> 0 | I5: {=SUMIFS(data_amt,data_item,$A5,data_cat,I$1,data_dir,Параметры!$B$3)} -> 0 | ... U5: {=SUMIFS(data_amt,data_item,$A5,data_cat,U$1,data_dir,Параметры!$B$3)} -> 459488.31 | V5: {=SUM(B5:U5)} -> 793475.43
A6: {=Статьи!A6} -> Аренда 1 | B6: {=SUMIFS(data_amt,data_item,$A6,data_cat,B$1,data_dir,Параметры!$B$3)} -> 0 | C6: {=SUMIFS(data_amt,data_item,$A6,data_cat,C$1,data_dir,Параметры!$B$3)} -> 0 | D6: {=SUMIFS(data_amt,data_item,$A6,data_cat,D$1,data_dir,Параметры!$B$3)} -> 0 | E6: {=SUMIFS(data_amt,data_item,$A6,data_cat,E$1,data_dir,Параметры!$B$3)} -> 0 | F6: {=SUMIFS(data_amt,data_item,$A6,data_cat,F$1,data_dir,Параметры!$B$3)} -> 0 | G6: {=SUMIFS(data_amt,data_item,$A6,data_cat,G$1,data_dir,Параметры!$B$3)} -> 0 | H6: {=SUMIFS(data_amt,data_item,$A6,data_cat,H$1,data_dir,Параметры!$B$3)} -> 0 | I6: {=SUMIFS(data_amt,data_item,$A6,data_cat,I$1,data_dir,Параметры!$B$3)} -> 0 | ... U6: {=SUMIFS(data_amt,data_item,$A6,data_cat,U$1,data_dir,Параметры!$B$3)} -> 0 | V6: {=SUM(B6:U6)} -> 943078.84
A7: Итого группа 1 | B7: {=SUM(B2:B6)} -> 131126.71 | C7: {=SUM(C2:C6)} -> -96224.34 | D7: {=SUM(D2:D6)} -> 685951.09 | E7: {=SUM(E2:E6)} -> 686679.61 | F7: {=SUM(F2:F6)} -> -23248.9 | G7: {=SUM(G2:G6)} -> 239698.95 | H7: {=SUM(H2:H6)} -> 150225.98 | I7: {=SUM(I2:I6)} -> 218245 | ... V7: {=SUM(V2:V6)} -> 4967589.1
A8: {=Статьи!A7} -> Связь 1 | B8: {=SUMIFS(data_amt,data_item,$A8,data_cat,B$1,data_dir,Параметры!$B$3)} -> 0 | C8: {=SUMIFS(data_amt,data_item,$A8,data_cat,C$1,data_dir,Параметры!$B$3)} -> 103573.35 | D8: {=SUMIFS(data_amt,data_item,$A8,data_cat,D$1,data_dir,Параметры!$B$3)} -> 0 | E8: {=SUMIFS(data_amt,data_item,$A8,data_cat,E$1,data_dir,Параметры!$B$3)} -> 0 | F8: {=SUMIFS(data_amt,data_item,$A8,data_cat,F$1,data_dir,Параметры!$B$3)} -> 0 | G8: {=SUMIFS(data_amt,data_item,$A8,data_cat,G$1,data_dir,Параметры!$B$3)} -> 0 | H8: {=SUMIFS(data_amt,data_item,$A8,data_cat,H$1,data_dir,Параметры!$B$3)} -> 0 | I8: {=SUMIFS(data_amt,data_item,$A8,data_cat,I$1,data_dir,Параметры!$B$3)} -> 0 | ... U8: {=SUMIFS(data_amt,data_item,$A8,data_cat,U$1,data_dir,Параметры!$B$3)} -> 0 | V8: {=SUM(B8:U8)} -> 694156.63
A9: {=Статьи!A8} -> Налог 1 | B9: {=SUMIFS(data_amt,data_item,$A9,data_cat,B$1,data_dir,Параметры!$B$3)} -> 0 | C9: {=SUMIFS(data_amt,data_item,$A9,data_cat,C$1,data_dir,Параметры!$B$3)} -> 0 | D9: {=SUMIFS(data_amt,data_item,$A9,data_cat,D$1,data_dir,Параметры!$B$3)} -> 81797.95 | E9: {=SUMIFS(data_amt,data_item,$A9,data_cat,E$1,data_dir,Параметры!$B$3)} -> 222390.05 | F9: {=SUMIFS(data_amt,data_item,$A9,data_cat,F$1,data_dir,Параметры!$B$3)} -> 0 | G9: {=SUMIFS(data_amt,data_item,$A9,data_cat,G$1,data_dir,Параметры!$B$3)} -> 0 | H9: {=SUMIFS(data_amt,data_item,$A9,data_cat,H$1,data_dir,Параметры!$B$3)} -> 0 | I9: {=SUMIFS(data_amt,data_item,$A9,data_cat,I$1,data_dir,Параметры!$B$3)} -> 0 | ... U9: {=SUMIFS(data_amt,data_item,$A9,data_cat,U$1,data_dir,Параметры!$B$3)} -> 0 | V9: {=SUM(B9:U9)} -> 171875.68
A10: {=Статьи!A9} -> Доход 1 | B10: {=SUMIFS(data_amt,data_item,$A10,data_cat,B$1,data_dir,Параметры!$B$3)} -> 0 | C10: {=SUMIFS(data_amt,data_item,$A10,data_cat,C$1,data_dir,Параметры!$B$3)} -> 0 | D10: {=SUMIFS(data_amt,data_item,$A10,data_cat,D$1,data_dir,Параметры!$B$3)} -> 280790.62 | E10: {=SUMIFS(data_amt,data_item,$A10,data_cat,E$1,data_dir,Параметры!$B$3)} -> 13305.2 | F10: {=SUMIFS(data_amt,data_item,$A10,data_cat,F$1,data_dir,Параметры!$B$3)} -> 0 | G10: {=SUMIFS(data_amt,data_item,$A10,data_cat,G$1,data_dir,Параметры!$B$3)} -> 0 | H10: {=SUMIFS(data_amt,data_item,$A10,data_cat,H$1,data_dir,Параметры!$B$3)} -> 274207.5 | I10: {=SUMIFS(data_amt,data_item,$A10,data_cat,I$1,data_dir,Параметры!$B$3)} -> 0 | ... U10: {=SUMIFS(data_amt,data_item,$A10,data_cat,U$1,data_dir,Параметры!$B$3)} -> 0 | V10: {=SUM(B10:U10)} -> 970400.64
A11: {=Статьи!A10} -> Сырьё 1 | B11: {=SUMIFS(data_amt,data_item,$A11,data_cat,B$1,data_dir,Параметры!$B$3)} -> 0 | C11: {=SUMIFS(data_amt,data_item,$A11,data_cat,C$1,data_dir,Параметры!$B$3)} -> 0 | D11: {=SUMIFS(data_amt,data_item,$A11,data_cat,D$1,data_dir,Параметры!$B$3)} -> -19432.35 | E11: {=SUMIFS(data_amt,data_item,$A11,data_cat,E$1,data_dir,Параметры!$B$3)} -> 0 | F11: {=SUMIFS(data_amt,data_item,$A11,data_cat,F$1,data_dir,Параметры!$B$3)} -> 0 | G11: {=SUMIFS(data_amt,data_item,$A11,data_cat,G$1,data_dir,Параметры!$B$3)} -> 0 | H11: {=SUMIFS(data_amt,data_item,$A11,data_cat,H$1,data_dir,Параметры!$B$3)} -> 0 | I11: {=SUMIFS(data_amt,data_item,$A11,data_cat,I$1,data_dir,Параметры!$B$3)} -> 0 | ... U11: {=SUMIFS(data_amt,data_item,$A11,data_cat,U$1,data_dir,Параметры!$B$3)} -> -23136.59 | V11: {=SUM(B11:U11)} -> 116389.61
A12: {=Статьи!A11} -> Сырье 1 | B12: {=SUMIFS(data_amt,data_item,$A12,data_cat,B$1,data_dir,Параметры!$B$3)} -> 0 | C12: {=SUMIFS(data_amt,data_item,$A12,data_cat,C$1,data_dir,Параметры!$B$3)} -> 0 | D12: {=SUMIFS(data_amt,data_item,$A12,data_cat,D$1,data_dir,Параметры!$B$3)} -> 266230.23 | E12: {=SUMIFS(data_amt,data_item,$A12,data_cat,E$1,data_dir,Параметры!$B$3)} -> 0 | F12: {=SUMIFS(data_amt,data_item,$A12,data_cat,F$1,data_dir,Параметры!$B$3)} -> 0 | G12: {=SUMIFS(data_amt,data_item,$A12,data_cat,G$1,data_dir,Параметры!$B$3)} -> 0 | H12: {=SUMIFS(data_amt,data_item,$A12,data_cat,H$1,data_dir,Параметры!$B$3)} -> 0 | I12: {=SUMIFS(data_amt,data_item,$A12,data_cat,I$1,data_dir,Параметры!$B$3)} -> 0 | ... U12: {=SUMIFS(data_amt,data_item,$A12,data_cat,U$1,data_dir,Параметры!$B$3)} -> 0 | V12: {=SUM(B12:U12)} -> 266230.23
A13: Итого группа 2 | B13: {=SUM(B8:B12)} -> 0 | C13: {=SUM(C8:C12)} -> 103573.35 | D13: {=SUM(D8:D12)} -> 609386.45 | E13: {=SUM(E8:E12)} -> 235695.25 | F13: {=SUM(F8:F12)} -> 0 | G13: {=SUM(G8:G12)} -> 0 | H13: {=SUM(H8:H12)} -> 274207.5 | I13: {=SUM(I8:I12)} -> 0 | ... V13: {=SUM(V8:V12)} -> 2219052.8
A14: {=Статьи!A12} -> Чай 2 | B14: {=SUMIFS(data_amt,data_item,$A14,data_cat,B$1,data_dir,Параметры!$B$3)} -> 0 | C14: {=SUMIFS(data_amt,data_item,$A14,data_cat,C$1,data_dir,Параметры!$B$3)} -> 0 | D14: {=SUMIFS(data_amt,data_item,$A14,data_cat,D$1,data_dir,Параметры!$B$3)} -> 0 | E14: {=SUMIFS(data_amt,data_item,$A14,data_cat,E$1,data_dir,Параметры!$B$3)} -> 0 | F14: {=SUMIFS(data_amt,data_item,$A14,data_cat,F$1,data_dir,Параметры!$B$3)} -> 100501.07 | G14: {=SUMIFS(data_amt,data_item,$A14,data_cat,G$1,data_dir,Параметры!$B$3)} -> 0 | H14: {=SUMIFS(data_amt,data_item,$A14,data_cat,H$1,data_dir,Параметры!$B$3)} -> 0 | I14: {=SUMIFS(data_amt,data_item,$A14,data_cat,I$1,data_dir,Параметры!$B$3)} -> 0 | ... U14: {=SUMIFS(data_amt,data_item,$A14,data_cat,U$1,data_dir,Параметры!$B$3)} -> 0 | V14: {=SUM(B14:U14)} -> 513883.18
A15: {=Статьи!A13} -> Чаи 2 | B15: {=SUMIFS(data_amt,data_item,$A15,data_cat,B$1,data_dir,Параметры!$B$3)} -> 0 | C15: {=SUMIFS(data_amt,data_item,$A15,data_cat,C$1,data_dir,Параметры!$B$3)} -> 0 | D15: {=SUMIFS(data_amt,data_item,$A15,data_cat,D$1,data_dir,Параметры!$B$3)} -> 0 | E15: {=SUMIFS(data_amt,data_item,$A15,data_cat,E$1,data_dir,Параметры!$B$3)} -> 0 | F15: {=SUMIFS(data_amt,data_item,$A15,data_cat,F$1,data_dir,Параметры!$B$3)} -> 0 | G15: {=SUMIFS(data_amt,data_item,$A15,data_cat,G$1,data_dir,Параметры!$B$3)} -> 0 | H15: {=SUMIFS(data_amt,data_item,$A15,data_cat,H$1,data_dir,Параметры!$B$3)} -> 0 | I15: {=SUMIFS(data_amt,data_item,$A15,data_cat,I$1,data_dir,Параметры!$B$3)} -> 0 | ... U15: {=SUMIFS(data_amt,data_item,$A15,data_cat,U$1,data_dir,Параметры!$B$3)} -> 0 | V15: {=SUM(B15:U15)} -> 0
A16: {=Статьи!A14} -> Ёлка 2 | B16: {=SUMIFS(data_amt,data_item,$A16,data_cat,B$1,data_dir,Параметры!$B$3)} -> 0 | C16: {=SUMIFS(data_amt,data_item,$A16,data_cat,C$1,data_dir,Параметры!$B$3)} -> 0 | D16: {=SUMIFS(data_amt,data_item,$A16,data_cat,D$1,data_dir,Параметры!$B$3)} -> 0 | E16: {=SUMIFS(data_amt,data_item,$A16,data_cat,E$1,data_dir,Параметры!$B$3)} -> 0 | F16: {=SUMIFS(data_amt,data_item,$A16,data_cat,F$1,data_dir,Параметры!$B$3)} -> 0 | G16: {=SUMIFS(data_amt,data_item,$A16,data_cat,G$1,data_dir,Параметры!$B$3)} -> 0 | H16: {=SUMIFS(data_amt,data_item,$A16,data_cat,H$1,data_dir,Параметры!$B$3)} -> 267894.61 | I16: {=SUMIFS(data_amt,data_item,$A16,data_cat,I$1,data_dir,Параметры!$B$3)} -> 0 | ... U16: {=SUMIFS(data_amt,data_item,$A16,data_cat,U$1,data_dir,Параметры!$B$3)} -> 0 | V16: {=SUM(B16:U16)} -> 512852.36
A17: {=Статьи!A15} -> Елка 2 | B17: {=SUMIFS(data_amt,data_item,$A17,data_cat,B$1,data_dir,Параметры!$B$3)} -> 0 | C17: {=SUMIFS(data_amt,data_item,$A17,data_cat,C$1,data_dir,Параметры!$B$3)} -> 0 | D17: {=SUMIFS(data_amt,data_item,$A17,data_cat,D$1,data_dir,Параметры!$B$3)} -> 0 | E17: {=SUMIFS(data_amt,data_item,$A17,data_cat,E$1,data_dir,Параметры!$B$3)} -> 0 | F17: {=SUMIFS(data_amt,data_item,$A17,data_cat,F$1,data_dir,Параметры!$B$3)} -> 103673.2 | G17: {=SUMIFS(data_amt,data_item,$A17,data_cat,G$1,data_dir,Параметры!$B$3)} -> 0 | H17: {=SUMIFS(data_amt,data_item,$A17,data_cat,H$1,data_dir,Параметры!$B$3)} -> 0 | I17: {=SUMIFS(data_amt,data_item,$A17,data_cat,I$1,data_dir,Параметры!$B$3)} -> 0 | ... U17: {=SUMIFS(data_amt,data_item,$A17,data_cat,U$1,data_dir,Параметры!$B$3)} -> 0 | V17: {=SUM(B17:U17)} -> 382494.46
A18: {=Статьи!A16} -> Аренда 2 | B18: {=SUMIFS(data_amt,data_item,$A18,data_cat,B$1,data_dir,Параметры!$B$3)} -> 0 | C18: {=SUMIFS(data_amt,data_item,$A18,data_cat,C$1,data_dir,Параметры!$B$3)} -> 0 | D18: {=SUMIFS(data_amt,data_item,$A18,data_cat,D$1,data_dir,Параметры!$B$3)} -> 318497.36 | E18: {=SUMIFS(data_amt,data_item,$A18,data_cat,E$1,data_dir,Параметры!$B$3)} -> 0 | F18: {=SUMIFS(data_amt,data_item,$A18,data_cat,F$1,data_dir,Параметры!$B$3)} -> 148233.03 | G18: {=SUMIFS(data_amt,data_item,$A18,data_cat,G$1,data_dir,Параметры!$B$3)} -> 0 | H18: {=SUMIFS(data_amt,data_item,$A18,data_cat,H$1,data_dir,Параметры!$B$3)} -> 0 | I18: {=SUMIFS(data_amt,data_item,$A18,data_cat,I$1,data_dir,Параметры!$B$3)} -> 0 | ... U18: {=SUMIFS(data_amt,data_item,$A18,data_cat,U$1,data_dir,Параметры!$B$3)} -> 0 | V18: {=SUM(B18:U18)} -> 820711.46
A19: Итого группа 3 | B19: {=SUM(B14:B18)} -> 0 | C19: {=SUM(C14:C18)} -> 0 | D19: {=SUM(D14:D18)} -> 318497.36 | E19: {=SUM(E14:E18)} -> 0 | F19: {=SUM(F14:F18)} -> 352407.3 | G19: {=SUM(G14:G18)} -> 0 | H19: {=SUM(H14:H18)} -> 267894.61 | I19: {=SUM(I14:I18)} -> 0 | ... V19: {=SUM(V14:V18)} -> 2229941.5
A20: {=Статьи!A17} -> Связь 2 | B20: {=SUMIFS(data_amt,data_item,$A20,data_cat,B$1,data_dir,Параметры!$B$3)} -> 0 | C20: {=SUMIFS(data_amt,data_item,$A20,data_cat,C$1,data_dir,Параметры!$B$3)} -> -50072.52 | D20: {=SUMIFS(data_amt,data_item,$A20,data_cat,D$1,data_dir,Параметры!$B$3)} -> 0 | E20: {=SUMIFS(data_amt,data_item,$A20,data_cat,E$1,data_dir,Параметры!$B$3)} -> 0 | F20: {=SUMIFS(data_amt,data_item,$A20,data_cat,F$1,data_dir,Параметры!$B$3)} -> 0 | G20: {=SUMIFS(data_amt,data_item,$A20,data_cat,G$1,data_dir,Параметры!$B$3)} -> 0 | H20: {=SUMIFS(data_amt,data_item,$A20,data_cat,H$1,data_dir,Параметры!$B$3)} -> 0 | I20: {=SUMIFS(data_amt,data_item,$A20,data_cat,I$1,data_dir,Параметры!$B$3)} -> 0 | ... U20: {=SUMIFS(data_amt,data_item,$A20,data_cat,U$1,data_dir,Параметры!$B$3)} -> 0 | V20: {=SUM(B20:U20)} -> 621535.72
A21: {=Статьи!A18} -> Налог 2 | B21: {=SUMIFS(data_amt,data_item,$A21,data_cat,B$1,data_dir,Параметры!$B$3)} -> 0 | C21: {=SUMIFS(data_amt,data_item,$A21,data_cat,C$1,data_dir,Параметры!$B$3)} -> 0 | D21: {=SUMIFS(data_amt,data_item,$A21,data_cat,D$1,data_dir,Параметры!$B$3)} -> 0 | E21: {=SUMIFS(data_amt,data_item,$A21,data_cat,E$1,data_dir,Параметры!$B$3)} -> 0 | F21: {=SUMIFS(data_amt,data_item,$A21,data_cat,F$1,data_dir,Параметры!$B$3)} -> 0 | G21: {=SUMIFS(data_amt,data_item,$A21,data_cat,G$1,data_dir,Параметры!$B$3)} -> 67383.54 | H21: {=SUMIFS(data_amt,data_item,$A21,data_cat,H$1,data_dir,Параметры!$B$3)} -> 0 | I21: {=SUMIFS(data_amt,data_item,$A21,data_cat,I$1,data_dir,Параметры!$B$3)} -> 0 | ... U21: {=SUMIFS(data_amt,data_item,$A21,data_cat,U$1,data_dir,Параметры!$B$3)} -> 0 | V21: {=SUM(B21:U21)} -> 111966.42
A22: {=Статьи!A19} -> Доход 2 | B22: {=SUMIFS(data_amt,data_item,$A22,data_cat,B$1,data_dir,Параметры!$B$3)} -> 0 | C22: {=SUMIFS(data_amt,data_item,$A22,data_cat,C$1,data_dir,Параметры!$B$3)} -> 0 | D22: {=SUMIFS(data_amt,data_item,$A22,data_cat,D$1,data_dir,Параметры!$B$3)} -> 0 | E22: {=SUMIFS(data_amt,data_item,$A22,data_cat,E$1,data_dir,Параметры!$B$3)} -> 0 | F22: {=SUMIFS(data_amt,data_item,$A22,data_cat,F$1,data_dir,Параметры!$B$3)} -> 236132.35 | G22: {=SUMIFS(data_amt,data_item,$A22,data_cat,G$1,data_dir,Параметры!$B$3)} -> 0 | H22: {=SUMIFS(data_amt,data_item,$A22,data_cat,H$1,data_dir,Параметры!$B$3)} -> 0 | I22: {=SUMIFS(data_amt,data_item,$A22,data_cat,I$1,data_dir,Параметры!$B$3)} -> 0 | ... U22: {=SUMIFS(data_amt,data_item,$A22,data_cat,U$1,data_dir,Параметры!$B$3)} -> 0 | V22: {=SUM(B22:U22)} -> 176711.74
A23: {=Статьи!A20} -> Сырьё 2 | B23: {=SUMIFS(data_amt,data_item,$A23,data_cat,B$1,data_dir,Параметры!$B$3)} -> 0 | C23: {=SUMIFS(data_amt,data_item,$A23,data_cat,C$1,data_dir,Параметры!$B$3)} -> 0 | D23: {=SUMIFS(data_amt,data_item,$A23,data_cat,D$1,data_dir,Параметры!$B$3)} -> 0 | E23: {=SUMIFS(data_amt,data_item,$A23,data_cat,E$1,data_dir,Параметры!$B$3)} -> 0 | F23: {=SUMIFS(data_amt,data_item,$A23,data_cat,F$1,data_dir,Параметры!$B$3)} -> 0 | G23: {=SUMIFS(data_amt,data_item,$A23,data_cat,G$1,data_dir,Параметры!$B$3)} -> 0 | H23: {=SUMIFS(data_amt,data_item,$A23,data_cat,H$1,data_dir,Параметры!$B$3)} -> 0 | I23: {=SUMIFS(data_amt,data_item,$A23,data_cat,I$1,data_dir,Параметры!$B$3)} -> 332928.47 | ... U23: {=SUMIFS(data_amt,data_item,$A23,data_cat,U$1,data_dir,Параметры!$B$3)} -> 29317.87 | V23: {=SUM(B23:U23)} -> 3.8101517e+08
A24: {=Статьи!A21} -> Сырье 2 | B24: {=SUMIFS(data_amt,data_item,$A24,data_cat,B$1,data_dir,Параметры!$B$3)} -> 0 | C24: {=SUMIFS(data_amt,data_item,$A24,data_cat,C$1,data_dir,Параметры!$B$3)} -> 0 | D24: {=SUMIFS(data_amt,data_item,$A24,data_cat,D$1,data_dir,Параметры!$B$3)} -> -42207.32 | E24: {=SUMIFS(data_amt,data_item,$A24,data_cat,E$1,data_dir,Параметры!$B$3)} -> 0 | F24: {=SUMIFS(data_amt,data_item,$A24,data_cat,F$1,data_dir,Параметры!$B$3)} -> 0 | G24: {=SUMIFS(data_amt,data_item,$A24,data_cat,G$1,data_dir,Параметры!$B$3)} -> 0 | H24: {=SUMIFS(data_amt,data_item,$A24,data_cat,H$1,data_dir,Параметры!$B$3)} -> -57859.49 | I24: {=SUMIFS(data_amt,data_item,$A24,data_cat,I$1,data_dir,Параметры!$B$3)} -> 0 | ... U24: {=SUMIFS(data_amt,data_item,$A24,data_cat,U$1,data_dir,Параметры!$B$3)} -> 150781.73 | V24: {=SUM(B24:U24)} -> 142799.74
A25: Итого группа 4 | B25: {=SUM(B20:B24)} -> 0 | C25: {=SUM(C20:C24)} -> -50072.52 | D25: {=SUM(D20:D24)} -> -42207.32 | E25: {=SUM(E20:E24)} -> 0 | F25: {=SUM(F20:F24)} -> 236132.35 | G25: {=SUM(G20:G24)} -> 67383.54 | H25: {=SUM(H20:H24)} -> -57859.49 | I25: {=SUM(I20:I24)} -> 332928.47 | ... V25: {=SUM(V20:V24)} -> 3.8206819e+08
A26: {=Статьи!A22} -> Чай 3 | B26: {=SUMIFS(data_amt,data_item,$A26,data_cat,B$1,data_dir,Параметры!$B$3)} -> -39388.8 | C26: {=SUMIFS(data_amt,data_item,$A26,data_cat,C$1,data_dir,Параметры!$B$3)} -> 0 | D26: {=SUMIFS(data_amt,data_item,$A26,data_cat,D$1,data_dir,Параметры!$B$3)} -> 0 | E26: {=SUMIFS(data_amt,data_item,$A26,data_cat,E$1,data_dir,Параметры!$B$3)} -> -5034.23 | F26: {=SUMIFS(data_amt,data_item,$A26,data_cat,F$1,data_dir,Параметры!$B$3)} -> 0 | G26: {=SUMIFS(data_amt,data_item,$A26,data_cat,G$1,data_dir,Параметры!$B$3)} -> 0 | H26: {=SUMIFS(data_amt,data_item,$A26,data_cat,H$1,data_dir,Параметры!$B$3)} -> 0 | I26: {=SUMIFS(data_amt,data_item,$A26,data_cat,I$1,data_dir,Параметры!$B$3)} -> 0 | ... U26: {=SUMIFS(data_amt,data_item,$A26,data_cat,U$1,data_dir,Параметры!$B$3)} -> 0 | V26: {=SUM(B26:U26)} -> 479445.66
A27: {=Статьи!A23} -> Чаи 3 | B27: {=SUMIFS(data_amt,data_item,$A27,data_cat,B$1,data_dir,Параметры!$B$3)} -> 0 | C27: {=SUMIFS(data_amt,data_item,$A27,data_cat,C$1,data_dir,Параметры!$B$3)} -> 0 | D27: {=SUMIFS(data_amt,data_item,$A27,data_cat,D$1,data_dir,Параметры!$B$3)} -> 255552.73 | E27: {=SUMIFS(data_amt,data_item,$A27,data_cat,E$1,data_dir,Параметры!$B$3)} -> 0 | F27: {=SUMIFS(data_amt,data_item,$A27,data_cat,F$1,data_dir,Параметры!$B$3)} -> 0 | G27: {=SUMIFS(data_amt,data_item,$A27,data_cat,G$1,data_dir,Параметры!$B$3)} -> 0 | H27: {=SUMIFS(data_amt,data_item,$A27,data_cat,H$1,data_dir,Параметры!$B$3)} -> 0 | I27: {=SUMIFS(data_amt,data_item,$A27,data_cat,I$1,data_dir,Параметры!$B$3)} -> 0 | ... U27: {=SUMIFS(data_amt,data_item,$A27,data_cat,U$1,data_dir,Параметры!$B$3)} -> 0 | V27: {=SUM(B27:U27)} -> 472137.74
A28: {=Статьи!A24} -> Ёлка 3 | B28: {=SUMIFS(data_amt,data_item,$A28,data_cat,B$1,data_dir,Параметры!$B$3)} -> 0 | C28: {=SUMIFS(data_amt,data_item,$A28,data_cat,C$1,data_dir,Параметры!$B$3)} -> 0 | D28: {=SUMIFS(data_amt,data_item,$A28,data_cat,D$1,data_dir,Параметры!$B$3)} -> 0 | E28: {=SUMIFS(data_amt,data_item,$A28,data_cat,E$1,data_dir,Параметры!$B$3)} -> -76555.96 | F28: {=SUMIFS(data_amt,data_item,$A28,data_cat,F$1,data_dir,Параметры!$B$3)} -> 0 | G28: {=SUMIFS(data_amt,data_item,$A28,data_cat,G$1,data_dir,Параметры!$B$3)} -> 0 | H28: {=SUMIFS(data_amt,data_item,$A28,data_cat,H$1,data_dir,Параметры!$B$3)} -> 0 | I28: {=SUMIFS(data_amt,data_item,$A28,data_cat,I$1,data_dir,Параметры!$B$3)} -> 314911.66 | ... U28: {=SUMIFS(data_amt,data_item,$A28,data_cat,U$1,data_dir,Параметры!$B$3)} -> 0 | V28: {=SUM(B28:U28)} -> 423128.18
A29: {=Статьи!A25} -> Елка 3 | B29: {=SUMIFS(data_amt,data_item,$A29,data_cat,B$1,data_dir,Параметры!$B$3)} -> 1.2817459e+09 | C29: {=SUMIFS(data_amt,data_item,$A29,data_cat,C$1,data_dir,Параметры!$B$3)} -> 0 | D29: {=SUMIFS(data_amt,data_item,$A29,data_cat,D$1,data_dir,Параметры!$B$3)} -> 0 | E29: {=SUMIFS(data_amt,data_item,$A29,data_cat,E$1,data_dir,Параметры!$B$3)} -> 38193.87 | F29: {=SUMIFS(data_amt,data_item,$A29,data_cat,F$1,data_dir,Параметры!$B$3)} -> 0 | G29: {=SUMIFS(data_amt,data_item,$A29,data_cat,G$1,data_dir,Параметры!$B$3)} -> 0 | H29: {=SUMIFS(data_amt,data_item,$A29,data_cat,H$1,data_dir,Параметры!$B$3)} -> 0 | I29: {=SUMIFS(data_amt,data_item,$A29,data_cat,I$1,data_dir,Параметры!$B$3)} -> 96889.02 | ... U29: {=SUMIFS(data_amt,data_item,$A29,data_cat,U$1,data_dir,Параметры!$B$3)} -> 0 | V29: {=SUM(B29:U29)} -> 1.2819248e+09
A30: {=Статьи!A26} -> Аренда 3 | B30: {=SUMIFS(data_amt,data_item,$A30,data_cat,B$1,data_dir,Параметры!$B$3)} -> -2930.33 | C30: {=SUMIFS(data_amt,data_item,$A30,data_cat,C$1,data_dir,Параметры!$B$3)} -> 376896.25 | D30: {=SUMIFS(data_amt,data_item,$A30,data_cat,D$1,data_dir,Параметры!$B$3)} -> 0 | E30: {=SUMIFS(data_amt,data_item,$A30,data_cat,E$1,data_dir,Параметры!$B$3)} -> 311123.45 | F30: {=SUMIFS(data_amt,data_item,$A30,data_cat,F$1,data_dir,Параметры!$B$3)} -> 0 | G30: {=SUMIFS(data_amt,data_item,$A30,data_cat,G$1,data_dir,Параметры!$B$3)} -> 0 | H30: {=SUMIFS(data_amt,data_item,$A30,data_cat,H$1,data_dir,Параметры!$B$3)} -> 0 | I30: {=SUMIFS(data_amt,data_item,$A30,data_cat,I$1,data_dir,Параметры!$B$3)} -> 0 | ... U30: {=SUMIFS(data_amt,data_item,$A30,data_cat,U$1,data_dir,Параметры!$B$3)} -> 0 | V30: {=SUM(B30:U30)} -> 685089.37
A31: Итого группа 5 | B31: {=SUM(B26:B30)} -> 1.2817036e+09 | C31: {=SUM(C26:C30)} -> 376896.25 | D31: {=SUM(D26:D30)} -> 255552.73 | E31: {=SUM(E26:E30)} -> 267727.13 | F31: {=SUM(F26:F30)} -> 0 | G31: {=SUM(G26:G30)} -> 0 | H31: {=SUM(H26:H30)} -> 0 | I31: {=SUM(I26:I30)} -> 411800.68 | ... V31: {=SUM(V26:V30)} -> 1.2839846e+09
A32: {=Статьи!A27} -> Связь 3 | B32: {=SUMIFS(data_amt,data_item,$A32,data_cat,B$1,data_dir,Параметры!$B$3)} -> 0 | C32: {=SUMIFS(data_amt,data_item,$A32,data_cat,C$1,data_dir,Параметры!$B$3)} -> 0 | D32: {=SUMIFS(data_amt,data_item,$A32,data_cat,D$1,data_dir,Параметры!$B$3)} -> 0 | E32: {=SUMIFS(data_amt,data_item,$A32,data_cat,E$1,data_dir,Параметры!$B$3)} -> 0 | F32: {=SUMIFS(data_amt,data_item,$A32,data_cat,F$1,data_dir,Параметры!$B$3)} -> 0 | G32: {=SUMIFS(data_amt,data_item,$A32,data_cat,G$1,data_dir,Параметры!$B$3)} -> 0 | H32: {=SUMIFS(data_amt,data_item,$A32,data_cat,H$1,data_dir,Параметры!$B$3)} -> 0 | I32: {=SUMIFS(data_amt,data_item,$A32,data_cat,I$1,data_dir,Параметры!$B$3)} -> 0 | ... U32: {=SUMIFS(data_amt,data_item,$A32,data_cat,U$1,data_dir,Параметры!$B$3)} -> 0 | V32: {=SUM(B32:U32)} -> 815355.81
A33: {=Статьи!A28} -> Налог 3 | B33: {=SUMIFS(data_amt,data_item,$A33,data_cat,B$1,data_dir,Параметры!$B$3)} -> 0 | C33: {=SUMIFS(data_amt,data_item,$A33,data_cat,C$1,data_dir,Параметры!$B$3)} -> 0 | D33: {=SUMIFS(data_amt,data_item,$A33,data_cat,D$1,data_dir,Параметры!$B$3)} -> 0 | E33: {=SUMIFS(data_amt,data_item,$A33,data_cat,E$1,data_dir,Параметры!$B$3)} -> 295033.37 | F33: {=SUMIFS(data_amt,data_item,$A33,data_cat,F$1,data_dir,Параметры!$B$3)} -> 0 | G33: {=SUMIFS(data_amt,data_item,$A33,data_cat,G$1,data_dir,Параметры!$B$3)} -> 0 | H33: {=SUMIFS(data_amt,data_item,$A33,data_cat,H$1,data_dir,Параметры!$B$3)} -> 0 | I33: {=SUMIFS(data_amt,data_item,$A33,data_cat,I$1,data_dir,Параметры!$B$3)} -> -84644.3 | ... U33: {=SUMIFS(data_amt,data_item,$A33,data_cat,U$1,data_dir,Параметры!$B$3)} -> 325797.92 | V33: {=SUM(B33:U33)} -> 536186.99
A34: {=Статьи!A29} -> Доход 3 | B34: {=SUMIFS(data_amt,data_item,$A34,data_cat,B$1,data_dir,Параметры!$B$3)} -> 0 | C34: {=SUMIFS(data_amt,data_item,$A34,data_cat,C$1,data_dir,Параметры!$B$3)} -> 0 | D34: {=SUMIFS(data_amt,data_item,$A34,data_cat,D$1,data_dir,Параметры!$B$3)} -> 0 | E34: {=SUMIFS(data_amt,data_item,$A34,data_cat,E$1,data_dir,Параметры!$B$3)} -> 522303.31 | F34: {=SUMIFS(data_amt,data_item,$A34,data_cat,F$1,data_dir,Параметры!$B$3)} -> 0 | G34: {=SUMIFS(data_amt,data_item,$A34,data_cat,G$1,data_dir,Параметры!$B$3)} -> 0 | H34: {=SUMIFS(data_amt,data_item,$A34,data_cat,H$1,data_dir,Параметры!$B$3)} -> 0 | I34: {=SUMIFS(data_amt,data_item,$A34,data_cat,I$1,data_dir,Параметры!$B$3)} -> 0 | ... U34: {=SUMIFS(data_amt,data_item,$A34,data_cat,U$1,data_dir,Параметры!$B$3)} -> 0 | V34: {=SUM(B34:U34)} -> 1066039.9
A35: {=Статьи!A30} -> Сырьё 3 | B35: {=SUMIFS(data_amt,data_item,$A35,data_cat,B$1,data_dir,Параметры!$B$3)} -> 0 | C35: {=SUMIFS(data_amt,data_item,$A35,data_cat,C$1,data_dir,Параметры!$B$3)} -> 0 | D35: {=SUMIFS(data_amt,data_item,$A35,data_cat,D$1,data_dir,Параметры!$B$3)} -> 0 | E35: {=SUMIFS(data_amt,data_item,$A35,data_cat,E$1,data_dir,Параметры!$B$3)} -> 0 | F35: {=SUMIFS(data_amt,data_item,$A35,data_cat,F$1,data_dir,Параметры!$B$3)} -> 0 | G35: {=SUMIFS(data_amt,data_item,$A35,data_cat,G$1,data_dir,Параметры!$B$3)} -> 0 | H35: {=SUMIFS(data_amt,data_item,$A35,data_cat,H$1,data_dir,Параметры!$B$3)} -> 255766.36 | I35: {=SUMIFS(data_amt,data_item,$A35,data_cat,I$1,data_dir,Параметры!$B$3)} -> 0 | ... U35: {=SUMIFS(data_amt,data_item,$A35,data_cat,U$1,data_dir,Параметры!$B$3)} -> 0 | V35: {=SUM(B35:U35)} -> 652074.19
A36: {=Статьи!A31} -> Сырье 3 | B36: {=SUMIFS(data_amt,data_item,$A36,data_cat,B$1,data_dir,Параметры!$B$3)} -> 0 | C36: {=SUMIFS(data_amt,data_item,$A36,data_cat,C$1,data_dir,Параметры!$B$3)} -> 0 | D36: {=SUMIFS(data_amt,data_item,$A36,data_cat,D$1,data_dir,Параметры!$B$3)} -> 0 | E36: {=SUMIFS(data_amt,data_item,$A36,data_cat,E$1,data_dir,Параметры!$B$3)} -> 0 | F36: {=SUMIFS(data_amt,data_item,$A36,data_cat,F$1,data_dir,Параметры!$B$3)} -> 180154.93 | G36: {=SUMIFS(data_amt,data_item,$A36,data_cat,G$1,data_dir,Параметры!$B$3)} -> 0 | H36: {=SUMIFS(data_amt,data_item,$A36,data_cat,H$1,data_dir,Параметры!$B$3)} -> 0 | I36: {=SUMIFS(data_amt,data_item,$A36,data_cat,I$1,data_dir,Параметры!$B$3)} -> 0 | ... U36: {=SUMIFS(data_amt,data_item,$A36,data_cat,U$1,data_dir,Параметры!$B$3)} -> 0 | V36: {=SUM(B36:U36)} -> 347281.43
A37: Итого группа 6 | B37: {=SUM(B32:B36)} -> 0 | C37: {=SUM(C32:C36)} -> 0 | D37: {=SUM(D32:D36)} -> 0 | E37: {=SUM(E32:E36)} -> 817336.68 | F37: {=SUM(F32:F36)} -> 180154.93 | G37: {=SUM(G32:G36)} -> 0 | H37: {=SUM(H32:H36)} -> 255766.36 | I37: {=SUM(I32:I36)} -> -84644.3 | ... V37: {=SUM(V32:V36)} -> 3416938.3
A38: {=Статьи!A32} -> Чай 4 | B38: {=SUMIFS(data_amt,data_item,$A38,data_cat,B$1,data_dir,Параметры!$B$3)} -> 0 | C38: {=SUMIFS(data_amt,data_item,$A38,data_cat,C$1,data_dir,Параметры!$B$3)} -> 0 | D38: {=SUMIFS(data_amt,data_item,$A38,data_cat,D$1,data_dir,Параметры!$B$3)} -> 0 | E38: {=SUMIFS(data_amt,data_item,$A38,data_cat,E$1,data_dir,Параметры!$B$3)} -> 0 | F38: {=SUMIFS(data_amt,data_item,$A38,data_cat,F$1,data_dir,Параметры!$B$3)} -> 0 | G38: {=SUMIFS(data_amt,data_item,$A38,data_cat,G$1,data_dir,Параметры!$B$3)} -> -44181.64 | H38: {=SUMIFS(data_amt,data_item,$A38,data_cat,H$1,data_dir,Параметры!$B$3)} -> 0 | I38: {=SUMIFS(data_amt,data_item,$A38,data_cat,I$1,data_dir,Параметры!$B$3)} -> 0 | ... U38: {=SUMIFS(data_amt,data_item,$A38,data_cat,U$1,data_dir,Параметры!$B$3)} -> 0 | V38: {=SUM(B38:U38)} -> -84126.87
A39: {=Статьи!A33} -> Чаи 4 | B39: {=SUMIFS(data_amt,data_item,$A39,data_cat,B$1,data_dir,Параметры!$B$3)} -> 0 | C39: {=SUMIFS(data_amt,data_item,$A39,data_cat,C$1,data_dir,Параметры!$B$3)} -> 0 | D39: {=SUMIFS(data_amt,data_item,$A39,data_cat,D$1,data_dir,Параметры!$B$3)} -> 0 | E39: {=SUMIFS(data_amt,data_item,$A39,data_cat,E$1,data_dir,Параметры!$B$3)} -> 12049.53 | F39: {=SUMIFS(data_amt,data_item,$A39,data_cat,F$1,data_dir,Параметры!$B$3)} -> 0 | G39: {=SUMIFS(data_amt,data_item,$A39,data_cat,G$1,data_dir,Параметры!$B$3)} -> 89894.04 | H39: {=SUMIFS(data_amt,data_item,$A39,data_cat,H$1,data_dir,Параметры!$B$3)} -> 0 | I39: {=SUMIFS(data_amt,data_item,$A39,data_cat,I$1,data_dir,Параметры!$B$3)} -> 0 | ... U39: {=SUMIFS(data_amt,data_item,$A39,data_cat,U$1,data_dir,Параметры!$B$3)} -> 0 | V39: {=SUM(B39:U39)} -> 143823.69
A40: {=Статьи!A34} -> Ёлка 4 | B40: {=SUMIFS(data_amt,data_item,$A40,data_cat,B$1,data_dir,Параметры!$B$3)} -> 0 | C40: {=SUMIFS(data_amt,data_item,$A40,data_cat,C$1,data_dir,Параметры!$B$3)} -> 237308.9 | D40: {=SUMIFS(data_amt,data_item,$A40,data_cat,D$1,data_dir,Параметры!$B$3)} -> 0 | E40: {=SUMIFS(data_amt,data_item,$A40,data_cat,E$1,data_dir,Параметры!$B$3)} -> 0 | F40: {=SUMIFS(data_amt,data_item,$A40,data_cat,F$1,data_dir,Параметры!$B$3)} -> 0 | G40: {=SUMIFS(data_amt,data_item,$A40,data_cat,G$1,data_dir,Параметры!$B$3)} -> 0 | H40: {=SUMIFS(data_amt,data_item,$A40,data_cat,H$1,data_dir,Параметры!$B$3)} -> -26964.42 | I40: {=SUMIFS(data_amt,data_item,$A40,data_cat,I$1,data_dir,Параметры!$B$3)} -> 0 | ... U40: {=SUMIFS(data_amt,data_item,$A40,data_cat,U$1,data_dir,Параметры!$B$3)} -> 0 | V40: {=SUM(B40:U40)} -> 210344.48
A41: {=Статьи!A35} -> Елка 4 | B41: {=SUMIFS(data_amt,data_item,$A41,data_cat,B$1,data_dir,Параметры!$B$3)} -> 0 | C41: {=SUMIFS(data_amt,data_item,$A41,data_cat,C$1,data_dir,Параметры!$B$3)} -> 0 | D41: {=SUMIFS(data_amt,data_item,$A41,data_cat,D$1,data_dir,Параметры!$B$3)} -> 0 | E41: {=SUMIFS(data_amt,data_item,$A41,data_cat,E$1,data_dir,Параметры!$B$3)} -> 0 | F41: {=SUMIFS(data_amt,data_item,$A41,data_cat,F$1,data_dir,Параметры!$B$3)} -> 0 | G41: {=SUMIFS(data_amt,data_item,$A41,data_cat,G$1,data_dir,Параметры!$B$3)} -> 295997.21 | H41: {=SUMIFS(data_amt,data_item,$A41,data_cat,H$1,data_dir,Параметры!$B$3)} -> 0 | I41: {=SUMIFS(data_amt,data_item,$A41,data_cat,I$1,data_dir,Параметры!$B$3)} -> 0 | ... U41: {=SUMIFS(data_amt,data_item,$A41,data_cat,U$1,data_dir,Параметры!$B$3)} -> 0 | V41: {=SUM(B41:U41)} -> 242319.47
A42: {=Статьи!A36} -> Аренда 4 | B42: {=SUMIFS(data_amt,data_item,$A42,data_cat,B$1,data_dir,Параметры!$B$3)} -> 0 | C42: {=SUMIFS(data_amt,data_item,$A42,data_cat,C$1,data_dir,Параметры!$B$3)} -> 0 | D42: {=SUMIFS(data_amt,data_item,$A42,data_cat,D$1,data_dir,Параметры!$B$3)} -> 0 | E42: {=SUMIFS(data_amt,data_item,$A42,data_cat,E$1,data_dir,Параметры!$B$3)} -> 0 | F42: {=SUMIFS(data_amt,data_item,$A42,data_cat,F$1,data_dir,Параметры!$B$3)} -> 0 | G42: {=SUMIFS(data_amt,data_item,$A42,data_cat,G$1,data_dir,Параметры!$B$3)} -> 0 | H42: {=SUMIFS(data_amt,data_item,$A42,data_cat,H$1,data_dir,Параметры!$B$3)} -> 0 | I42: {=SUMIFS(data_amt,data_item,$A42,data_cat,I$1,data_dir,Параметры!$B$3)} -> 0 | ... U42: {=SUMIFS(data_amt,data_item,$A42,data_cat,U$1,data_dir,Параметры!$B$3)} -> 0 | V42: {=SUM(B42:U42)} -> 776105.51
A43: Итого группа 7 | B43: {=SUM(B38:B42)} -> 0 | C43: {=SUM(C38:C42)} -> 237308.9 | D43: {=SUM(D38:D42)} -> 0 | E43: {=SUM(E38:E42)} -> 12049.53 | F43: {=SUM(F38:F42)} -> 0 | G43: {=SUM(G38:G42)} -> 341709.61 | H43: {=SUM(H38:H42)} -> -26964.42 | I43: {=SUM(I38:I42)} -> 0 | ... V43: {=SUM(V38:V42)} -> 1288466.3
A44: {=Статьи!A37} -> Связь 4 | B44: {=SUMIFS(data_amt,data_item,$A44,data_cat,B$1,data_dir,Параметры!$B$3)} -> 0 | C44: {=SUMIFS(data_amt,data_item,$A44,data_cat,C$1,data_dir,Параметры!$B$3)} -> 0 | D44: {=SUMIFS(data_amt,data_item,$A44,data_cat,D$1,data_dir,Параметры!$B$3)} -> 0 | E44: {=SUMIFS(data_amt,data_item,$A44,data_cat,E$1,data_dir,Параметры!$B$3)} -> 12844.7 | F44: {=SUMIFS(data_amt,data_item,$A44,data_cat,F$1,data_dir,Параметры!$B$3)} -> 0 | G44: {=SUMIFS(data_amt,data_item,$A44,data_cat,G$1,data_dir,Параметры!$B$3)} -> 0 | H44: {=SUMIFS(data_amt,data_item,$A44,data_cat,H$1,data_dir,Параметры!$B$3)} -> 0 | I44: {=SUMIFS(data_amt,data_item,$A44,data_cat,I$1,data_dir,Параметры!$B$3)} -> 0 | ... U44: {=SUMIFS(data_amt,data_item,$A44,data_cat,U$1,data_dir,Параметры!$B$3)} -> 0 | V44: {=SUM(B44:U44)} -> 315230.72
A45: {=Статьи!A38} -> Налог 4 | B45: {=SUMIFS(data_amt,data_item,$A45,data_cat,B$1,data_dir,Параметры!$B$3)} -> 0 | C45: {=SUMIFS(data_amt,data_item,$A45,data_cat,C$1,data_dir,Параметры!$B$3)} -> 0 | D45: {=SUMIFS(data_amt,data_item,$A45,data_cat,D$1,data_dir,Параметры!$B$3)} -> 0 | E45: {=SUMIFS(data_amt,data_item,$A45,data_cat,E$1,data_dir,Параметры!$B$3)} -> 0 | F45: {=SUMIFS(data_amt,data_item,$A45,data_cat,F$1,data_dir,Параметры!$B$3)} -> 167868.39 | G45: {=SUMIFS(data_amt,data_item,$A45,data_cat,G$1,data_dir,Параметры!$B$3)} -> 116477.62 | H45: {=SUMIFS(data_amt,data_item,$A45,data_cat,H$1,data_dir,Параметры!$B$3)} -> 0 | I45: {=SUMIFS(data_amt,data_item,$A45,data_cat,I$1,data_dir,Параметры!$B$3)} -> 0 | ... U45: {=SUMIFS(data_amt,data_item,$A45,data_cat,U$1,data_dir,Параметры!$B$3)} -> 0 | V45: {=SUM(B45:U45)} -> 261023.11
A46: {=Статьи!A39} -> Доход 4 | B46: {=SUMIFS(data_amt,data_item,$A46,data_cat,B$1,data_dir,Параметры!$B$3)} -> 0 | C46: {=SUMIFS(data_amt,data_item,$A46,data_cat,C$1,data_dir,Параметры!$B$3)} -> 0 | D46: {=SUMIFS(data_amt,data_item,$A46,data_cat,D$1,data_dir,Параметры!$B$3)} -> 317210.93 | E46: {=SUMIFS(data_amt,data_item,$A46,data_cat,E$1,data_dir,Параметры!$B$3)} -> 0 | F46: {=SUMIFS(data_amt,data_item,$A46,data_cat,F$1,data_dir,Параметры!$B$3)} -> 0 | G46: {=SUMIFS(data_amt,data_item,$A46,data_cat,G$1,data_dir,Параметры!$B$3)} -> 0 | H46: {=SUMIFS(data_amt,data_item,$A46,data_cat,H$1,data_dir,Параметры!$B$3)} -> 129951.6 | I46: {=SUMIFS(data_amt,data_item,$A46,data_cat,I$1,data_dir,Параметры!$B$3)} -> 0 | ... U46: {=SUMIFS(data_amt,data_item,$A46,data_cat,U$1,data_dir,Параметры!$B$3)} -> 0 | V46: {=SUM(B46:U46)} -> 454274.82
A47: {=Статьи!A40} -> Сырьё 4 | B47: {=SUMIFS(data_amt,data_item,$A47,data_cat,B$1,data_dir,Параметры!$B$3)} -> 0 | C47: {=SUMIFS(data_amt,data_item,$A47,data_cat,C$1,data_dir,Параметры!$B$3)} -> 0 | D47: {=SUMIFS(data_amt,data_item,$A47,data_cat,D$1,data_dir,Параметры!$B$3)} -> 0 | E47: {=SUMIFS(data_amt,data_item,$A47,data_cat,E$1,data_dir,Параметры!$B$3)} -> 0 | F47: {=SUMIFS(data_amt,data_item,$A47,data_cat,F$1,data_dir,Параметры!$B$3)} -> 0 | G47: {=SUMIFS(data_amt,data_item,$A47,data_cat,G$1,data_dir,Параметры!$B$3)} -> 132167.11 | H47: {=SUMIFS(data_amt,data_item,$A47,data_cat,H$1,data_dir,Параметры!$B$3)} -> -77915.36 | I47: {=SUMIFS(data_amt,data_item,$A47,data_cat,I$1,data_dir,Параметры!$B$3)} -> 0 | ... U47: {=SUMIFS(data_amt,data_item,$A47,data_cat,U$1,data_dir,Параметры!$B$3)} -> 0 | V47: {=SUM(B47:U47)} -> 708887.37
A48: {=Статьи!A41} -> Сырье 4 | B48: {=SUMIFS(data_amt,data_item,$A48,data_cat,B$1,data_dir,Параметры!$B$3)} -> 0 | C48: {=SUMIFS(data_amt,data_item,$A48,data_cat,C$1,data_dir,Параметры!$B$3)} -> 0 | D48: {=SUMIFS(data_amt,data_item,$A48,data_cat,D$1,data_dir,Параметры!$B$3)} -> 0 | E48: {=SUMIFS(data_amt,data_item,$A48,data_cat,E$1,data_dir,Параметры!$B$3)} -> 0 | F48: {=SUMIFS(data_amt,data_item,$A48,data_cat,F$1,data_dir,Параметры!$B$3)} -> 0 | G48: {=SUMIFS(data_amt,data_item,$A48,data_cat,G$1,data_dir,Параметры!$B$3)} -> 0 | H48: {=SUMIFS(data_amt,data_item,$A48,data_cat,H$1,data_dir,Параметры!$B$3)} -> 0 | I48: {=SUMIFS(data_amt,data_item,$A48,data_cat,I$1,data_dir,Параметры!$B$3)} -> 0 | ... U48: {=SUMIFS(data_amt,data_item,$A48,data_cat,U$1,data_dir,Параметры!$B$3)} -> 0 | V48: {=SUM(B48:U48)} -> 0
A49: Итого группа 8 | B49: {=SUM(B44:B48)} -> 0 | C49: {=SUM(C44:C48)} -> 0 | D49: {=SUM(D44:D48)} -> 317210.93 | E49: {=SUM(E44:E48)} -> 12844.7 | F49: {=SUM(F44:F48)} -> 167868.39 | G49: {=SUM(G44:G48)} -> 248644.73 | H49: {=SUM(H44:H48)} -> 52036.24 | I49: {=SUM(I44:I48)} -> 0 | ... V49: {=SUM(V44:V48)} -> 1739416

Sheet ПоНаправлениям
A1: ПоНаправлениям | B1: {=EOMONTH(Параметры!$B$1,-1)+1} -> 45658 | C1: {=EOMONTH(Параметры!$B$1,-1)+1} -> 45658 | D1: {=EOMONTH(Параметры!$B$1,0)+1} -> 45689 | E1: {=EOMONTH(Параметры!$B$1,0)+1} -> 45689 | F1: {=EOMONTH(Параметры!$B$1,1)+1} -> 45717 | G1: {=EOMONTH(Параметры!$B$1,1)+1} -> 45717 | H1: {=EOMONTH(Параметры!$B$1,2)+1} -> 45748 | I1: {=EOMONTH(Параметры!$B$1,2)+1} -> 45748 | J1: {=EOMONTH(Параметры!$B$1,3)+1} -> 45778 | K1: {=EOMONTH(Параметры!$B$1,3)+1} -> 45778 | L1: {=EOMONTH(Параметры!$B$1,4)+1} -> 45809 | M1: {=EOMONTH(Параметры!$B$1,4)+1} -> 45809 | N1: {=EOMONTH(Параметры!$B$1,5)+1} -> 45839 | O1: {=EOMONTH(Параметры!$B$1,5)+1} -> 45839 | P1: {=EOMONTH(Параметры!$B$1,6)+1} -> 45870 | Q1: {=EOMONTH(Параметры!$B$1,6)+1} -> 45870 | R1: {=EOMONTH(Параметры!$B$1,7)+1} -> 45901 | S1: {=EOMONTH(Параметры!$B$1,7)+1} -> 45901 | T1: {=EOMONTH(Параметры!$B$1,8)+1} -> 45931 | U1: {=EOMONTH(Параметры!$B$1,8)+1} -> 45931 | V1: {=EOMONTH(Параметры!$B$1,9)+1} -> 45962 | W1: {=EOMONTH(Параметры!$B$1,9)+1} -> 45962 | X1: {=EOMONTH(Параметры!$B$1,10)+1} -> 45992 | Y1: {=EOMONTH(Параметры!$B$1,10)+1} -> 45992
B2: {=EOMONTH(Параметры!$B$1,0)} -> 45688 | C2: {=EOMONTH(Параметры!$B$1,0)} -> 45688 | D2: {=EOMONTH(Параметры!$B$1,1)} -> 45716 | E2: {=EOMONTH(Параметры!$B$1,1)} -> 45716 | F2: {=EOMONTH(Параметры!$B$1,2)} -> 45747 | G2: {=EOMONTH(Параметры!$B$1,2)} -> 45747 | H2: {=EOMONTH(Параметры!$B$1,3)} -> 45777 | I2: {=EOMONTH(Параметры!$B$1,3)} -> 45777 | J2: {=EOMONTH(Параметры!$B$1,4)} -> 45808 | K2: {=EOMONTH(Параметры!$B$1,4)} -> 45808 | L2: {=EOMONTH(Параметры!$B$1,5)} -> 45838 | M2: {=EOMONTH(Параметры!$B$1,5)} -> 45838 | N2: {=EOMONTH(Параметры!$B$1,6)} -> 45869 | O2: {=EOMONTH(Параметры!$B$1,6)} -> 45869 | P2: {=EOMONTH(Параметры!$B$1,7)} -> 45900 | Q2: {=EOMONTH(Параметры!$B$1,7)} -> 45900 | R2: {=EOMONTH(Параметры!$B$1,8)} -> 45930 | S2: {=EOMONTH(Параметры!$B$1,8)} -> 45930 | T2: {=EOMONTH(Параметры!$B$1,9)} -> 45961 | U2: {=EOMONTH(Параметры!$B$1,9)} -> 45961 | V2: {=EOMONTH(Параметры!$B$1,10)} -> 45991 | W2: {=EOMONTH(Параметры!$B$1,10)} -> 45991 | X2: {=EOMONTH(Параметры!$B$1,11)} -> 46022 | Y2: {=EOMONTH(Параметры!$B$1,11)} -> 46022
B3: {=Параметры!$B$3} -> приход | C3: {=Параметры!$B$4} -> расход | D3: {=Параметры!$B$3} -> приход | E3: {=Параметры!$B$4} -> расход | F3: {=Параметры!$B$3} -> приход | G3: {=Параметры!$B$4} -> расход | H3: {=Параметры!$B$3} -> приход | I3: {=Параметры!$B$4} -> расход | J3: {=Параметры!$B$3} -> приход | K3: {=Параметры!$B$4} -> расход | L3: {=Параметры!$B$3} -> приход | M3: {=Параметры!$B$4} -> расход | N3: {=Параметры!$B$3} -> приход | O3: {=Параметры!$B$4} -> расход | P3: {=Параметры!$B$3} -> приход | Q3: {=Параметры!$B$4} -> расход | R3: {=Параметры!$B$3} -> приход | S3: {=Параметры!$B$4} -> расход | T3: {=Параметры!$B$3} -> приход | U3: {=Параметры!$B$4} -> расход | V3: {=Параметры!$B$3} -> приход | W3: {=Параметры!$B$4} -> расход | X3: {=Параметры!$B$3} -> приход | Y3: {=Параметры!$B$4} -> расход
A4: {=Статьи!A2} -> Чай 1 | B4: {=SUMIFS(Данные!$D:$D,Данные!$B:$B,$A4,Данные!$E:$E,B$3,Данные!$A:$A,">="&B$1,Данные!$A:$A,"<="&B$2)} -> -73607.44 | C4: {=SUMIFS(Данные!$D:$D,Данные!$B:$B,$A4,Данные!$E:$E,C$3,Данные!$A:$A,">="&C$1,Данные!$A:$A,"<="&C$2)} -> 275047.94 | D4: {=SUMIFS(Данные!$D:$D,Данные!$B:$B,$A4,Данные!$E:$E,D$3,Данные!$A:$A,">="&D$1,Данные!$A:$A,"<="&D$2)} -> 0 | E4: {=SUMIFS(Данные!$D:$D,Данные!$B:$B,$A4,Данные!$E:$E,E$3,Данные!$A:$A,">="&E$1,Данные!$A:$A,"<="&E$2)} -> 0 | F4: {=SUMIFS(Данные!$D:$D,Данные!$B:$B,$A4,Данные!$E:$E,F$3,Данные!$A:$A,">="&F$1,Данные!$A:$A,"<="&F$2)} -> 674698.26 | G4: {=SUMIFS(Данные!$D:$D,Данные!$B:$B,$A4,Данные!$E:$E,G$3,Данные!$A:$A,">="&G$1,Данные!$A:$A,"<="&G$2)} -> 0 | H4: {=SUMIFS(Данные!$D:$D,Данные!$B:$B,$A4,Данные!$E:$E,H$3,Данные!$A:$A,">="&H$1,Данные!$A:$A,"<="&H$2)} -> 0 | I4: {=SUMIFS(Данные!$D:$D,Данные!$B:$B,$A4,Данные!$E:$E,I$3,Данные!$A:$A,">="&I$1,Данные!$A:$A,"<="&I$2)} -> -77680.2 | ... Y4: {=SUMIFS(Данные!$D:$D,Данные!$B:$B,$A4,Данные!$E:$E,Y$3,Данные!$A:$A,">="&Y$1,Данные!$A:$A,"<="&Y$2)} -> 206959.82 | Z4: {=SUM(B4:Y4)} -> 1884168.1
A5: {=Статьи!A3} -> Чаи 1 | B5: {=SUMIFS(Данные!$D:$D,Данные!$B:$B,$A5,Данные!$E:$E,B$3,Данные!$A:$A,">="&B$1,Данные!$A:$A,"<="&B$2)} -> 150225.98 | C5: {=SUMIFS(Данные!$D:$D,Данные!$B:$B,$A5,Данные!$E:$E,C$3,Данные!$A:$A,">="&C$1,Данные!$A:$A,"<="&C$2)} -> 0 | D5: {=SUMIFS(Данные!$D:$D,Данные!$B:$B,$A5,Данные!$E:$E,D$3,Данные!$A:$A,">="&D$1,Данные!$A:$A,"<="&D$2)} -> 0 | E5: {=SUMIFS(Данные!$D:$D,Данные!$B:$B,$A5,Данные!$E:$E,E$3,Данные!$A:$A,">="&E$1,Данные!$A:$A,"<="&E$2)} -> 0 | F5: {=SUMIFS(Данные!$D:$D,Данные!$B:$B,$A5,Данные!$E:$E,F$3,Данные!$A:$A,">="&F$1,Данные!$A:$A,"<="&F$2)} -> 0 | G5: {=SUMIFS(Данные!$D:$D,Данные!$B:$B,$A5,Данные!$E:$E,G$3,Данные!$A:$A,">="&G$1,Данные!$A:$A,"<="&G$2)} -> 0 | H5: {=SUMIFS(Данные!$D:$D,Данные!$B:$B,$A5,Данные!$E:$E,H$3,Данные!$A:$A,">="&H$1,Данные!$A:$A,"<="&H$2)} -> 0 | I5: {=SUMIFS(Данные!$D:$D,Данные!$B:$B,$A5,Данные!$E:$E,I$3,Данные!$A:$A,">="&I$1,Данные!$A:$A,"<="&I$2)} -> 0 | ... Y5: {=SUMIFS(Данные!$D:$D,Данные!$B:$B,$A5,Данные!$E:$E,Y$3,Данные!$A:$A,">="&Y$1,Данные!$A:$A,"<="&Y$2)} -> 764775.37 | Z5: {=SUM(B5:Y5)} -> 1786608.3
A6: {=Статьи!A4} -> Ёлка 1 | B6: {=SUMIFS(Данные!$D:$D,Данные!$B:$B,$A6,Данные!$E:$E,B$3,Данные!$A:$A,">="&B$1,Данные!$A:$A,"<="&B$2)} -> 284772.29 | C6: {=SUMIFS(Данные!$D:$D,Данные!$B:$B,$A6,Данные!$E:$E,C$3,Данные!$A:$A,">="&C$1,Данные!$A:$A,"<="&C$2)} -> 0 | D6: {=SUMIFS(Данные!$D:$D,Данные!$B:$B,$A6,Данные!$E:$E,D$3,Данные!$A:$A,">="&D$1,Данные!$A:$A,"<="&D$2)} -> 253587.77 | E6: {=SUMIFS(Данные!$D:$D,Данные!$B:$B,$A6,Данные!$E:$E,E$3,Данные!$A:$A,">="&E$1,Данные!$A:$A,"<="&E$2)} -> 222968.2 | F6: {=SUMIFS(Данные!$D:$D,Данные!$B:$B,$A6,Данные!$E:$E,F$3,Данные!$A:$A,">="&F$1,Данные!$A:$A,"<="&F$2)} -> 0 | G6: {=SUMIFS(Данные!$D:$D,Данные!$B:$B,$A6,Данные!$E:$E,G$3,Данные!$A:$A,">="&G$1,Данные!$A:$A,"<="&G$2)} -> 0 | H6: {=SUMIFS(Данные!$D:$D,Данные!$B:$B,$A6,Данные!$E:$E,H$3,Данные!$A:$A,">="&H$1,Данные!$A:$A,"<="&H$2)} -> 239698.95 | I6: {=SUMIFS(Данные!$D:$D,Данные!$B:$B,$A6,Данные!$E:$E,I$3,Данные!$A:$A,">="&I$1,Данные!$A:$A,"<="&I$2)} -> 0 | ... Y6: {=SUMIFS(Данные!$D:$D,Данные!$B:$B,$A6,Данные!$E:$E,Y$3,Данные!$A:$A,">="&Y$1,Данные!$A:$A,"<="&Y$2)} -> 0 | Z6: {=SUM(B6:Y6)} -> 1939261.5
A7: {=Статьи!A5} -> Елка 1 | B7: {=SUMIFS(Данные!$D:$D,Данные!$B:$B,$A7,Данные!$E:$E,B$3,Данные!$A:$A,">="&B$1,Данные!$A:$A,"<="&B$2)} -> 0 | C7: {=SUMIFS(Данные!$D:$D,Данные!$B:$B,$A7,Данные!$E:$E,C$3,Данные!$A:$A,">="&C$1,Данные!$A:$A,"<="&C$2)} -> 0 | D7: {=SUMIFS(Данные!$D:$D,Данные!$B:$B,$A7,Данные!$E:$E,D$3,Данные!$A:$A,">="&D$1,Данные!$A:$A,"<="&D$2)} -> 111694.51 | E7: {=SUMIFS(Данные!$D:$D,Данные!$B:$B,$A7,Данные!$E:$E,E$3,Данные!$A:$A,">="&E$1,Данные!$A:$A,"<="&E$2)} -> 0 | F7: {=SUMIFS(Данные!$D:$D,Данные!$B:$B,$A7,Данные!$E:$E,F$3,Данные!$A:$A,">="&F$1,Данные!$A:$A,"<="&F$2)} -> 426810.2 | G7: {=SUMIFS(Данные!$D:$D,Данные!$B:$B,$A7,Данные!$E:$E,G$3,Данные!$A:$A,">="&G$1,Данные!$A:$A,"<="&G$2)} -> 134585.93 | H7: {=SUMIFS(Данные!$D:$D,Данные!$B:$B,$A7,Данные!$E:$E,H$3,Данные!$A:$A,">="&H$1,Данные!$A:$A,"<="&H$2)} -> 0 | I7: {=SUMIFS(Данные!$D:$D,Данные!$B:$B,$A7,Данные!$E:$E,I$3,Данные!$A:$A,">="&I$1,Данные!$A:$A,"<="&I$2)} -> 0 | ... Y7: {=SUMIFS(Данные!$D:$D,Данные!$B:$B,$A7,Данные!$E:$E,Y$3,Данные!$A:$A,">="&Y$1,Данные!$A:$A,"<="&Y$2)} -> 0 | Z7: {=SUM(B7:Y7)} -> 1525962.7
A8: {=Статьи!A6} -> Аренда 1 | B8: {=SUMIFS(Данные!$D:$D,Данные!$B:$B,$A8,Данные!$E:$E,B$3,Данные!$A:$A,">="&B$1,Данные!$A:$A,"<="&B$2)} -> 0 | C8: {=SUMIFS(Данные!$D:$D,Данные!$B:$B,$A8,Данные!$E:$E,C$3,Данные!$A:$A,">="&C$1,Данные!$A:$A,"<="&C$2)} -> 0 | D8: {=SUMIFS(Данные!$D:$D,Данные!$B:$B,$A8,Данные!$E:$E,D$3,Данные!$A:$A,">="&D$1,Данные!$A:$A,"<="&D$2)} -> 0 | E8: {=SUMIFS(Данные!$D:$D,Данные!$B:$B,$A8,Данные!$E:$E,E$3,Данные!$A:$A,">="&E$1,Данные!$A:$A,"<="&E$2)} -> 117411.05 | F8: {=SUMIFS(Данные!$D:$D,Данные!$B:$B,$A8,Данные!$E:$E,F$3,Данные!$A:$A,">="&F$1,Данные!$A:$A,"<="&F$2)} -> 200873.7 | G8: {=SUMIFS(Данные!$D:$D,Данные!$B:$B,$A8,Данные!$E:$E,G$3,Данные!$A:$A,">="&G$1,Данные!$A:$A,"<="&G$2)} -> 0 | H8: {=SUMIFS(Данные!$D:$D,Данные!$B:$B,$A8,Данные!$E:$E,H$3,Данные!$A:$A,">="&H$1,Данные!$A:$A,"<="&H$2)} -> 0 | I8: {=SUMIFS(Данные!$D:$D,Данные!$B:$B,$A8,Данные!$E:$E,I$3,Данные!$A:$A,">="&I$1,Данные!$A:$A,"<="&I$2)} -> 90275.12 | ... Y8: {=SUMIFS(Данные!$D:$D,Данные!$B:$B,$A8,Данные!$E:$E,Y$3,Данные!$A:$A,">="&Y$1,Данные!$A:$A,"<="&Y$2)} -> 0 | Z8: {=SUM(B8:Y8)} -> 1496071.2
A9: Итого группа 1 | B9: {=SUM(B4:B8)} -> 361390.83 | C9: {=SUM(C4:C8)} -> 275047.94 | D9: {=SUM(D4:D8)} -> 365282.28 | E9: {=SUM(E4:E8)} -> 340379.25 | F9: {=SUM(F4:F8)} -> 1302382.2 | G9: {=SUM(G4:G8)} -> 134585.93 | H9: {=SUM(H4:H8)} -> 239698.95 | I9: {=SUM(I4:I8)} -> 12594.92 | ... Z9: {=SUM(Z4:Z8)} -> 8632071.8
A10: {=Статьи!A7} -> Связь 1 | B10: {=SUMIFS(Данные!$D:$D,Данные!$B:$B,$A10,Данные!$E:$E,B$3,Данные!$A:$A,">="&B$1,Данные!$A:$A,"<="&B$2)} -> 97614.39 | C10: {=SUMIFS(Данные!$D:$D,Данные!$B:$B,$A10,Данные!$E:$E,C$3,Данные!$A:$A,">="&C$1,Данные!$A:$A,"<="&C$2)} -> 0 | D10: {=SUMIFS(Данные!$D:$D,Данные!$B:$B,$A10,Данные!$E:$E,D$3,Данные!$A:$A,">="&D$1,Данные!$A:$A,"<="&D$2)} -> 178192.36 | E10: {=SUMIFS(Данные!$D:$D,Данные!$B:$B,$A10,Данные!$E:$E,E$3,Данные!$A:$A,">="&E$1,Данные!$A:$A,"<="&E$2)} -> 0 | F10: {=SUMIFS(Данные!$D:$D,Данные!$B:$B,$A10,Данные!$E:$E,F$3,Данные!$A:$A,">="&F$1,Данные!$A:$A,"<="&F$2)} -> 0 | G10: {=SUMIFS(Данные!$D:$D,Данные!$B:$B,$A10,Данные!$E:$E,G$3,Данные!$A:$A,">="&G$1,Данные!$A:$A,"<="&G$2)} -> 0 | H10: {=SUMIFS(Данные!$D:$D,Данные!$B:$B,$A10,Данные!$E:$E,H$3,Данные!$A:$A,">="&H$1,Данные!$A:$A,"<="&H$2)} -> 0 | I10: {=SUMIFS(Данные!$D:$D,Данные!$B:$B,$A10,Данные!$E:$E,I$3,Данные!$A:$A,">="&I$1,Данные!$A:$A,"<="&I$2)} -> 0 | ... Y10: {=SUMIFS(Данные!$D:$D,Данные!$B:$B,$A10,Данные!$E:$E,Y$3,Данные!$A:$A,">="&Y$1,Данные!$A:$A,"<="&Y$2)} -> 78369.71 | Z10: {=SUM(B10:Y10)} -> 1284143.1
A11: {=Статьи!A8} -> Налог 1 | B11: {=SUMIFS(Данные!$D:$D,Данные!$B:$B,$A11,Данные!$E:$E,B$3,Данные!$A:$A,">="&B$1,Данные!$A:$A,"<="&B$2)} -> 0 | C11: {=SUMIFS(Данные!$D:$D,Данные!$B:$B,$A11,Данные!$E:$E,C$3,Данные!$A:$A,">="&C$1,Данные!$A:$A,"<="&C$2)} -> 0 | D11: {=SUMIFS(Данные!$D:$D,Данные!$B:$B,$A11,Данные!$E:$E,D$3,Данные!$A:$A,">="&D$1,Данные!$A:$A,"<="&D$2)} -> 0 | E11: {=SUMIFS(Данные!$D:$D,Данные!$B:$B,$A11,Данные!$E:$E,E$3,Данные!$A:$A,">="&E$1,Данные!$A:$A,"<="&E$2)} -> 24606.32 | F11: {=SUMIFS(Данные!$D:$D,Данные!$B:$B,$A11,Данные!$E:$E,F$3,Данные!$A:$A,">="&F$1,Данные!$A:$A,"<="&F$2)} -> -53530.76 | G11: {=SUMIFS(Данные!$D:$D,Данные!$B:$B,$A11,Данные!$E:$E,G$3,Данные!$A:$A,">="&G$1,Данные!$A:$A,"<="&G$2)} -> 0 | H11: {=SUMIFS(Данные!$D:$D,Данные!$B:$B,$A11,Данные!$E:$E,H$3,Данные!$A:$A,">="&H$1,Данные!$A:$A,"<="&H$2)} -> 0 | I11: {=SUMIFS(Данные!$D:$D,Данные!$B:$B,$A11,Данные!$E:$E,I$3,Данные!$A:$A,">="&I$1,Данные!$A:$A,"<="&I$2)} -> 0 | ... Y11: {=SUMIFS(Данные!$D:$D,Данные!$B:$B,$A11,Данные!$E:$E,Y$3,Данные!$A:$A,">="&Y$1,Данные!$A:$A,"<="&Y$2)} -> 0 | Z11: {=SUM(B11:Y11)} -> 630619.24
A12: {=Статьи!A9} -> Доход 1 | B12: {=SUMIFS(Данные!$D:$D,Данные!$B:$B,$A12,Данные!$E:$E,B$3,Данные!$A:$A,">="&B$1,Данные!$A:$A,"<="&B$2)} -> 10010.8 | C12: {=SUMIFS(Данные!$D:$D,Данные!$B:$B,$A12,Данные!$E:$E,C$3,Данные!$A:$A,">="&C$1,Данные!$A:$A,"<="&C$2)} -> 0 | D12: {=SUMIFS(Данные!$D:$D,Данные!$B:$B,$A12,Данные!$E:$E,D$3,Данные!$A:$A,">="&D$1,Данные!$A:$A,"<="&D$2)} -> 0 | E12: {=SUMIFS(Данные!$D:$D,Данные!$B:$B,$A12,Данные!$E:$E,E$3,Данные!$A:$A,">="&E$1,Данные!$A:$A,"<="&E$2)} -> 0 | F12: {=SUMIFS(Данные!$D:$D,Данные!$B:$B,$A12,Данные!$E:$E,F$3,Данные!$A:$A,">="&F$1,Данные!$A:$A,"<="&F$2)} -> 0 | G12: {=SUMIFS(Данные!$D:$D,Данные!$B:$B,$A12,Данные!$E:$E,G$3,Данные!$A:$A,">="&G$1,Данные!$A:$A,"<="&G$2)} -> 242812.16 | H12: {=SUMIFS(Данные!$D:$D,Данные!$B:$B,$A12,Данные!$E:$E,H$3,Данные!$A:$A,">="&H$1,Данные!$A:$A,"<="&H$2)} -> 0 | I12: {=SUMIFS(Данные!$D:$D,Данные!$B:$B,$A12,Данные!$E:$E,I$3,Данные!$A:$A,">="&I$1,Данные!$A:$A,"<="&I$2)} -> 0 | ... Y12: {=SUMIFS(Данные!$D:$D,Данные!$B:$B,$A12,Данные!$E:$E,Y$3,Данные!$A:$A,">="&Y$1,Данные!$A:$A,"<="&Y$2)} -> 0 | Z12: {=SUM(B12:Y12)} -> 1746676.3
A13: {=Статьи!A10} -> Сырьё 1 | B13: {=SUMIFS(Данные!$D:$D,Данные!$B:$B,$A13,Данные!$E:$E,B$3,Данные!$A:$A,">="&B$1,Данные!$A:$A,"<="&B$2)} -> 128341.97 | C13: {=SUMIFS(Данные!$D:$D,Данные!$B:$B,$A13,Данные!$E:$E,C$3,Данные!$A:$A,">="&C$1,Данные!$A:$A,"<="&C$2)} -> 227978.85 | D13: {=SUMIFS(Данные!$D:$D,Данные!$B:$B,$A13,Данные!$E:$E,D$3,Данные!$A:$A,">="&D$1,Данные!$A:$A,"<="&D$2)} -> 0 | E13: {=SUMIFS(Данные!$D:$D,Данные!$B:$B,$A13,Данные!$E:$E,E$3,Данные!$A:$A,">="&E$1,Данные!$A:$A,"<="&E$2)} -> 0 | F13: {=SUMIFS(Данные!$D:$D,Данные!$B:$B,$A13,Данные!$E:$E,F$3,Данные!$A:$A,">="&F$1,Данные!$A:$A,"<="&F$2)} -> 0 | G13: {=SUMIFS(Данные!$D:$D,Данные!$B:$B,$A13,Данные!$E:$E,G$3,Данные!$A:$A,">="&G$1,Данные!$A:$A,"<="&G$2)} -> 0 | H13: {=SUMIFS(Данные!$D:$D,Данные!$B:$B,$A13,Данные!$E:$E,H$3,Данные!$A:$A,">="&H$1,Данные!$A:$A,"<="&H$2)} -> 0 | I13: {=SUMIFS(Данные!$D:$D,Данные!$B:$B,$A13,Данные!$E:$E,I$3,Данные!$A:$A,">="&I$1,Данные!$A:$A,"<="&I$2)} -> 339107.89 | ... Y13: {=SUMIFS(Данные!$D:$D,Данные!$B:$B,$A13,Данные!$E:$E,Y$3,Данные!$A:$A,">="&Y$1,Данные!$A:$A,"<="&Y$2)} -> 326886.85 | Z13: {=SUM(B13:Y13)} -> 1461005.5
A14: {=Статьи!A11} -> Сырье 1 | B14: {=SUMIFS(Данные!$D:$D,Данные!$B:$B,$A14,Данные!$E:$E,B$3,Данные!$A:$A,">="&B$1,Данные!$A:$A,"<="&B$2)} -> 0 | C14: {=SUMIFS(Данные!$D:$D,Данные!$B:$B,$A14,Данные!$E:$E,C$3,Данные!$A:$A,">="&C$1,Данные!$A:$A,"<="&C$2)} -> 0 | D14: {=SUMIFS(Данные!$D:$D,Данные!$B:$B,$A14,Данные!$E:$E,D$3,Данные!$A:$A,">="&D$1,Данные!$A:$A,"<="&D$2)} -> 0 | E14: {=SUMIFS(Данные!$D:$D,Данные!$B:$B,$A14,Данные!$E:$E,E$3,Данные!$A:$A,">="&E$1,Данные!$A:$A,"<="&E$2)} -> 0 | F14: {=SUMIFS(Данные!$D:$D,Данные!$B:$B,$A14,Данные!$E:$E,F$3,Данные!$A:$A,">="&F$1,Данные!$A:$A,"<="&F$2)} -> 0 | G14: {=SUMIFS(Данные!$D:$D,Данные!$B:$B,$A14,Данные!$E:$E,G$3,Данные!$A:$A,">="&G$1,Данные!$A:$A,"<="&G$2)} -> -7891.15 | H14: {=SUMIFS(Данные!$D:$D,Данные!$B:$B,$A14,Данные!$E:$E,H$3,Данные!$A:$A,">="&H$1,Данные!$A:$A,"<="&H$2)} -> 0 | I14: {=SUMIFS(Данные!$D:$D,Данные!$B:$B,$A14,Данные!$E:$E,I$3,Данные!$A:$A,">="&I$1,Данные!$A:$A,"<="&I$2)} -> 0 | ... Y14: {=SUMIFS(Данные!$D:$D,Данные!$B:$B,$A14,Данные!$E:$E,Y$3,Данные!$A:$A,">="&Y$1,Данные!$A:$A,"<="&Y$2)} -> -31559.73 | Z14: {=SUM(B14:Y14)} -> 472649.75
A15: Итого группа 2 | B15: {=SUM(B10:B14)} -> 235967.16 | C15: {=SUM(C10:C14)} -> 227978.85 | D15: {=SUM(D10:D14)} -> 178192.36 | E15: {=SUM(E10:E14)} -> 24606.32 | F15: {=SUM(F10:F14)} -> -53530.76 | G15: {=SUM(G10:G14)} -> 234921.01 | H15: {=SUM(H10:H14)} -> 0 | I15: {=SUM(I10:I14)} -> 339107.89 | ... Z15: {=SUM(Z10:Z14)} -> 5595093.9
A16: {=Статьи!A12} -> Чай 2 | B16: {=SUMIFS(Данные!$D:$D,Данные!$B:$B,$A16,Данные!$E:$E,B$3,Данные!$A:$A,">="&B$1,Данные!$A:$A,"<="&B$2)} -> 0 | C16: {=SUMIFS(Данные!$D:$D,Данные!$B:$B,$A16,Данные!$E:$E,C$3,Данные!$A:$A,">="&C$1,Данные!$A:$A,"<="&C$2)} -> 0 | D16: {=SUMIFS(Данные!$D:$D,Данные!$B:$B,$A16,Данные!$E:$E,D$3,Данные!$A:$A,">="&D$1,Данные!$A:$A,"<="&D$2)} -> 0 | E16: {=SUMIFS(Данные!$D:$D,Данные!$B:$B,$A16,Данные!$E:$E,E$3,Данные!$A:$A,">="&E$1,Данные!$A:$A,"<="&E$2)} -> 0 | F16: {=SUMIFS(Данные!$D:$D,Данные!$B:$B,$A16,Данные!$E:$E,F$3,Данные!$A:$A,">="&F$1,Данные!$A:$A,"<="&F$2)} -> 0 | G16: {=SUMIFS(Данные!$D:$D,Данные!$B:$B,$A16,Данные!$E:$E,G$3,Данные!$A:$A,">="&G$1,Данные!$A:$A,"<="&G$2)} -> 261512.61 | H16: {=SUMIFS(Данные!$D:$D,Данные!$B:$B,$A16,Данные!$E:$E,H$3,Данные!$A:$A,">="&H$1,Данные!$A:$A,"<="&H$2)} -> 0 | I16: {=SUMIFS(Данные!$D:$D,Данные!$B:$B,$A16,Данные!$E:$E,I$3,Данные!$A:$A,">="&I$1,Данные!$A:$A,"<="&I$2)} -> -82587.59 | ... Y16: {=SUMIFS(Данные!$D:$D,Данные!$B:$B,$A16,Данные!$E:$E,Y$3,Данные!$A:$A,">="&Y$1,Данные!$A:$A,"<="&Y$2)} -> 635438.37 | Z16: {=SUM(B16:Y16)} -> 2050056.9
A17: {=Статьи!A13} -> Чаи 2 | B17: {=SUMIFS(Данные!$D:$D,Данные!$B:$B,$A17,Данные!$E:$E,B$3,Данные!$A:$A,">="&B$1,Данные!$A:$A,"<="&B$2)} -> 0 | C17: {=SUMIFS(Данные!$D:$D,Данные!$B:$B,$A17,Данные!$E:$E,C$3,Данные!$A:$A,">="&C$1,Данные!$A:$A,"<="&C$2)} -> 0 | D17: {=SUMIFS(Данные!$D:$D,Данные!$B:$B,$A17,Данные!$E:$E,D$3,Данные!$A:$A,">="&D$1,Данные!$A:$A,"<="&D$2)} -> 0 | E17: {=SUMIFS(Данные!$D:$D,Данные!$B:$B,$A17,Данные!$E:$E,E$3,Данные!$A:$A,">="&E$1,Данные!$A:$A,"<="&E$2)} -> 0 | F17: {=SUMIFS(Данные!$D:$D,Данные!$B:$B,$A17,Данные!$E:$E,F$3,Данные!$A:$A,">="&F$1,Данные!$A:$A,"<="&F$2)} -> 0 | G17: {=SUMIFS(Данные!$D:$D,Данные!$B:$B,$A17,Данные!$E:$E,G$3,Данные!$A:$A,">="&G$1,Данные!$A:$A,"<="&G$2)} -> 0 | H17: {=SUMIFS(Данные!$D:$D,Данные!$B:$B,$A17,Данные!$E:$E,H$3,Данные!$A:$A,">="&H$1,Данные!$A:$A,"<="&H$2)} -> 0 | I17: {=SUMIFS(Данные!$D:$D,Данные!$B:$B,$A17,Данные!$E:$E,I$3,Данные!$A:$A,">="&I$1,Данные!$A:$A,"<="&I$2)} -> 0 | ... Y17: {=SUMIFS(Данные!$D:$D,Данные!$B:$B,$A17,Данные!$E:$E,Y$3,Данные!$A:$A,">="&Y$1,Данные!$A:$A,"<="&Y$2)} -> 73165.31 | Z17: {=SUM(B17:Y17)} -> 334421.4
A18: {=Статьи!A14} -> Ёлка 2 | B18: {=SUMIFS(Данные!$D:$D,Данные!$B:$B,$A18,Данные!$E:$E,B$3,Данные!$A:$A,">="&B$1,Данные!$A:$A,"<="&B$2)} -> 0 | C18: {=SUMIFS(Данные!$D:$D,Данные!$B:$B,$A18,Данные!$E:$E,C$3,Данные!$A:$A,">="&C$1,Данные!$A:$A,"<="&C$2)} -> 225830.81 | D18: {=SUMIFS(Данные!$D:$D,Данные!$B:$B,$A18,Данные!$E:$E,D$3,Данные!$A:$A,">="&D$1,Данные!$A:$A,"<="&D$2)} -> 0 | E18: {=SUMIFS(Данные!$D:$D,Данные!$B:$B,$A18,Данные!$E:$E,E$3,Данные!$A:$A,">="&E$1,Данные!$A:$A,"<="&E$2)} -> -52645.57 | F18: {=SUMIFS(Данные!$D:$D,Данные!$B:$B,$A18,Данные!$E:$E,F$3,Данные!$A:$A,">="&F$1,Данные!$A:$A,"<="&F$2)} -> 273906.27 | G18: {=SUMIFS(Данные!$D:$D,Данные!$B:$B,$A18,Данные!$E:$E,G$3,Данные!$A:$A,">="&G$1,Данные!$A:$A,"<="&G$2)} -> 0 | H18: {=SUMIFS(Данные!$D:$D,Данные!$B:$B,$A18,Данные!$E:$E,H$3,Данные!$A:$A,">="&H$1,Данные!$A:$A,"<="&H$2)} -> 0 | I18: {=SUMIFS(Данные!$D:$D,Данные!$B:$B,$A18,Данные!$E:$E,I$3,Данные!$A:$A,">="&I$1,Данные!$A:$A,"<="&I$2)} -> 0 | ... Y18: {=SUMIFS(Данные!$D:$D,Данные!$B:$B,$A18,Данные!$E:$E,Y$3,Данные!$A:$A,">="&Y$1,Данные!$A:$A,"<="&Y$2)} -> 0 | Z18: {=SUM(B18:Y18)} -> 773174.4
