Workbook

Sheet D
B1: 4 | C1: 2 | D1: 1 | E1: 1 | F1: Аренда | G1: 1 | H1: 45657 | I1: -10000 | J1: -10000 | L1: 1 | M1: one | N1: 10 | P1: 1 | Q1: 2 | R1: 5 | S1: 6 | U1: Tree | V1: Height | W1: Age | X1: Yield | Y1: Profit | AA1: Tree | AB1: Height | AC1: Tree | AD1: Tree | AE1: Tree | AF1: Tree | AG1: Tree | AH1: 0 | AI1: 0.2 | AK1: 58 | AL1: 35 | AM1: 45.35 | AN1: 47.65 | AP1: 41235 | AQ1: 0.09 | AR1: 1 | AS1: 1 | AT1: 0 | AU1: 39448 | AV1: 4 | AW1: TRUE | AX1: TRUE | AY1: 3 | AZ1: 1 | BA1: 6 | BB1: 33100 | BC1: 11 | BD1: 17 | BE1: 89 | BF1: 1 | BG1: 1 | BH1: a
A2: 2 | B2: 8 | C2: 7 | D2: 2 | E2: 2 | F2: аренда | G2: 2 | H2: 45658 | I2: 3000 | J2: 2750 | L2: 2 | M2: two | N2: 20 | P2: 3 | Q2: 4 | R2: 7 | S2: 8 | U2: Apple | V2: 18 | W2: 20 | X2: 14 | Y2: 105 | AA2: Apple | AB2: >10 | AC2: Pear | AD2: a* | AE2: Cherry | AF2: Plum | AH2: 1 | AI2: 0.3 | AK2: 11 | AL2: 25 | AM2: 17.56 | AN2: 18.44 | AP2: 41247 | AQ2: 0.11 | AR2: -0.5 | AS2: 2 | AT2: 10 | AU2: 39508 | AV2: 5 | AW2: FALSE | AX2: TRUE | AY2: 5 | AZ2: 2 | BA2: 7 | BB2: 47300 | BC2: 12 | BD2: 18 | BE2: 88 | BF2: 2 | BG2: 2
A3: abc | B3: 15 | C3: 11 | D3: abc | E3: =1/0 -> #DIV/0! | F3: Арендй | G3: 4 | H3: 45659 | I3: 4200 | J3: 4250 | L3: 3 | M3: three | N3: 30 | U3: Pear | V3: 12 | W3: 12 | X3: 10 | Y3: 96 | AH3: 2 | AI3: 0.1 | AK3: 10 | AL3: 23 | AM3: 16.09 | AN3: 16.91 | AP3: 41295 | AQ3: 0.1 | AR3: 0.041666667 | AS3: 2 | AT3: 20 | AU3: 39751 | AV3: 8 | AW3: abc | AX3: 1 | AY3: 7 | AZ3: 3 | BB3: 69000 | BC3: 13 | BE3: 92 | BF3: 2 | BG3: 3 | BH3: Б
A4: TRUE | B4: 16 | C4: 19 | D4: TRUE | E4: 4 | F4: Арeнда* | G4: 8 | H4: 45689 | I4: 6800 | J4: 3250 | L4: 5 | M4: five | N4: 50 | P4: 1 | Q4: 2 | R4: 3 | U4: Cherry | V4: 13 | W4: 14 | X4: 9 | Y4: 105 | AH4: 3 | AI4: 0.4 | AP4: 39778 | AR4: -0.0013888889 | AS4: a | AU4: 39859 | AV4: 7 | AY4: 10 | AZ4: 4 | BB4: 102000 | BC4: 14 | BE4: 101 | BF4: 3 | BG4: 4
A5: FALSE | B5: 23 | C5: 21 | E5: 5 | F5: x*y | G5: 16 | H5: 45717 | I5: 1200 | J5: 2750 | L5: 8 | M5: eight | N5: 80 | P5: 4 | Q5: 5 | R5: 6 | U5: Apple | V5: 14 | W5: 15 | X5: 10 | Y5: 75 | AK5: 58 | AL5: 35 | AP5: 39786 | AS5: A | AU5: 39904 | AV5: 11 | AY5: 11 | AZ5: 5 | BB5: 150000 | BC5: 15 | BE5: 94 | BF5: 5 | BG5: 3
A6: 45688 | B6: 42 | C6: 40 | D6: 5 | E6: 6 | F6: Чай | G6: 32 | H6: 45473 | L6: 13 | M6: thirteen | N6: 130 | U6: Pear | V6: 9 | W6: 8 | X6: 8 | Y6: 76.8 | AK6: 11 | AP6: 39834 | AS6: 3 | AV6: 4 | BB6: 220000 | BC6: 16 | BE6: 97 | BF6: 2 | BG6: 2
A7: =1/0 -> #DIV/0! | B7: -3.5 | C7: -1 | D7: FALSE | E7: 7 | F7: Чаи | G7: 64 | H7: 46022 | I7: -10000 | J7: 100 | U7: Apple | V7: 8 | W7: 9 | X7: 6 | Y7: 45 | AK7: TRUE | AL7: 23 | AP7: 38719 | AS7: 1 | AU7: 39508 | AV7: 3 | BE7: 95 | BG7: 1
A8: =NA() -> #N/A | B8: 10.25 | C8: 9 | D8: 3.5 | E8: 8 | I8: 3000 | J8: 200 | L8: 1 | M8: 2 | N8: 3 | O8: 5 | P8: 8 | Q8: 13 | AP8: 38733 | AS8: b | AU8: 39448 | BG8: 2
A9: Привет Мир | I9: 4200 | J9: 300 | L9: one | M9: two | N9: three | O9: five | P9: eight | Q9: thirteen | AK9: 58 | AL9: 35 | AU9: 39751 | BG9: 3
A10: 1.5 | J10: 400 | L10: 10 | M10: 20 | N10: 30 | O10: 50 | P10: 80 | Q10: 130 | AK10: 11 | AL10: =1/0 -> #DIV/0! | AU10: 39859 | BG10: 5
A11: 1,5 | I11: 6800 | J11: 500 | AK11: 10 | AL11: 23 | AU11: 39904 | BG11: 6
A12: 0 | BG12: 1
A13: ="" | I13: -10000
A14: =CHAR(9)&"abc"&CHAR(10) -> abc | I14: 3000
A15: 45688.75 | I15: =NA() -> #N/A
I16: 6800
I17: 1200

Sheet C
A1: {=PV(0.00666666666666667,FALSE,500,0,0)} -> 0 | B1: =IF(ISERROR(A1),ERROR.TYPE(A1),IF(ISNUMBER(A1),0,IF(ISLOGICAL(A1),IF(A1,-1,-2),IF(ISTEXT(A1),-3,-4)))) -> 0 | C1: =IF(ISNUMBER(A1),A1,0) -> 0 | D1: =IF(ISTEXT(A1),A1,"") | E1: all:PV#8
A2: {=PV(0.00666666666666667,240,,0,0)} -> 0 | B2: =IF(ISERROR(A2),ERROR.TYPE(A2),IF(ISNUMBER(A2),0,IF(ISLOGICAL(A2),IF(A2,-1,-2),IF(ISTEXT(A2),-3,-4)))) -> 0 | C2: =IF(ISNUMBER(A2),A2,0) -> 0 | D2: =IF(ISTEXT(A2),A2,"") | E2: all:PV#9
A3: {=PV(0.00666666666666667,240,0,0,0)} -> 0 | B3: =IF(ISERROR(A3),ERROR.TYPE(A3),IF(ISNUMBER(A3),0,IF(ISLOGICAL(A3),IF(A3,-1,-2),IF(ISTEXT(A3),-3,-4)))) -> 0 | C3: =IF(ISNUMBER(A3),A3,0) -> 0 | D3: =IF(ISTEXT(A3),A3,"") | E3: all:PV#10
A4: {=PV(0.00666666666666667,240,"",0,0)} -> #VALUE! | B4: =IF(ISERROR(A4),ERROR.TYPE(A4),IF(ISNUMBER(A4),0,IF(ISLOGICAL(A4),IF(A4,-1,-2),IF(ISTEXT(A4),-3,-4)))) -> 3 | C4: =IF(ISNUMBER(A4),A4,0) -> 0 | D4: =IF(ISTEXT(A4),A4,"") | E4: all:PV#11
A5: {=PV(0.00666666666666667,240,FALSE,0,0)} -> 0 | B5: =IF(ISERROR(A5),ERROR.TYPE(A5),IF(ISNUMBER(A5),0,IF(ISLOGICAL(A5),IF(A5,-1,-2),IF(ISTEXT(A5),-3,-4)))) -> 0 | C5: =IF(ISNUMBER(A5),A5,0) -> 0 | D5: =IF(ISTEXT(A5),A5,"") | E5: all:PV#12
A6: {=PV(0.00666666666666667,240,500,,0)} -> -59777.146 | B6: =IF(ISERROR(A6),ERROR.TYPE(A6),IF(ISNUMBER(A6),0,IF(ISLOGICAL(A6),IF(A6,-1,-2),IF(ISTEXT(A6),-3,-4)))) -> 0 | C6: =IF(ISNUMBER(A6),A6,0) -> -59777.146 | D6: =IF(ISTEXT(A6),A6,"") | E6: all:PV#13
A7: {=PV(0.00666666666666667,240,500,0,0)} -> -59777.146 | B7: =IF(ISERROR(A7),ERROR.TYPE(A7),IF(ISNUMBER(A7),0,IF(ISLOGICAL(A7),IF(A7,-1,-2),IF(ISTEXT(A7),-3,-4)))) -> 0 | C7: =IF(ISNUMBER(A7),A7,0) -> -59777.146 | D7: =IF(ISTEXT(A7),A7,"") | E7: all:PV#14
A8: {=PV(0.00666666666666667,240,500,"",0)} -> #VALUE! | B8: =IF(ISERROR(A8),ERROR.TYPE(A8),IF(ISNUMBER(A8),0,IF(ISLOGICAL(A8),IF(A8,-1,-2),IF(ISTEXT(A8),-3,-4)))) -> 3 | C8: =IF(ISNUMBER(A8),A8,0) -> 0 | D8: =IF(ISTEXT(A8),A8,"") | E8: all:PV#15
A9: {=PV(0.00666666666666667,240,500,FALSE,0)} -> -59777.146 | B9: =IF(ISERROR(A9),ERROR.TYPE(A9),IF(ISNUMBER(A9),0,IF(ISLOGICAL(A9),IF(A9,-1,-2),IF(ISTEXT(A9),-3,-4)))) -> 0 | C9: =IF(ISNUMBER(A9),A9,0) -> -59777.146 | D9: =IF(ISTEXT(A9),A9,"") | E9: all:PV#16
A10: {=PV(0.00666666666666667,240,500,0,)} -> -59777.146 | B10: =IF(ISERROR(A10),ERROR.TYPE(A10),IF(ISNUMBER(A10),0,IF(ISLOGICAL(A10),IF(A10,-1,-2),IF(ISTEXT(A10),-3,-4)))) -> 0 | C10: =IF(ISNUMBER(A10),A10,0) -> -59777.146 | D10: =IF(ISTEXT(A10),A10,"") | E10: all:PV#17
A11: {=PV(0.00666666666666667,240,500,0,0)} -> -59777.146 | B11: =IF(ISERROR(A11),ERROR.TYPE(A11),IF(ISNUMBER(A11),0,IF(ISLOGICAL(A11),IF(A11,-1,-2),IF(ISTEXT(A11),-3,-4)))) -> 0 | C11: =IF(ISNUMBER(A11),A11,0) -> -59777.146 | D11: =IF(ISTEXT(A11),A11,"") | E11: all:PV#18
A12: {=PV(0.00666666666666667,240,500,0,"")} -> #VALUE! | B12: =IF(ISERROR(A12),ERROR.TYPE(A12),IF(ISNUMBER(A12),0,IF(ISLOGICAL(A12),IF(A12,-1,-2),IF(ISTEXT(A12),-3,-4)))) -> 3 | C12: =IF(ISNUMBER(A12),A12,0) -> 0 | D12: =IF(ISTEXT(A12),A12,"") | E12: all:PV#19
A13: {=PV(0.00666666666666667,240,500,0,FALSE)} -> -59777.146 | B13: =IF(ISERROR(A13),ERROR.TYPE(A13),IF(ISNUMBER(A13),0,IF(ISLOGICAL(A13),IF(A13,-1,-2),IF(ISTEXT(A13),-3,-4)))) -> 0 | C13: =IF(ISNUMBER(A13),A13,0) -> -59777.146 | D13: =IF(ISTEXT(A13),A13,"") | E13: all:PV#20
A14: {=QUARTILE(,1)} -> 0 | B14: =IF(ISERROR(A14),ERROR.TYPE(A14),IF(ISNUMBER(A14),0,IF(ISLOGICAL(A14),IF(A14,-1,-2),IF(ISTEXT(A14),-3,-4)))) -> 0 | C14: =IF(ISNUMBER(A14),A14,0) -> 0 | D14: =IF(ISTEXT(A14),A14,"") | E14: all:QUARTILE#1
A15: {=QUARTILE(0,1)} -> 0 | B15: =IF(ISERROR(A15),ERROR.TYPE(A15),IF(ISNUMBER(A15),0,IF(ISLOGICAL(A15),IF(A15,-1,-2),IF(ISTEXT(A15),-3,-4)))) -> 0 | C15: =IF(ISNUMBER(A15),A15,0) -> 0 | D15: =IF(ISTEXT(A15),A15,"") | E15: all:QUARTILE#2
A16: {=QUARTILE("",1)} -> #VALUE! | B16: =IF(ISERROR(A16),ERROR.TYPE(A16),IF(ISNUMBER(A16),0,IF(ISLOGICAL(A16),IF(A16,-1,-2),IF(ISTEXT(A16),-3,-4)))) -> 3 | C16: =IF(ISNUMBER(A16),A16,0) -> 0 | D16: =IF(ISTEXT(A16),A16,"") | E16: all:QUARTILE#3
A17: {=QUARTILE(FALSE,1)} -> 0 | B17: =IF(ISERROR(A17),ERROR.TYPE(A17),IF(ISNUMBER(A17),0,IF(ISLOGICAL(A17),IF(A17,-1,-2),IF(ISTEXT(A17),-3,-4)))) -> 0 | C17: =IF(ISNUMBER(A17),A17,0) -> 0 | D17: =IF(ISTEXT(A17),A17,"") | E17: all:QUARTILE#4
A18: {=QUARTILE(D!B1:B8,)} -> -3.5 | B18: =IF(ISERROR(A18),ERROR.TYPE(A18),IF(ISNUMBER(A18),0,IF(ISLOGICAL(A18),IF(A18,-1,-2),IF(ISTEXT(A18),-3,-4)))) -> 0 | C18: =IF(ISNUMBER(A18),A18,0) -> -3.5 | D18: =IF(ISTEXT(A18),A18,"") | E18: all:QUARTILE#5
A19: {=QUARTILE(D!B1:B8,0)} -> -3.5 | B19: =IF(ISERROR(A19),ERROR.TYPE(A19),IF(ISNUMBER(A19),0,IF(ISLOGICAL(A19),IF(A19,-1,-2),IF(ISTEXT(A19),-3,-4)))) -> 0 | C19: =IF(ISNUMBER(A19),A19,0) -> -3.5 | D19: =IF(ISTEXT(A19),A19,"") | E19: all:QUARTILE#6
A20: {=QUARTILE(D!B1:B8,"")} -> #VALUE! | B20: =IF(ISERROR(A20),ERROR.TYPE(A20),IF(ISNUMBER(A20),0,IF(ISLOGICAL(A20),IF(A20,-1,-2),IF(ISTEXT(A20),-3,-4)))) -> 3 | C20: =IF(ISNUMBER(A20),A20,0) -> 0 | D20: =IF(ISTEXT(A20),A20,"") | E20: all:QUARTILE#7
A21: {=QUARTILE(D!B1:B8,FALSE)} -> -3.5 | B21: =IF(ISERROR(A21),ERROR.TYPE(A21),IF(ISNUMBER(A21),0,IF(ISLOGICAL(A21),IF(A21,-1,-2),IF(ISTEXT(A21),-3,-4)))) -> 0 | C21: =IF(ISNUMBER(A21),A21,0) -> -3.5 | D21: =IF(ISTEXT(A21),A21,"") | E21: all:QUARTILE#8
A22: {=_xlfn.QUARTILE.EXC(,1)} -> #NUM! | B22: =IF(ISERROR(A22),ERROR.TYPE(A22),IF(ISNUMBER(A22),0,IF(ISLOGICAL(A22),IF(A22,-1,-2),IF(ISTEXT(A22),-3,-4)))) -> 6 | C22: =IF(ISNUMBER(A22),A22,0) -> 0 | D22: =IF(ISTEXT(A22),A22,"") | E22: all:QUARTILE.EXC#1
A23: {=_xlfn.QUARTILE.EXC(0,1)} -> #NUM! | B23: =IF(ISERROR(A23),ERROR.TYPE(A23),IF(ISNUMBER(A23),0,IF(ISLOGICAL(A23),IF(A23,-1,-2),IF(ISTEXT(A23),-3,-4)))) -> 6 | C23: =IF(ISNUMBER(A23),A23,0) -> 0 | D23: =IF(ISTEXT(A23),A23,"") | E23: all:QUARTILE.EXC#2
A24: {=_xlfn.QUARTILE.EXC("",1)} -> #VALUE! | B24: =IF(ISERROR(A24),ERROR.TYPE(A24),IF(ISNUMBER(A24),0,IF(ISLOGICAL(A24),IF(A24,-1,-2),IF(ISTEXT(A24),-3,-4)))) -> 3 | C24: =IF(ISNUMBER(A24),A24,0) -> 0 | D24: =IF(ISTEXT(A24),A24,"") | E24: all:QUARTILE.EXC#3
A25: {=_xlfn.QUARTILE.EXC(FALSE,1)} -> #NUM! | B25: =IF(ISERROR(A25),ERROR.TYPE(A25),IF(ISNUMBER(A25),0,IF(ISLOGICAL(A25),IF(A25,-1,-2),IF(ISTEXT(A25),-3,-4)))) -> 6 | C25: =IF(ISNUMBER(A25),A25,0) -> 0 | D25: =IF(ISTEXT(A25),A25,"") | E25: all:QUARTILE.EXC#4
A26: {=_xlfn.QUARTILE.EXC(D!B1:B8,)} -> #NUM! | B26: =IF(ISERROR(A26),ERROR.TYPE(A26),IF(ISNUMBER(A26),0,IF(ISLOGICAL(A26),IF(A26,-1,-2),IF(ISTEXT(A26),-3,-4)))) -> 6 | C26: =IF(ISNUMBER(A26),A26,0) -> 0 | D26: =IF(ISTEXT(A26),A26,"") | E26: all:QUARTILE.EXC#5
A27: {=_xlfn.QUARTILE.EXC(D!B1:B8,0)} -> #NUM! | B27: =IF(ISERROR(A27),ERROR.TYPE(A27),IF(ISNUMBER(A27),0,IF(ISLOGICAL(A27),IF(A27,-1,-2),IF(ISTEXT(A27),-3,-4)))) -> 6 | C27: =IF(ISNUMBER(A27),A27,0) -> 0 | D27: =IF(ISTEXT(A27),A27,"") | E27: all:QUARTILE.EXC#6
A28: {=_xlfn.QUARTILE.EXC(D!B1:B8,"")} -> #VALUE! | B28: =IF(ISERROR(A28),ERROR.TYPE(A28),IF(ISNUMBER(A28),0,IF(ISLOGICAL(A28),IF(A28,-1,-2),IF(ISTEXT(A28),-3,-4)))) -> 3 | C28: =IF(ISNUMBER(A28),A28,0) -> 0 | D28: =IF(ISTEXT(A28),A28,"") | E28: all:QUARTILE.EXC#7
A29: {=_xlfn.QUARTILE.EXC(D!B1:B8,FALSE)} -> #NUM! | B29: =IF(ISERROR(A29),ERROR.TYPE(A29),IF(ISNUMBER(A29),0,IF(ISLOGICAL(A29),IF(A29,-1,-2),IF(ISTEXT(A29),-3,-4)))) -> 6 | C29: =IF(ISNUMBER(A29),A29,0) -> 0 | D29: =IF(ISTEXT(A29),A29,"") | E29: all:QUARTILE.EXC#8
A30: {=_xlfn.QUARTILE.INC(,1)} -> 0 | B30: =IF(ISERROR(A30),ERROR.TYPE(A30),IF(ISNUMBER(A30),0,IF(ISLOGICAL(A30),IF(A30,-1,-2),IF(ISTEXT(A30),-3,-4)))) -> 0 | C30: =IF(ISNUMBER(A30),A30,0) -> 0 | D30: =IF(ISTEXT(A30),A30,"") | E30: all:QUARTILE.INC#1
A31: {=_xlfn.QUARTILE.INC(0,1)} -> 0 | B31: =IF(ISERROR(A31),ERROR.TYPE(A31),IF(ISNUMBER(A31),0,IF(ISLOGICAL(A31),IF(A31,-1,-2),IF(ISTEXT(A31),-3,-4)))) -> 0 | C31: =IF(ISNUMBER(A31),A31,0) -> 0 | D31: =IF(ISTEXT(A31),A31,"") | E31: all:QUARTILE.INC#2
A32: {=_xlfn.QUARTILE.INC("",1)} -> #VALUE! | B32: =IF(ISERROR(A32),ERROR.TYPE(A32),IF(ISNUMBER(A32),0,IF(ISLOGICAL(A32),IF(A32,-1,-2),IF(ISTEXT(A32),-3,-4)))) -> 3 | C32: =IF(ISNUMBER(A32),A32,0) -> 0 | D32: =IF(ISTEXT(A32),A32,"") | E32: all:QUARTILE.INC#3
A33: {=_xlfn.QUARTILE.INC(FALSE,1)} -> 0 | B33: =IF(ISERROR(A33),ERROR.TYPE(A33),IF(ISNUMBER(A33),0,IF(ISLOGICAL(A33),IF(A33,-1,-2),IF(ISTEXT(A33),-3,-4)))) -> 0 | C33: =IF(ISNUMBER(A33),A33,0) -> 0 | D33: =IF(ISTEXT(A33),A33,"") | E33: all:QUARTILE.INC#4
A34: {=_xlfn.QUARTILE.INC(D!B1:B8,)} -> -3.5 | B34: =IF(ISERROR(A34),ERROR.TYPE(A34),IF(ISNUMBER(A34),0,IF(ISLOGICAL(A34),IF(A34,-1,-2),IF(ISTEXT(A34),-3,-4)))) -> 0 | C34: =IF(ISNUMBER(A34),A34,0) -> -3.5 | D34: =IF(ISTEXT(A34),A34,"") | E34: all:QUARTILE.INC#5
A35: {=_xlfn.QUARTILE.INC(D!B1:B8,0)} -> -3.5 | B35: =IF(ISERROR(A35),ERROR.TYPE(A35),IF(ISNUMBER(A35),0,IF(ISLOGICAL(A35),IF(A35,-1,-2),IF(ISTEXT(A35),-3,-4)))) -> 0 | C35: =IF(ISNUMBER(A35),A35,0) -> -3.5 | D35: =IF(ISTEXT(A35),A35,"") | E35: all:QUARTILE.INC#6
A36: {=_xlfn.QUARTILE.INC(D!B1:B8,"")} -> #VALUE! | B36: =IF(ISERROR(A36),ERROR.TYPE(A36),IF(ISNUMBER(A36),0,IF(ISLOGICAL(A36),IF(A36,-1,-2),IF(ISTEXT(A36),-3,-4)))) -> 3 | C36: =IF(ISNUMBER(A36),A36,0) -> 0 | D36: =IF(ISTEXT(A36),A36,"") | E36: all:QUARTILE.INC#7
A37: {=_xlfn.QUARTILE.INC(D!B1:B8,FALSE)} -> -3.5 | B37: =IF(ISERROR(A37),ERROR.TYPE(A37),IF(ISNUMBER(A37),0,IF(ISLOGICAL(A37),IF(A37,-1,-2),IF(ISTEXT(A37),-3,-4)))) -> 0 | C37: =IF(ISNUMBER(A37),A37,0) -> -3.5 | D37: =IF(ISTEXT(A37),A37,"") | E37: all:QUARTILE.INC#8
A38: {=QUOTIENT(,2)} -> #N/A | B38: =IF(ISERROR(A38),ERROR.TYPE(A38),IF(ISNUMBER(A38),0,IF(ISLOGICAL(A38),IF(A38,-1,-2),IF(ISTEXT(A38),-3,-4)))) -> 7 | C38: =IF(ISNUMBER(A38),A38,0) -> 0 | D38: =IF(ISTEXT(A38),A38,"") | E38: all:QUOTIENT#1
A39: {=QUOTIENT(0,2)} -> 0 | B39: =IF(ISERROR(A39),ERROR.TYPE(A39),IF(ISNUMBER(A39),0,IF(ISLOGICAL(A39),IF(A39,-1,-2),IF(ISTEXT(A39),-3,-4)))) -> 0 | C39: =IF(ISNUMBER(A39),A39,0) -> 0 | D39: =IF(ISTEXT(A39),A39,"") | E39: all:QUOTIENT#2
A40: {=QUOTIENT("",2)} -> #VALUE! | B40: =IF(ISERROR(A40),ERROR.TYPE(A40),IF(ISNUMBER(A40),0,IF(ISLOGICAL(A40),IF(A40,-1,-2),IF(ISTEXT(A40),-3,-4)))) -> 3 | C40: =IF(ISNUMBER(A40),A40,0) -> 0 | D40: =IF(ISTEXT(A40),A40,"") | E40: all:QUOTIENT#3
A41: {=QUOTIENT(FALSE,2)} -> #VALUE! | B41: =IF(ISERROR(A41),ERROR.TYPE(A41),IF(ISNUMBER(A41),0,IF(ISLOGICAL(A41),IF(A41,-1,-2),IF(ISTEXT(A41),-3,-4)))) -> 3 | C41: =IF(ISNUMBER(A41),A41,0) -> 0 | D41: =IF(ISTEXT(A41),A41,"") | E41: all:QUOTIENT#4
A42: {=QUOTIENT(5,)} -> #N/A | B42: =IF(ISERROR(A42),ERROR.TYPE(A42),IF(ISNUMBER(A42),0,IF(ISLOGICAL(A42),IF(A42,-1,-2),IF(ISTEXT(A42),-3,-4)))) -> 7 | C42: =IF(ISNUMBER(A42),A42,0) -> 0 | D42: =IF(ISTEXT(A42),A42,"") | E42: all:QUOTIENT#5
A43: {=QUOTIENT(5,0)} -> #DIV/0! | B43: =IF(ISERROR(A43),ERROR.TYPE(A43),IF(ISNUMBER(A43),0,IF(ISLOGICAL(A43),IF(A43,-1,-2),IF(ISTEXT(A43),-3,-4)))) -> 2 | C43: =IF(ISNUMBER(A43),A43,0) -> 0 | D43: =IF(ISTEXT(A43),A43,"") | E43: all:QUOTIENT#6
A44: {=QUOTIENT(5,"")} -> #VALUE! | B44: =IF(ISERROR(A44),ERROR.TYPE(A44),IF(ISNUMBER(A44),0,IF(ISLOGICAL(A44),IF(A44,-1,-2),IF(ISTEXT(A44),-3,-4)))) -> 3 | C44: =IF(ISNUMBER(A44),A44,0) -> 0 | D44: =IF(ISTEXT(A44),A44,"") | E44: all:QUOTIENT#7
A45: {=QUOTIENT(5,FALSE)} -> #VALUE! | B45: =IF(ISERROR(A45),ERROR.TYPE(A45),IF(ISNUMBER(A45),0,IF(ISLOGICAL(A45),IF(A45,-1,-2),IF(ISTEXT(A45),-3,-4)))) -> 3 | C45: =IF(ISNUMBER(A45),A45,0) -> 0 | D45: =IF(ISTEXT(A45),A45,"") | E45: all:QUOTIENT#8
A46: {=RANK(,D!B1:B8)} -> #N/A | B46: =IF(ISERROR(A46),ERROR.TYPE(A46),IF(ISNUMBER(A46),0,IF(ISLOGICAL(A46),IF(A46,-1,-2),IF(ISTEXT(A46),-3,-4)))) -> 7 | C46: =IF(ISNUMBER(A46),A46,0) -> 0 | D46: =IF(ISTEXT(A46),A46,"") | E46: all:RANK#1
A47: {=RANK(0,D!B1:B8)} -> #N/A | B47: =IF(ISERROR(A47),ERROR.TYPE(A47),IF(ISNUMBER(A47),0,IF(ISLOGICAL(A47),IF(A47,-1,-2),IF(ISTEXT(A47),-3,-4)))) -> 7 | C47: =IF(ISNUMBER(A47),A47,0) -> 0 | D47: =IF(ISTEXT(A47),A47,"") | E47: all:RANK#2
A48: {=RANK("",D!B1:B8)} -> #VALUE! | B48: =IF(ISERROR(A48),ERROR.TYPE(A48),IF(ISNUMBER(A48),0,IF(ISLOGICAL(A48),IF(A48,-1,-2),IF(ISTEXT(A48),-3,-4)))) -> 3 | C48: =IF(ISNUMBER(A48),A48,0) -> 0 | D48: =IF(ISTEXT(A48),A48,"") | E48: all:RANK#3
A49: {=RANK(FALSE,D!B1:B8)} -> #N/A | B49: =IF(ISERROR(A49),ERROR.TYPE(A49),IF(ISNUMBER(A49),0,IF(ISLOGICAL(A49),IF(A49,-1,-2),IF(ISTEXT(A49),-3,-4)))) -> 7 | C49: =IF(ISNUMBER(A49),A49,0) -> 0 | D49: =IF(ISTEXT(A49),A49,"") | E49: all:RANK#4
A50: {=RANK(15,D!B1:B8)} -> 4 | B50: =IF(ISERROR(A50),ERROR.TYPE(A50),IF(ISNUMBER(A50),0,IF(ISLOGICAL(A50),IF(A50,-1,-2),IF(ISTEXT(A50),-3,-4)))) -> 0 | C50: =IF(ISNUMBER(A50),A50,0) -> 4 | D50: =IF(ISTEXT(A50),A50,"") | E50: all:RANK#5
A51: {=RANK(15,D!B1:B8,)} -> 4 | B51: =IF(ISERROR(A51),ERROR.TYPE(A51),IF(ISNUMBER(A51),0,IF(ISLOGICAL(A51),IF(A51,-1,-2),IF(ISTEXT(A51),-3,-4)))) -> 0 | C51: =IF(ISNUMBER(A51),A51,0) -> 4 | D51: =IF(ISTEXT(A51),A51,"") | E51: all:RANK#6
A52: {=RANK(15,D!B1:B8,0)} -> 4 | B52: =IF(ISERROR(A52),ERROR.TYPE(A52),IF(ISNUMBER(A52),0,IF(ISLOGICAL(A52),IF(A52,-1,-2),IF(ISTEXT(A52),-3,-4)))) -> 0 | C52: =IF(ISNUMBER(A52),A52,0) -> 4 | D52: =IF(ISTEXT(A52),A52,"") | E52: all:RANK#7
A53: {=RANK(15,D!B1:B8,"")} -> #VALUE! | B53: =IF(ISERROR(A53),ERROR.TYPE(A53),IF(ISNUMBER(A53),0,IF(ISLOGICAL(A53),IF(A53,-1,-2),IF(ISTEXT(A53),-3,-4)))) -> 3 | C53: =IF(ISNUMBER(A53),A53,0) -> 0 | D53: =IF(ISTEXT(A53),A53,"") | E53: all:RANK#8
A54: {=RANK(15,D!B1:B8,FALSE)} -> 4 | B54: =IF(ISERROR(A54),ERROR.TYPE(A54),IF(ISNUMBER(A54),0,IF(ISLOGICAL(A54),IF(A54,-1,-2),IF(ISTEXT(A54),-3,-4)))) -> 0 | C54: =IF(ISNUMBER(A54),A54,0) -> 4 | D54: =IF(ISTEXT(A54),A54,"") | E54: all:RANK#9
A55: {=_xlfn.RANK.AVG(,D!BE1:BE7)} -> #N/A | B55: =IF(ISERROR(A55),ERROR.TYPE(A55),IF(ISNUMBER(A55),0,IF(ISLOGICAL(A55),IF(A55,-1,-2),IF(ISTEXT(A55),-3,-4)))) -> 7 | C55: =IF(ISNUMBER(A55),A55,0) -> 0 | D55: =IF(ISTEXT(A55),A55,"") | E55: all:RANK.AVG#1
A56: {=_xlfn.RANK.AVG(0,D!BE1:BE7)} -> #N/A | B56: =IF(ISERROR(A56),ERROR.TYPE(A56),IF(ISNUMBER(A56),0,IF(ISLOGICAL(A56),IF(A56,-1,-2),IF(ISTEXT(A56),-3,-4)))) -> 7 | C56: =IF(ISNUMBER(A56),A56,0) -> 0 | D56: =IF(ISTEXT(A56),A56,"") | E56: all:RANK.AVG#2
A57: {=_xlfn.RANK.AVG("",D!BE1:BE7)} -> #VALUE! | B57: =IF(ISERROR(A57),ERROR.TYPE(A57),IF(ISNUMBER(A57),0,IF(ISLOGICAL(A57),IF(A57,-1,-2),IF(ISTEXT(A57),-3,-4)))) -> 3 | C57: =IF(ISNUMBER(A57),A57,0) -> 0 | D57: =IF(ISTEXT(A57),A57,"") | E57: all:RANK.AVG#3
A58: {=_xlfn.RANK.AVG(FALSE,D!BE1:BE7)} -> #N/A | B58: =IF(ISERROR(A58),ERROR.TYPE(A58),IF(ISNUMBER(A58),0,IF(ISLOGICAL(A58),IF(A58,-1,-2),IF(ISTEXT(A58),-3,-4)))) -> 7 | C58: =IF(ISNUMBER(A58),A58,0) -> 0 | D58: =IF(ISTEXT(A58),A58,"") | E58: all:RANK.AVG#4
A59: {=_xlfn.RANK.AVG(94,D!BE1:BE7)} -> 4 | B59: =IF(ISERROR(A59),ERROR.TYPE(A59),IF(ISNUMBER(A59),0,IF(ISLOGICAL(A59),IF(A59,-1,-2),IF(ISTEXT(A59),-3,-4)))) -> 0 | C59: =IF(ISNUMBER(A59),A59,0) -> 4 | D59: =IF(ISTEXT(A59),A59,"") | E59: all:RANK.AVG#5
A60: {=_xlfn.RANK.AVG(94,D!BE1:BE7,)} -> 4 | B60: =IF(ISERROR(A60),ERROR.TYPE(A60),IF(ISNUMBER(A60),0,IF(ISLOGICAL(A60),IF(A60,-1,-2),IF(ISTEXT(A60),-3,-4)))) -> 0 | C60: =IF(ISNUMBER(A60),A60,0) -> 4 | D60: =IF(ISTEXT(A60),A60,"") | E60: all:RANK.AVG#6
A61: {=_xlfn.RANK.AVG(94,D!BE1:BE7,0)} -> 4 | B61: =IF(ISERROR(A61),ERROR.TYPE(A61),IF(ISNUMBER(A61),0,IF(ISLOGICAL(A61),IF(A61,-1,-2),IF(ISTEXT(A61),-3,-4)))) -> 0 | C61: =IF(ISNUMBER(A61),A61,0) -> 4 | D61: =IF(ISTEXT(A61),A61,"") | E61: all:RANK.AVG#7
A62: {=_xlfn.RANK.AVG(94,D!BE1:BE7,"")} -> #VALUE! | B62: =IF(ISERROR(A62),ERROR.TYPE(A62),IF(ISNUMBER(A62),0,IF(ISLOGICAL(A62),IF(A62,-1,-2),IF(ISTEXT(A62),-3,-4)))) -> 3 | C62: =IF(ISNUMBER(A62),A62,0) -> 0 | D62: =IF(ISTEXT(A62),A62,"") | E62: all:RANK.AVG#8
A63: {=_xlfn.RANK.AVG(94,D!BE1:BE7,FALSE)} -> 4 | B63: =IF(ISERROR(A63),ERROR.TYPE(A63),IF(ISNUMBER(A63),0,IF(ISLOGICAL(A63),IF(A63,-1,-2),IF(ISTEXT(A63),-3,-4)))) -> 0 | C63: =IF(ISNUMBER(A63),A63,0) -> 4 | D63: =IF(ISTEXT(A63),A63,"") | E63: all:RANK.AVG#9
A64: {=_xlfn.RANK.EQ(,D!BE1:BE7)} -> #N/A | B64: =IF(ISERROR(A64),ERROR.TYPE(A64),IF(ISNUMBER(A64),0,IF(ISLOGICAL(A64),IF(A64,-1,-2),IF(ISTEXT(A64),-3,-4)))) -> 7 | C64: =IF(ISNUMBER(A64),A64,0) -> 0 | D64: =IF(ISTEXT(A64),A64,"") | E64: all:RANK.EQ#1
A65: {=_xlfn.RANK.EQ(0,D!BE1:BE7)} -> #N/A | B65: =IF(ISERROR(A65),ERROR.TYPE(A65),IF(ISNUMBER(A65),0,IF(ISLOGICAL(A65),IF(A65,-1,-2),IF(ISTEXT(A65),-3,-4)))) -> 7 | C65: =IF(ISNUMBER(A65),A65,0) -> 0 | D65: =IF(ISTEXT(A65),A65,"") | E65: all:RANK.EQ#2
A66: {=_xlfn.RANK.EQ("",D!BE1:BE7)} -> #VALUE! | B66: =IF(ISERROR(A66),ERROR.TYPE(A66),IF(ISNUMBER(A66),0,IF(ISLOGICAL(A66),IF(A66,-1,-2),IF(ISTEXT(A66),-3,-4)))) -> 3 | C66: =IF(ISNUMBER(A66),A66,0) -> 0 | D66: =IF(ISTEXT(A66),A66,"") | E66: all:RANK.EQ#3
A67: {=_xlfn.RANK.EQ(FALSE,D!BE1:BE7)} -> #N/A | B67: =IF(ISERROR(A67),ERROR.TYPE(A67),IF(ISNUMBER(A67),0,IF(ISLOGICAL(A67),IF(A67,-1,-2),IF(ISTEXT(A67),-3,-4)))) -> 7 | C67: =IF(ISNUMBER(A67),A67,0) -> 0 | D67: =IF(ISTEXT(A67),A67,"") | E67: all:RANK.EQ#4
A68: {=_xlfn.RANK.EQ(94,D!BE1:BE7)} -> 4 | B68: =IF(ISERROR(A68),ERROR.TYPE(A68),IF(ISNUMBER(A68),0,IF(ISLOGICAL(A68),IF(A68,-1,-2),IF(ISTEXT(A68),-3,-4)))) -> 0 | C68: =IF(ISNUMBER(A68),A68,0) -> 4 | D68: =IF(ISTEXT(A68),A68,"") | E68: all:RANK.EQ#5
A69: {=_xlfn.RANK.EQ(94,D!BE1:BE7,)} -> 4 | B69: =IF(ISERROR(A69),ERROR.TYPE(A69),IF(ISNUMBER(A69),0,IF(ISLOGICAL(A69),IF(A69,-1,-2),IF(ISTEXT(A69),-3,-4)))) -> 0 | C69: =IF(ISNUMBER(A69),A69,0) -> 4 | D69: =IF(ISTEXT(A69),A69,"") | E69: all:RANK.EQ#6
A70: {=_xlfn.RANK.EQ(94,D!BE1:BE7,0)} -> 4 | B70: =IF(ISERROR(A70),ERROR.TYPE(A70),IF(ISNUMBER(A70),0,IF(ISLOGICAL(A70),IF(A70,-1,-2),IF(ISTEXT(A70),-3,-4)))) -> 0 | C70: =IF(ISNUMBER(A70),A70,0) -> 4 | D70: =IF(ISTEXT(A70),A70,"") | E70: all:RANK.EQ#7
A71: {=_xlfn.RANK.EQ(94,D!BE1:BE7,"")} -> #VALUE! | B71: =IF(ISERROR(A71),ERROR.TYPE(A71),IF(ISNUMBER(A71),0,IF(ISLOGICAL(A71),IF(A71,-1,-2),IF(ISTEXT(A71),-3,-4)))) -> 3 | C71: =IF(ISNUMBER(A71),A71,0) -> 0 | D71: =IF(ISTEXT(A71),A71,"") | E71: all:RANK.EQ#8
A72: {=_xlfn.RANK.EQ(94,D!BE1:BE7,FALSE)} -> 4 | B72: =IF(ISERROR(A72),ERROR.TYPE(A72),IF(ISNUMBER(A72),0,IF(ISLOGICAL(A72),IF(A72,-1,-2),IF(ISTEXT(A72),-3,-4)))) -> 0 | C72: =IF(ISNUMBER(A72),A72,0) -> 4 | D72: =IF(ISTEXT(A72),A72,"") | E72: all:RANK.EQ#9
A73: {=RATE(,-200,8000)} -> #NUM! | B73: =IF(ISERROR(A73),ERROR.TYPE(A73),IF(ISNUMBER(A73),0,IF(ISLOGICAL(A73),IF(A73,-1,-2),IF(ISTEXT(A73),-3,-4)))) -> 6 | C73: =IF(ISNUMBER(A73),A73,0) -> 0 | D73: =IF(ISTEXT(A73),A73,"") | E73: all:RATE#1
A74: {=RATE(0,-200,8000)} -> #NUM! | B74: =IF(ISERROR(A74),ERROR.TYPE(A74),IF(ISNUMBER(A74),0,IF(ISLOGICAL(A74),IF(A74,-1,-2),IF(ISTEXT(A74),-3,-4)))) -> 6 | C74: =IF(ISNUMBER(A74),A74,0) -> 0 | D74: =IF(ISTEXT(A74),A74,"") | E74: all:RATE#2
A75: {=RATE("",-200,8000)} -> #VALUE! | B75: =IF(ISERROR(A75),ERROR.TYPE(A75),IF(ISNUMBER(A75),0,IF(ISLOGICAL(A75),IF(A75,-1,-2),IF(ISTEXT(A75),-3,-4)))) -> 3 | C75: =IF(ISNUMBER(A75),A75,0) -> 0 | D75: =IF(ISTEXT(A75),A75,"") | E75: all:RATE#3
A76: {=RATE(FALSE,-200,8000)} -> #NUM! | B76: =IF(ISERROR(A76),ERROR.TYPE(A76),IF(ISNUMBER(A76),0,IF(ISLOGICAL(A76),IF(A76,-1,-2),IF(ISTEXT(A76),-3,-4)))) -> 6 | C76: =IF(ISNUMBER(A76),A76,0) -> 0 | D76: =IF(ISTEXT(A76),A76,"") | E76: all:RATE#4
A77: {=RATE(48,,8000)} -> #NUM! | B77: =IF(ISERROR(A77),ERROR.TYPE(A77),IF(ISNUMBER(A77),0,IF(ISLOGICAL(A77),IF(A77,-1,-2),IF(ISTEXT(A77),-3,-4)))) -> 6 | C77: =IF(ISNUMBER(A77),A77,0) -> 0 | D77: =IF(ISTEXT(A77),A77,"") | E77: all:RATE#5
A78: {=RATE(48,0,8000)} -> #NUM! | B78: =IF(ISERROR(A78),ERROR.TYPE(A78),IF(ISNUMBER(A78),0,IF(ISLOGICAL(A78),IF(A78,-1,-2),IF(ISTEXT(A78),-3,-4)))) -> 6 | C78: =IF(ISNUMBER(A78),A78,0) -> 0 | D78: =IF(ISTEXT(A78),A78,"") | E78: all:RATE#6
A79: {=RATE(48,"",8000)} -> #VALUE! | B79: =IF(ISERROR(A79),ERROR.TYPE(A79),IF(ISNUMBER(A79),0,IF(ISLOGICAL(A79),IF(A79,-1,-2),IF(ISTEXT(A79),-3,-4)))) -> 3 | C79: =IF(ISNUMBER(A79),A79,0) -> 0 | D79: =IF(ISTEXT(A79),A79,"") | E79: all:RATE#7
A80: {=RATE(48,FALSE,8000)} -> #NUM! | B80: =IF(ISERROR(A80),ERROR.TYPE(A80),IF(ISNUMBER(A80),0,IF(ISLOGICAL(A80),IF(A80,-1,-2),IF(ISTEXT(A80),-3,-4)))) -> 6 | C80: =IF(ISNUMBER(A80),A80,0) -> 0 | D80: =IF(ISTEXT(A80),A80,"") | E80: all:RATE#8
A81: {=RATE(48,-200,)} -> #NUM! | B81: =IF(ISERROR(A81),ERROR.TYPE(A81),IF(ISNUMBER(A81),0,IF(ISLOGICAL(A81),IF(A81,-1,-2),IF(ISTEXT(A81),-3,-4)))) -> 6 | C81: =IF(ISNUMBER(A81),A81,0) -> 0 | D81: =IF(ISTEXT(A81),A81,"") | E81: all:RATE#9
A82: {=RATE(48,-200,0)} -> #NUM! | B82: =IF(ISERROR(A82),ERROR.TYPE(A82),IF(ISNUMBER(A82),0,IF(ISLOGICAL(A82),IF(A82,-1,-2),IF(ISTEXT(A82),-3,-4)))) -> 6 | C82: =IF(ISNUMBER(A82),A82,0) -> 0 | D82: =IF(ISTEXT(A82),A82,"") | E82: all:RATE#10
A83: {=RATE(48,-200,"")} -> #VALUE! | B83: =IF(ISERROR(A83),ERROR.TYPE(A83),IF(ISNUMBER(A83),0,IF(ISLOGICAL(A83),IF(A83,-1,-2),IF(ISTEXT(A83),-3,-4)))) -> 3 | C83: =IF(ISNUMBER(A83),A83,0) -> 0 | D83: =IF(ISTEXT(A83),A83,"") | E83: all:RATE#11
A84: {=RATE(48,-200,FALSE)} -> #NUM! | B84: =IF(ISERROR(A84),ERROR.TYPE(A84),IF(ISNUMBER(A84),0,IF(ISLOGICAL(A84),IF(A84,-1,-2),IF(ISTEXT(A84),-3,-4)))) -> 6 | C84: =IF(ISNUMBER(A84),A84,0) -> 0 | D84: =IF(ISTEXT(A84),A84,"") | E84: all:RATE#12
A85: {=RATE(48,-200,8000)} -> 0.0077014725 | B85: =IF(ISERROR(A85),ERROR.TYPE(A85),IF(ISNUMBER(A85),0,IF(ISLOGICAL(A85),IF(A85,-1,-2),IF(ISTEXT(A85),-3,-4)))) -> 0 | C85: =IF(ISNUMBER(A85),A85,0) -> 0.0077014725 | D85: =IF(ISTEXT(A85),A85,"") | E85: all:RATE#13
A86: {=RATE(48,-200,8000,)} -> 0.0077014725 | B86: =IF(ISERROR(A86),ERROR.TYPE(A86),IF(ISNUMBER(A86),0,IF(ISLOGICAL(A86),IF(A86,-1,-2),IF(ISTEXT(A86),-3,-4)))) -> 0 | C86: =IF(ISNUMBER(A86),A86,0) -> 0.0077014725 | D86: =IF(ISTEXT(A86),A86,"") | E86: all:RATE#14
A87: {=RATE(48,-200,8000,0)} -> 0.0077014725 | B87: =IF(ISERROR(A87),ERROR.TYPE(A87),IF(ISNUMBER(A87),0,IF(ISLOGICAL(A87),IF(A87,-1,-2),IF(ISTEXT(A87),-3,-4)))) -> 0 | C87: =IF(ISNUMBER(A87),A87,0) -> 0.0077014725 | D87: =IF(ISTEXT(A87),A87,"") | E87: all:RATE#15
A88: {=RATE(48,-200,8000,"")} -> #VALUE! | B88: =IF(ISERROR(A88),ERROR.TYPE(A88),IF(ISNUMBER(A88),0,IF(ISLOGICAL(A88),IF(A88,-1,-2),IF(ISTEXT(A88),-3,-4)))) -> 3 | C88: =IF(ISNUMBER(A88),A88,0) -> 0 | D88: =IF(ISTEXT(A88),A88,"") | E88: all:RATE#16
A89: {=RATE(48,-200,8000,FALSE)} -> 0.0077014725 | B89: =IF(ISERROR(A89),ERROR.TYPE(A89),IF(ISNUMBER(A89),0,IF(ISLOGICAL(A89),IF(A89,-1,-2),IF(ISTEXT(A89),-3,-4)))) -> 0 | C89: =IF(ISNUMBER(A89),A89,0) -> 0.0077014725 | D89: =IF(ISTEXT(A89),A89,"") | E89: all:RATE#17
A90: {=RECEIVED(,DATE(2008,5,15),1000000,0.0575,2)} -> #N/A | B90: =IF(ISERROR(A90),ERROR.TYPE(A90),IF(ISNUMBER(A90),0,IF(ISLOGICAL(A90),IF(A90,-1,-2),IF(ISTEXT(A90),-3,-4)))) -> 7 | C90: =IF(ISNUMBER(A90),A90,0) -> 0 | D90: =IF(ISTEXT(A90),A90,"") | E90: all:RECEIVED#1
A91: {=RECEIVED(0,DATE(2008,5,15),1000000,0.0575,2)} -> #NUM! | B91: =IF(ISERROR(A91),ERROR.TYPE(A91),IF(ISNUMBER(A91),0,IF(ISLOGICAL(A91),IF(A91,-1,-2),IF(ISTEXT(A91),-3,-4)))) -> 6 | C91: =IF(ISNUMBER(A91),A91,0) -> 0 | D91: =IF(ISTEXT(A91),A91,"") | E91: all:RECEIVED#2
A92: {=RECEIVED("",DATE(2008,5,15),1000000,0.0575,2)} -> #VALUE! | B92: =IF(ISERROR(A92),ERROR.TYPE(A92),IF(ISNUMBER(A92),0,IF(ISLOGICAL(A92),IF(A92,-1,-2),IF(ISTEXT(A92),-3,-4)))) -> 3 | C92: =IF(ISNUMBER(A92),A92,0) -> 0 | D92: =IF(ISTEXT(A92),A92,"") | E92: all:RECEIVED#3
A93: {=RECEIVED(FALSE,DATE(2008,5,15),1000000,0.0575,2)} -> #VALUE! | B93: =IF(ISERROR(A93),ERROR.TYPE(A93),IF(ISNUMBER(A93),0,IF(ISLOGICAL(A93),IF(A93,-1,-2),IF(ISTEXT(A93),-3,-4)))) -> 3 | C93: =IF(ISNUMBER(A93),A93,0) -> 0 | D93: =IF(ISTEXT(A93),A93,"") | E93: all:RECEIVED#4
A94: {=RECEIVED(DATE(2008,2,15),,1000000,0.0575,2)} -> #N/A | B94: =IF(ISERROR(A94),ERROR.TYPE(A94),IF(ISNUMBER(A94),0,IF(ISLOGICAL(A94),IF(A94,-1,-2),IF(ISTEXT(A94),-3,-4)))) -> 7 | C94: =IF(ISNUMBER(A94),A94,0) -> 0 | D94: =IF(ISTEXT(A94),A94,"") | E94: all:RECEIVED#5
A95: {=RECEIVED(DATE(2008,2,15),0,1000000,0.0575,2)} -> #NUM! | B95: =IF(ISERROR(A95),ERROR.TYPE(A95),IF(ISNUMBER(A95),0,IF(ISLOGICAL(A95),IF(A95,-1,-2),IF(ISTEXT(A95),-3,-4)))) -> 6 | C95: =IF(ISNUMBER(A95),A95,0) -> 0 | D95: =IF(ISTEXT(A95),A95,"") | E95: all:RECEIVED#6
A96: {=RECEIVED(DATE(2008,2,15),"",1000000,0.0575,2)} -> #VALUE! | B96: =IF(ISERROR(A96),ERROR.TYPE(A96),IF(ISNUMBER(A96),0,IF(ISLOGICAL(A96),IF(A96,-1,-2),IF(ISTEXT(A96),-3,-4)))) -> 3 | C96: =IF(ISNUMBER(A96),A96,0) -> 0 | D96: =IF(ISTEXT(A96),A96,"") | E96: all:RECEIVED#7
A97: {=RECEIVED(DATE(2008,2,15),FALSE,1000000,0.0575,2)} -> #VALUE! | B97: =IF(ISERROR(A97),ERROR.TYPE(A97),IF(ISNUMBER(A97),0,IF(ISLOGICAL(A97),IF(A97,-1,-2),IF(ISTEXT(A97),-3,-4)))) -> 3 | C97: =IF(ISNUMBER(A97),A97,0) -> 0 | D97: =IF(ISTEXT(A97),A97,"") | E97: all:RECEIVED#8
A98: {=RECEIVED(DATE(2008,2,15),DATE(2008,5,15),,0.0575,2)} -> #N/A | B98: =IF(ISERROR(A98),ERROR.TYPE(A98),IF(ISNUMBER(A98),0,IF(ISLOGICAL(A98),IF(A98,-1,-2),IF(ISTEXT(A98),-3,-4)))) -> 7 | C98: =IF(ISNUMBER(A98),A98,0) -> 0 | D98: =IF(ISTEXT(A98),A98,"") | E98: all:RECEIVED#9
A99: {=RECEIVED(DATE(2008,2,15),DATE(2008,5,15),0,0.0575,2)} -> #NUM! | B99: =IF(ISERROR(A99),ERROR.TYPE(A99),IF(ISNUMBER(A99),0,IF(ISLOGICAL(A99),IF(A99,-1,-2),IF(ISTEXT(A99),-3,-4)))) -> 6 | C99: =IF(ISNUMBER(A99),A99,0) -> 0 | D99: =IF(ISTEXT(A99),A99,"") | E99: all:RECEIVED#10
A100: {=RECEIVED(DATE(2008,2,15),DATE(2008,5,15),"",0.0575,2)} -> #VALUE! | B100: =IF(ISERROR(A100),ERROR.TYPE(A100),IF(ISNUMBER(A100),0,IF(ISLOGICAL(A100),IF(A100,-1,-2),IF(ISTEXT(A100),-3,-4)))) -> 3 | C100: =IF(ISNUMBER(A100),A100,0) -> 0 | D100: =IF(ISTEXT(A100),A100,"") | E100: all:RECEIVED#11
...
